{"ticker":"000852.SH","mode":"close","summary":{"schema_version":"1.0","ticker":"000852.SH","name":"中证一千","data_date":"2026-07-10","generated_at":"2026-07-11T04:21:57.907354Z","conclusion":"日线偏弱 0/4，周线偏弱 1/4。今日-1.2%，近5日-4.9%，成交额6918.1亿，量能平稳（量比1.0），价跌量增。MACD 零轴下、死叉区、柱扩大；RSI 中性偏弱；KDJ 中位死叉区。","conclusion_segments":[{"text":"日线","tone":"neutral"},{"text":"偏弱 0/4","tone":"risk"},{"text":"，周线","tone":"neutral"},{"text":"偏弱 1/4","tone":"risk"},{"text":"。今日","tone":"neutral"},{"text":"-1.2%","tone":"risk"},{"text":"，近5日","tone":"neutral"},{"text":"-4.9%","tone":"risk"},{"text":"，成交额6918.1亿","tone":"neutral"},{"text":"，","tone":"neutral"},{"text":"量能平稳（量比1.0）","tone":"neutral"},{"text":"，","tone":"neutral"},{"text":"价跌量增","tone":"orange"},{"text":"。MACD ","tone":"neutral"},{"text":"零轴下","tone":"risk"},{"text":"死叉区","tone":"risk"},{"text":"，柱扩大","tone":"risk"},{"text":"（DIF -59.344 DEA 4.642 柱-127.972）","tone":"neutral"},{"text":"；RSI ","tone":"neutral"},{"text":"中性偏弱","tone":"risk"},{"text":"（41.0）","tone":"neutral"},{"text":"；KDJ ","tone":"neutral"},{"text":"中位死叉区","tone":"risk"},{"text":"（K24 D31 J10）","tone":"neutral"},{"text":"。","tone":"neutral"}],"trend_score":-2,"signals":[{"type":"risk","text":"日线强弱：偏弱 0/4"},{"type":"risk","text":"日线 MACD：死叉区"},{"type":"neutral","text":"日线 RSI/KDJ：中性偏弱；中位死叉区"},{"type":"neutral","text":"量价：量能平稳，价跌量增"}],"key_levels":{"support":[8113.77],"resistance":[8278.13,8492.11,8515.17],"extended":{"support":[{"label":"整数关","value":6000.0},{"label":"整数关","value":5000.0},{"label":"整数关","value":4000.0}],"resistance":[{"label":"Fib 0.382","value":8367.6},{"label":"Fib 0.236","value":8606.19},{"label":"整数关","value":9000.0}],"high_20":8944.19,"low_20":7978.81,"high_120":8991.85,"low_120":7357.7}},"advice":{"text":"当前价约 8198.31。日线偏弱但短线已有超卖特征，杀跌后可能出现修复。支撑位参考 8113.77，压力位参考 8278.13 / 8492.11 / 8515.17。RSI 中性偏弱，KDJ 中位死叉区，BOLL 下轨附近。未重新站回关键均线前以观察为主，只考虑小仓试探，不把反弹当反转。主要风险：超跌/杀跌风险、常规波动。操作区间：回落到 8113.77 附近且缩量企稳，可观察低吸或补仓机会；反弹到 8278.13 附近若量价背离，可考虑减仓或止盈。建议仓位：0-2成，并随消息面、成交量和关键价位突破/跌破动态调整。","risk":"超跌/杀跌风险、常规波动","trend":"日线偏弱但短线已有超卖特征，杀跌后可能出现修复。","overbought_oversold":"RSI 中性偏弱，KDJ 中位死叉区，BOLL 下轨附近。","timing":"未重新站回关键均线前以观察为主，只考虑小仓试探，不把反弹当反转。","support":[8113.77],"resistance":[8278.13,8492.11,8515.17],"operation_range":"回落到 8113.77 附近且缩量企稳，可观察低吸或补仓机会；反弹到 8278.13 附近若量价背离，可考虑减仓或止盈。","suggested_position":"0-2成","source":"technical_fallback"},"disclaimer":"仅供研究复盘，不构成投资建议。","close":8198.3078,"pct_chg":-1.23,"pct_chg_5d":-4.9,"volume":30850360900,"vol_chg_pct":21.2,"vol_ratio":1.05,"source":"stock-market-intraday-daily/reports/daily/2026-07-10"},"analysis_view":{"schema_version":"1.0","ticker":"000852.SH","name":"中证一千","data_date":"2026-07-10","generated_at":"2026-07-11T04:21:57.907354Z","sections":[{"id":"conclusion","title":"综合结论","cards":[{"type":"summary","title":"核心判断","items":[{"label":"结论","value":"日线偏弱 0/4，周线偏弱 1/4。今日-1.2%，近5日-4.9%，成交额6918.1亿，量能平稳（量比1.0），价跌量增。MACD 零轴下、死叉区、柱扩大；RSI 中性偏弱；KDJ 中位死叉区。","tone":"risk"},{"label":"趋势评分","value":-2,"tone":"risk"},{"label":"数据日期","value":"2026-07-10","tone":"muted"}]},{"type":"signal_list","title":"信号摘要","items":[{"label":"risk","value":"日线强弱：偏弱 0/4","tone":"risk"},{"label":"risk","value":"日线 MACD：死叉区","tone":"risk"},{"label":"neutral","value":"日线 RSI/KDJ：中性偏弱；中位死叉区","tone":"neutral"},{"label":"neutral","value":"量价：量能平稳，价跌量增","tone":"neutral"}]},{"type":"metric_grid","title":"关键价位","items":[{"label":"支撑位","value":"8113.77","tone":"positive"},{"label":"压力位","value":"8278.13 / 8492.11 / 8515.17","tone":"risk"}]},{"type":"text","title":"综合操作建议","items":[{"label":"建议","value":"当前价约 8198.31。日线偏弱但短线已有超卖特征，杀跌后可能出现修复。支撑位参考 8113.77，压力位参考 8278.13 / 8492.11 / 8515.17。RSI 中性偏弱，KDJ 中位死叉区，BOLL 下轨附近。未重新站回关键均线前以观察为主，只考虑小仓试探，不把反弹当反转。主要风险：超跌/杀跌风险、常规波动。操作区间：回落到 8113.77 附近且缩量企稳，可观察低吸或补仓机会；反弹到 8278.13 附近若量价背离，可考虑减仓或止盈。建议仓位：0-2成，并随消息面、成交量和关键价位突破/跌破动态调整。","tone":"risk"},{"label":"仓位","value":"0-2成","tone":"neutral"},{"label":"区间","value":"回落到 8113.77 附近且缩量企稳，可观察低吸或补仓机会；反弹到 8278.13 附近若量价背离，可考虑减仓或止盈。","tone":"neutral"}]}]},{"id":"daily","title":"日线状态","cards":[{"type":"metric_grid","title":"价格与趋势","items":[{"label":"收盘","value":8198.3078,"tone":"neutral"},{"label":"涨跌幅","value":-1.2261,"tone":"neutral","unit":"%"},{"label":"强弱","value":"偏弱 0/4","tone":"risk"},{"label":"BOLL","value":"下轨附近 (上9039.58/中8576.68/下8113.77)","tone":"neutral"}]},{"type":"metric_grid","title":"均线","items":[{"label":"MA5","value":8278.1304,"tone":"neutral"},{"label":"MA10","value":8492.1083,"tone":"neutral"},{"label":"MA20","value":8576.677,"tone":"neutral"},{"label":"MA60","value":8515.1728,"tone":"neutral"}]},{"type":"metric_grid","title":"技术指标","items":[{"label":"MACD","value":"死叉区 (DIF -59.344)","tone":"risk"},{"label":"DIF","value":-59.3438,"tone":"neutral"},{"label":"DEA","value":4.6421,"tone":"neutral"},{"label":"HIST","value":-127.9719,"tone":"neutral"},{"label":"RSI14","value":"41.0 (中性偏弱)","tone":"risk"},{"label":"KDJ","value":"中位死叉区 (K 23.7 D 30.6 J 9.9)","tone":"risk"}]},{"type":"metric_grid","title":"量价关系","items":[{"label":"量比","value":"1.05","tone":"neutral"},{"label":"量能","value":"量能平稳 (量比1.05)","tone":"neutral"},{"label":"价量","value":"价跌量增","tone":"risk"},{"label":"换手","value":3.122,"tone":"neutral","unit":"%"}]}]},{"id":"weekly","title":"周线状态","cards":[{"type":"metric_grid","title":"周线趋势","items":[{"label":"周期","value":"未完成","tone":"muted"},{"label":"强弱","value":"偏弱 1/4","tone":"risk"},{"label":"MACD","value":"死叉区 (DIF 205.019)","tone":"risk"},{"label":"RSI14","value":"50.2 (中性偏强)","tone":"positive"},{"label":"KDJ","value":"中位死叉区 (K 48.5 D 58.0 J 29.4)","tone":"risk"}]},{"type":"signal_list","title":"风险提示","items":[{"label":"风险","value":"常规波动","tone":"neutral"}]}]}],"disclaimer":"仅供研究复盘，不构成投资建议。"},"chart_payload":{"schema_version":"1.0","ticker":"000852.SH","name":"中证一千","timeframe":"1d","candles":[{"date":"2025-06-17","open":6153.15,"high":6171.17,"low":6120.57,"close":6141.47,"volume":20842728000.0,"amount":260873532301.4,"turnover":2.1764,"pct_chg":-0.0975},{"date":"2025-06-18","open":6126.18,"high":6143.21,"low":6086.69,"close":6135.39,"volume":20410575500.0,"amount":256463608433.8,"turnover":2.131,"pct_chg":-0.099},{"date":"2025-06-19","open":6127.94,"high":6146.64,"low":6028.72,"close":6048.22,"volume":21221733600.0,"amount":270827079699.4,"turnover":2.2148,"pct_chg":-1.4206},{"date":"2025-06-20","open":6039.99,"high":6061.84,"low":5997.59,"close":5999.59,"volume":18085734200.0,"amount":226531986434.8,"turnover":1.8869,"pct_chg":-0.8041},{"date":"2025-06-23","open":5966.5,"high":6083.53,"low":5965.66,"close":6078.22,"volume":19355849000.0,"amount":239995084576.3,"turnover":2.0188,"pct_chg":1.3106},{"date":"2025-06-24","open":6082.74,"high":6194.67,"low":6082.74,"close":6194.67,"volume":23345340300.0,"amount":303658275673.7,"turnover":2.435,"pct_chg":1.9158},{"date":"2025-06-25","open":6196.15,"high":6282.11,"low":6194.15,"close":6276.16,"volume":24755632500.0,"amount":334997601175.6,"turnover":2.5818,"pct_chg":1.3156},{"date":"2025-06-26","open":6272.44,"high":6310.54,"low":6244.78,"close":6247.79,"volume":25424649500.0,"amount":343746329448.1,"turnover":2.6513,"pct_chg":-0.4521},{"date":"2025-06-27","open":6265.92,"high":6319.16,"low":6257.59,"close":6276.94,"volume":24856335200.0,"amount":330455014092.6,"turnover":2.5914,"pct_chg":0.4665},{"date":"2025-06-30","open":6297.08,"high":6358.03,"low":6292.51,"close":6356.18,"volume":23732297300.0,"amount":336221160415.2,"turnover":2.4727,"pct_chg":1.2625},{"date":"2025-07-01","open":6358.06,"high":6373.77,"low":6308.06,"close":6373.77,"volume":24353733000.0,"amount":334302458347.3,"turnover":2.5352,"pct_chg":0.2767},{"date":"2025-07-02","open":6358.87,"high":6358.87,"low":6285.0,"close":6309.48,"volume":23858090300.0,"amount":296643998872.1,"turnover":2.4836,"pct_chg":-1.0086},{"date":"2025-07-03","open":6306.75,"high":6349.14,"low":6295.23,"close":6342.64,"volume":21398076500.0,"amount":270492479384.7,"turnover":2.2276,"pct_chg":0.5255},{"date":"2025-07-04","open":6338.56,"high":6375.07,"low":6292.14,"close":6312.2,"volume":23813321000.0,"amount":304676921480.6,"turnover":2.4787,"pct_chg":-0.4799},{"date":"2025-07-07","open":6305.04,"high":6333.51,"low":6303.86,"close":6327.14,"volume":21047736100.0,"amount":264834579254.8,"turnover":2.1899,"pct_chg":0.2367},{"date":"2025-07-08","open":6321.55,"high":6408.11,"low":6318.52,"close":6407.7,"volume":23512558300.0,"amount":306816858617.1,"turnover":2.446,"pct_chg":1.2732},{"date":"2025-07-09","open":6412.14,"high":6431.09,"low":6375.08,"close":6390.47,"volume":23617558900.0,"amount":303195813288.7,"turnover":2.4571,"pct_chg":-0.2689},{"date":"2025-07-10","open":6385.21,"high":6427.74,"low":6367.66,"close":6406.57,"volume":24018338000.0,"amount":296726316907.6,"turnover":2.4986,"pct_chg":0.252},{"date":"2025-07-11","open":6411.31,"high":6487.44,"low":6388.4,"close":6461.1,"volume":28256128300.0,"amount":352065982159.2,"turnover":2.9394,"pct_chg":0.8512},{"date":"2025-07-14","open":6465.51,"high":6474.93,"low":6443.56,"close":6462.31,"volume":24205780100.0,"amount":302637448818.8,"turnover":2.5181,"pct_chg":0.0187},{"date":"2025-07-15","open":6452.0,"high":6472.53,"low":6381.56,"close":6442.83,"volume":26986941100.0,"amount":347377816360.1,"turnover":2.8066,"pct_chg":-0.3013},{"date":"2025-07-16","open":6440.52,"high":6487.83,"low":6433.51,"close":6462.06,"volume":22023002400.0,"amount":306082808216.7,"turnover":2.2904,"pct_chg":0.2985},{"date":"2025-07-17","open":6458.41,"high":6535.67,"low":6451.15,"close":6535.67,"volume":22783164600.0,"amount":325983691186.5,"turnover":2.3693,"pct_chg":1.1391},{"date":"2025-07-18","open":6546.36,"high":6563.82,"low":6521.5,"close":6552.07,"volume":23446171300.0,"amount":330217284922.4,"turnover":2.4382,"pct_chg":0.251},{"date":"2025-07-21","open":6557.25,"high":6614.61,"low":6555.04,"close":6612.26,"volume":27659155200.0,"amount":359907688649.3,"turnover":2.8759,"pct_chg":0.9186},{"date":"2025-07-22","open":6607.83,"high":6642.23,"low":6597.05,"close":6637.1,"volume":30165999400.0,"amount":395915308553.6,"turnover":3.1365,"pct_chg":0.3757},{"date":"2025-07-23","open":6634.12,"high":6667.86,"low":6594.48,"close":6607.22,"volume":29410927500.0,"amount":378330158758.8,"turnover":3.058,"pct_chg":-0.4502},{"date":"2025-07-24","open":6602.17,"high":6701.12,"low":6602.17,"close":6701.12,"volume":28541821900.0,"amount":374405610913.0,"turnover":2.9674,"pct_chg":1.4212},{"date":"2025-07-25","open":6708.08,"high":6716.7,"low":6674.54,"close":6706.61,"volume":26400479800.0,"amount":363139664173.9,"turnover":2.7442,"pct_chg":0.0819},{"date":"2025-07-28","open":6713.82,"high":6736.08,"low":6679.21,"close":6729.98,"volume":25274290400.0,"amount":359575849641.3,"turnover":2.6248,"pct_chg":0.3485},{"date":"2025-07-29","open":6724.31,"high":6773.88,"low":6684.16,"close":6773.88,"volume":25926123600.0,"amount":383703631543.7,"turnover":2.6921,"pct_chg":0.6524},{"date":"2025-07-30","open":6758.33,"high":6770.88,"low":6662.91,"close":6718.48,"volume":26817955900.0,"amount":392675091205.8,"turnover":2.7848,"pct_chg":-0.8179},{"date":"2025-07-31","open":6701.16,"high":6750.08,"low":6639.12,"close":6661.19,"volume":27013867700.0,"amount":401821827245.2,"turnover":2.8051,"pct_chg":-0.8528},{"date":"2025-08-01","open":6665.64,"high":6702.68,"low":6625.93,"close":6670.47,"volume":23248467000.0,"amount":349070970147.4,"turnover":2.4127,"pct_chg":0.1394},{"date":"2025-08-04","open":6637.84,"high":6739.73,"low":6631.12,"close":6739.69,"volume":21349152500.0,"amount":329554815219.1,"turnover":2.2156,"pct_chg":1.0377},{"date":"2025-08-05","open":6753.53,"high":6787.48,"low":6744.07,"close":6787.48,"volume":22372467700.0,"amount":348578384502.9,"turnover":2.3215,"pct_chg":0.709},{"date":"2025-08-06","open":6784.17,"high":6865.02,"low":6774.03,"close":6861.31,"volume":25813388800.0,"amount":399056054133.9,"turnover":2.6786,"pct_chg":1.0877},{"date":"2025-08-07","open":6864.45,"high":6876.5,"low":6813.77,"close":6862.15,"volume":26138960000.0,"amount":411411186262.3,"turnover":2.7122,"pct_chg":0.0123},{"date":"2025-08-08","open":6844.44,"high":6865.84,"low":6816.09,"close":6838.13,"volume":25146567100.0,"amount":381544614396.8,"turnover":2.608,"pct_chg":-0.35},{"date":"2025-08-11","open":6850.57,"high":6957.4,"low":6850.57,"close":6943.94,"volume":26097024100.0,"amount":401163366844.0,"turnover":2.7052,"pct_chg":1.5473},{"date":"2025-08-12","open":6943.67,"high":6963.8,"low":6894.85,"close":6963.61,"volume":26048986900.0,"amount":409922645283.8,"turnover":2.7002,"pct_chg":0.2833},{"date":"2025-08-13","open":6966.27,"high":7070.5,"low":6966.27,"close":7064.33,"volume":29465387400.0,"amount":471479346408.7,"turnover":3.0543,"pct_chg":1.4464},{"date":"2025-08-14","open":7072.9,"high":7077.81,"low":6957.4,"close":6976.49,"volume":31727293600.0,"amount":513604373008.8,"turnover":3.288,"pct_chg":-1.2435},{"date":"2025-08-15","open":6956.51,"high":7117.51,"low":6956.51,"close":7117.5,"volume":30400522600.0,"amount":492508504867.1,"turnover":3.1503,"pct_chg":2.0213},{"date":"2025-08-18","open":7158.53,"high":7267.98,"low":7143.07,"close":7237.6,"volume":37983126300.0,"amount":606867233382.2,"turnover":3.9336,"pct_chg":1.6874},{"date":"2025-08-19","open":7231.93,"high":7289.03,"low":7193.59,"close":7242.85,"volume":34087904500.0,"amount":558781044092.1,"turnover":3.5299,"pct_chg":0.0725},{"date":"2025-08-20","open":7212.97,"high":7305.46,"low":7166.99,"close":7305.46,"volume":32475150300.0,"amount":517521411018.5,"turnover":3.3628,"pct_chg":0.8645},{"date":"2025-08-21","open":7318.76,"high":7343.17,"low":7215.34,"close":7253.34,"volume":32682289100.0,"amount":516507411053.1,"turnover":3.3838,"pct_chg":-0.7134},{"date":"2025-08-22","open":7250.19,"high":7362.94,"low":7250.19,"close":7362.94,"volume":32680749200.0,"amount":527766039448.3,"turnover":3.3838,"pct_chg":1.511},{"date":"2025-08-25","open":7418.35,"high":7504.01,"low":7405.94,"close":7477.73,"volume":40845765500.0,"amount":660911467973.6,"turnover":4.2278,"pct_chg":1.559},{"date":"2025-08-26","open":7457.77,"high":7526.17,"low":7435.3,"close":7476.47,"volume":36368466100.0,"amount":573343123463.7,"turnover":3.7637,"pct_chg":-0.0169},{"date":"2025-08-27","open":7488.93,"high":7565.35,"low":7336.5,"close":7336.5,"volume":41675926500.0,"amount":672784131893.9,"turnover":4.3128,"pct_chg":-1.8721},{"date":"2025-08-28","open":7331.19,"high":7447.11,"low":7216.77,"close":7447.11,"volume":38146643500.0,"amount":631711691476.3,"turnover":3.9474,"pct_chg":1.5076},{"date":"2025-08-29","open":7449.86,"high":7477.2,"low":7380.83,"close":7438.68,"volume":32764088100.0,"amount":565058625663.1,"turnover":3.3895,"pct_chg":-0.1132},{"date":"2025-09-01","open":7475.0,"high":7502.59,"low":7424.34,"close":7501.15,"volume":32422071200.0,"amount":564568450678.9,"turnover":3.354,"pct_chg":0.8398},{"date":"2025-09-02","open":7498.44,"high":7499.6,"low":7258.59,"close":7313.88,"volume":35043585300.0,"amount":598514462449.8,"turnover":3.625,"pct_chg":-2.4965},{"date":"2025-09-03","open":7336.39,"high":7361.03,"low":7182.29,"close":7206.88,"volume":29028856800.0,"amount":486667166562.6,"turnover":3.0028,"pct_chg":-1.4631},{"date":"2025-09-04","open":7214.72,"high":7255.0,"low":6939.66,"close":7041.15,"volume":29762275400.0,"amount":488595037929.4,"turnover":3.0786,"pct_chg":-2.2995},{"date":"2025-09-05","open":7046.96,"high":7248.58,"low":7017.95,"close":7245.67,"volume":28276593100.0,"amount":458842754388.2,"turnover":2.9249,"pct_chg":2.9045},{"date":"2025-09-08","open":7257.33,"high":7321.16,"low":7220.59,"close":7311.03,"volume":30781328900.0,"amount":495541349344.0,"turnover":3.1838,"pct_chg":0.9022},{"date":"2025-09-09","open":7287.4,"high":7315.97,"low":7198.32,"close":7226.03,"volume":28244306100.0,"amount":431928802540.2,"turnover":2.9203,"pct_chg":-1.1627},{"date":"2025-09-10","open":7214.23,"high":7296.0,"low":7179.76,"close":7230.17,"volume":25267415800.0,"amount":396104754790.1,"turnover":2.6121,"pct_chg":0.0573},{"date":"2025-09-11","open":7215.93,"high":7399.89,"low":7161.28,"close":7399.89,"volume":29397514200.0,"amount":486236595199.9,"turnover":3.0391,"pct_chg":2.3474},{"date":"2025-09-12","open":7402.42,"high":7472.87,"low":7387.59,"close":7422.88,"volume":31583879300.0,"amount":508828451805.1,"turnover":3.2651,"pct_chg":0.3108},{"date":"2025-09-15","open":7445.5,"high":7454.3,"low":7404.5,"close":7415.57,"volume":30130776100.0,"amount":475104705371.8,"turnover":3.1145,"pct_chg":-0.0985},{"date":"2025-09-16","open":7426.41,"high":7487.07,"low":7364.73,"close":7483.63,"volume":30901059000.0,"amount":474734476789.6,"turnover":3.1942,"pct_chg":0.9178},{"date":"2025-09-17","open":7478.41,"high":7564.82,"low":7461.41,"close":7554.81,"volume":30170648500.0,"amount":493296275782.6,"turnover":3.1187,"pct_chg":0.9512},{"date":"2025-09-18","open":7552.23,"high":7665.97,"low":7393.18,"close":7476.4,"volume":39860010200.0,"amount":654022739891.2,"turnover":4.1188,"pct_chg":-1.0379},{"date":"2025-09-19","open":7473.02,"high":7520.92,"low":7405.29,"close":7438.19,"volume":29589587000.0,"amount":483203148485.4,"turnover":3.0565,"pct_chg":-0.5111},{"date":"2025-09-22","open":7457.89,"high":7489.48,"low":7418.46,"close":7489.48,"volume":27036260200.0,"amount":440515484560.2,"turnover":2.7921,"pct_chg":0.6895},{"date":"2025-09-23","open":7500.62,"high":7504.23,"low":7261.67,"close":7408.07,"volume":31326028000.0,"amount":503959593111.7,"turnover":3.235,"pct_chg":-1.087},{"date":"2025-09-24","open":7375.91,"high":7534.22,"low":7342.47,"close":7534.22,"volume":27891276100.0,"amount":494397619555.6,"turnover":2.8801,"pct_chg":1.7029},{"date":"2025-09-25","open":7521.32,"high":7563.08,"low":7487.12,"close":7506.51,"volume":26440371200.0,"amount":464745025578.9,"turnover":2.7303,"pct_chg":-0.3678},{"date":"2025-09-26","open":7476.94,"high":7516.11,"low":7396.58,"close":7397.59,"volume":25875025900.0,"amount":436863300985.5,"turnover":2.6704,"pct_chg":-1.451},{"date":"2025-09-29","open":7415.13,"high":7517.12,"low":7376.91,"close":7497.83,"volume":25868018400.0,"amount":419534690314.0,"turnover":2.6689,"pct_chg":1.3551},{"date":"2025-09-30","open":7525.62,"high":7592.91,"low":7524.92,"close":7574.96,"volume":25517378500.0,"amount":442639611194.1,"turnover":2.6326,"pct_chg":1.0287},{"date":"2025-10-09","open":7623.3,"high":7671.17,"low":7590.47,"close":7648.05,"volume":30349138000.0,"amount":530500291414.7,"turnover":3.1298,"pct_chg":0.9649},{"date":"2025-10-10","open":7608.29,"high":7621.98,"low":7513.17,"close":7533.82,"volume":29042992200.0,"amount":485703734784.3,"turnover":2.9946,"pct_chg":-1.4936},{"date":"2025-10-13","open":7250.58,"high":7535.21,"low":7250.58,"close":7519.76,"volume":28840041100.0,"amount":470990827391.5,"turnover":2.9735,"pct_chg":-0.1866},{"date":"2025-10-14","open":7580.39,"high":7611.83,"low":7342.6,"close":7373.15,"volume":30441201300.0,"amount":506690155148.9,"turnover":3.1387,"pct_chg":-1.9497},{"date":"2025-10-15","open":7384.01,"high":7484.05,"low":7315.48,"close":7483.45,"volume":24485396500.0,"amount":403797525523.9,"turnover":2.5245,"pct_chg":1.4959},{"date":"2025-10-16","open":7460.76,"high":7472.75,"low":7378.3,"close":7401.84,"volume":23464307000.0,"amount":374296521876.0,"turnover":2.4173,"pct_chg":-1.0906},{"date":"2025-10-17","open":7395.87,"high":7426.21,"low":7176.96,"close":7185.48,"volume":25432732500.0,"amount":383875372638.0,"turnover":2.6201,"pct_chg":-2.923},{"date":"2025-10-20","open":7259.49,"high":7301.99,"low":7196.28,"close":7239.18,"volume":21857967600.0,"amount":328445222616.7,"turnover":2.2508,"pct_chg":0.7474},{"date":"2025-10-21","open":7257.11,"high":7350.92,"low":7236.63,"close":7344.05,"volume":23725016500.0,"amount":348158794786.9,"turnover":2.443,"pct_chg":1.4485},{"date":"2025-10-22","open":7304.96,"high":7349.8,"low":7278.71,"close":7312.21,"volume":22732450300.0,"amount":332181328130.8,"turnover":2.3407,"pct_chg":-0.4335},{"date":"2025-10-23","open":7292.39,"high":7319.55,"low":7192.42,"close":7308.1,"volume":23156897600.0,"amount":328574781927.4,"turnover":2.3836,"pct_chg":-0.0562},{"date":"2025-10-24","open":7340.67,"high":7419.41,"low":7340.67,"close":7419.24,"volume":24555995300.0,"amount":397473067375.7,"turnover":2.5272,"pct_chg":1.5207},{"date":"2025-10-27","open":7483.3,"high":7511.41,"low":7430.62,"close":7495.38,"volume":26534474900.0,"amount":458169856647.9,"turnover":2.7263,"pct_chg":1.0264},{"date":"2025-10-28","open":7462.91,"high":7534.05,"low":7443.7,"close":7479.22,"volume":25180424900.0,"amount":431016068636.5,"turnover":2.5872,"pct_chg":-0.2156},{"date":"2025-10-29","open":7481.24,"high":7569.12,"low":7469.07,"close":7569.12,"volume":26584612900.0,"amount":439161754318.7,"turnover":2.7315,"pct_chg":1.2019},{"date":"2025-10-30","open":7560.6,"high":7569.16,"low":7476.7,"close":7485.08,"volume":29738526900.0,"amount":478507155180.5,"turnover":3.0559,"pct_chg":-1.1102},{"date":"2025-10-31","open":7480.66,"high":7583.03,"low":7480.66,"close":7506.67,"volume":29974520600.0,"amount":475587998227.9,"turnover":3.0802,"pct_chg":0.2884},{"date":"2025-11-03","open":7507.37,"high":7539.33,"low":7417.27,"close":7538.12,"volume":27824170500.0,"amount":432422773380.5,"turnover":2.8592,"pct_chg":0.4189},{"date":"2025-11-04","open":7523.64,"high":7523.64,"low":7387.38,"close":7435.73,"volume":25167741300.0,"amount":381678891758.6,"turnover":2.5862,"pct_chg":-1.3583},{"date":"2025-11-05","open":7332.1,"high":7490.9,"low":7332.1,"close":7464.86,"volume":25854817800.0,"amount":373351692087.5,"turnover":2.6568,"pct_chg":0.3918},{"date":"2025-11-06","open":7482.91,"high":7551.83,"low":7466.75,"close":7551.83,"volume":26361295900.0,"amount":405168970723.4,"turnover":2.7088,"pct_chg":1.165},{"date":"2025-11-07","open":7519.75,"high":7581.56,"low":7492.93,"close":7541.88,"volume":26788866400.0,"amount":419611056738.1,"turnover":2.7528,"pct_chg":-0.1318},{"date":"2025-11-10","open":7568.75,"high":7592.76,"low":7515.68,"close":7563.25,"volume":27436131700.0,"amount":433797531456.7,"turnover":2.8171,"pct_chg":0.2834},{"date":"2025-11-11","open":7579.91,"high":7598.99,"low":7530.14,"close":7540.79,"volume":26525073100.0,"amount":404867228036.5,"turnover":2.7236,"pct_chg":-0.297},{"date":"2025-11-12","open":7520.18,"high":7537.76,"low":7421.46,"close":7486.38,"volume":26696336300.0,"amount":390482493659.0,"turnover":2.7411,"pct_chg":-0.7216},{"date":"2025-11-13","open":7483.66,"high":7604.89,"low":7475.51,"close":7590.58,"volume":27563607300.0,"amount":420596449342.4,"turnover":2.8301,"pct_chg":1.3919},{"date":"2025-11-14","open":7527.83,"high":7591.32,"low":7502.76,"close":7502.76,"volume":27197278300.0,"amount":406292990194.2,"turnover":2.7921,"pct_chg":-1.157},{"date":"2025-11-17","open":7514.84,"high":7544.72,"low":7487.81,"close":7523.08,"volume":26115611800.0,"amount":391318349646.0,"turnover":2.6807,"pct_chg":0.2708},{"date":"2025-11-18","open":7508.53,"high":7521.66,"low":7412.28,"close":7448.1,"volume":27748040900.0,"amount":418065487002.4,"turnover":2.8482,"pct_chg":-0.9966},{"date":"2025-11-19","open":7438.14,"high":7471.73,"low":7348.04,"close":7387.21,"volume":23839382000.0,"amount":367172563737.6,"turnover":2.4471,"pct_chg":-0.8176},{"date":"2025-11-20","open":7429.7,"high":7439.04,"low":7332.32,"close":7340.41,"volume":22753609000.0,"amount":356711968727.4,"turnover":2.3353,"pct_chg":-0.6335},{"date":"2025-11-21","open":7235.33,"high":7274.33,"low":7067.7,"close":7067.7,"volume":28480069000.0,"amount":408671897438.1,"turnover":2.923,"pct_chg":-3.7152},{"date":"2025-11-24","open":7105.64,"high":7190.72,"low":7064.6,"close":7156.41,"volume":24065506200.0,"amount":368993404400.1,"turnover":2.4694,"pct_chg":1.2551},{"date":"2025-11-25","open":7195.1,"high":7311.73,"low":7194.77,"close":7249.95,"volume":24542942900.0,"amount":404174105411.0,"turnover":2.5183,"pct_chg":1.3071},{"date":"2025-11-26","open":7236.66,"high":7307.2,"low":7225.09,"close":7248.45,"volume":23177682400.0,"amount":376963938111.3,"turnover":2.3782,"pct_chg":-0.0207},{"date":"2025-11-27","open":7243.71,"high":7330.6,"low":7243.71,"close":7257.45,"volume":21127741200.0,"amount":365625943247.2,"turnover":2.1671,"pct_chg":0.1242},{"date":"2025-11-28","open":7257.17,"high":7334.21,"low":7239.85,"close":7334.21,"volume":20068050800.0,"amount":342185224996.4,"turnover":2.0584,"pct_chg":1.0576},{"date":"2025-12-01","open":7356.51,"high":7388.62,"low":7342.6,"close":7386.68,"volume":23441158300.0,"amount":392320297531.6,"turnover":2.4043,"pct_chg":0.7154},{"date":"2025-12-02","open":7364.2,"high":7364.2,"low":7299.27,"close":7313.18,"volume":20051247700.0,"amount":320218841083.3,"turnover":2.0567,"pct_chg":-0.9951},{"date":"2025-12-03","open":7312.67,"high":7324.21,"low":7220.98,"close":7248.27,"volume":21463340000.0,"amount":335034477208.3,"turnover":2.2015,"pct_chg":-0.8875},{"date":"2025-12-04","open":7246.86,"high":7269.9,"low":7185.91,"close":7248.66,"volume":19483925400.0,"amount":311315804959.7,"turnover":1.9984,"pct_chg":0.0053},{"date":"2025-12-05","open":7244.28,"high":7347.0,"low":7194.66,"close":7342.49,"volume":21572766300.0,"amount":352805657180.3,"turnover":2.2125,"pct_chg":1.2945},{"date":"2025-12-08","open":7359.49,"high":7446.19,"low":7359.49,"close":7423.05,"volume":24091899500.0,"amount":418474779432.4,"turnover":2.4708,"pct_chg":1.0971},{"date":"2025-12-09","open":7400.93,"high":7439.55,"low":7370.3,"close":7380.58,"volume":22849142800.0,"amount":392312852126.3,"turnover":2.3406,"pct_chg":-0.572},{"date":"2025-12-10","open":7367.49,"high":7421.42,"low":7332.05,"close":7408.24,"volume":21561113400.0,"amount":360245249692.5,"turnover":2.2086,"pct_chg":0.3748},{"date":"2025-12-11","open":7421.79,"high":7425.44,"low":7312.0,"close":7312.0,"volume":23402087300.0,"amount":381933822512.9,"turnover":2.3972,"pct_chg":-1.2992},{"date":"2025-12-12","open":7312.87,"high":7384.85,"low":7284.56,"close":7370.94,"volume":24352518300.0,"amount":422779414910.8,"turnover":2.4946,"pct_chg":0.8062},{"date":"2025-12-15","open":7324.48,"high":7375.61,"low":7305.83,"close":7309.08,"volume":22095769700.0,"amount":372658890926.0,"turnover":2.2397,"pct_chg":-0.8393},{"date":"2025-12-16","open":7302.16,"high":7302.16,"low":7143.61,"close":7181.62,"volume":23052600700.0,"amount":361621759667.3,"turnover":2.3367,"pct_chg":-1.7438},{"date":"2025-12-17","open":7178.31,"high":7303.38,"low":7149.02,"close":7288.74,"volume":22049877500.0,"amount":366263786190.1,"turnover":2.2349,"pct_chg":1.4916},{"date":"2025-12-18","open":7244.64,"high":7336.73,"low":7241.86,"close":7272.4,"volume":20004466200.0,"amount":348983557160.8,"turnover":2.0273,"pct_chg":-0.2241},{"date":"2025-12-19","open":7295.67,"high":7357.04,"low":7279.99,"close":7329.81,"volume":21920554700.0,"amount":362345403569.5,"turnover":2.2215,"pct_chg":0.7893},{"date":"2025-12-22","open":7363.06,"high":7433.43,"low":7363.06,"close":7408.35,"volume":22160188600.0,"amount":381186010909.5,"turnover":2.2346,"pct_chg":1.0716},{"date":"2025-12-23","open":7410.22,"high":7441.41,"low":7363.93,"close":7392.42,"volume":22428856600.0,"amount":397181525761.7,"turnover":2.2605,"pct_chg":-0.215},{"date":"2025-12-24","open":7391.56,"high":7513.25,"low":7386.49,"close":7506.38,"volume":21796145500.0,"amount":406286039967.0,"turnover":2.1965,"pct_chg":1.5416},{"date":"2025-12-25","open":7507.3,"high":7591.78,"low":7502.15,"close":7579.38,"volume":22874491700.0,"amount":434419255592.9,"turnover":2.3051,"pct_chg":0.9725},{"date":"2025-12-26","open":7575.93,"high":7644.84,"low":7550.01,"close":7605.53,"volume":26626161100.0,"amount":473665628418.3,"turnover":2.6831,"pct_chg":0.345},{"date":"2025-12-29","open":7606.44,"high":7637.91,"low":7574.77,"close":7594.16,"volume":26406479600.0,"amount":466873470411.6,"turnover":2.661,"pct_chg":-0.1495},{"date":"2025-12-30","open":7556.54,"high":7636.15,"low":7552.4,"close":7597.3,"volume":26333187400.0,"amount":468024130590.7,"turnover":2.6534,"pct_chg":0.0414},{"date":"2025-12-31","open":7606.65,"high":7619.22,"low":7560.72,"close":7595.28,"volume":24454923100.0,"amount":440672066748.3,"turnover":2.4639,"pct_chg":-0.0265},{"date":"2026-01-05","open":7639.54,"high":7753.96,"low":7623.75,"close":7753.88,"volume":30537472600.0,"amount":542230841526.3,"turnover":3.0761,"pct_chg":2.0881},{"date":"2026-01-06","open":7756.16,"high":7864.9,"low":7755.07,"close":7864.9,"volume":33116203400.0,"amount":580815076334.1,"turnover":3.3354,"pct_chg":1.4318},{"date":"2026-01-07","open":7881.84,"high":7939.75,"low":7864.14,"close":7906.42,"volume":31873436700.0,"amount":617917011024.8,"turnover":3.2102,"pct_chg":0.5279},{"date":"2026-01-08","open":7886.81,"high":7993.63,"low":7886.63,"close":7971.59,"volume":32556390800.0,"amount":605389117078.6,"turnover":3.279,"pct_chg":0.8243},{"date":"2026-01-09","open":7969.19,"high":8131.49,"low":7969.19,"close":8129.18,"volume":38104386900.0,"amount":705322959792.5,"turnover":3.8373,"pct_chg":1.977},{"date":"2026-01-12","open":8196.08,"high":8371.75,"low":8171.11,"close":8357.01,"volume":44722895400.0,"amount":827564717480.8,"turnover":4.5031,"pct_chg":2.8026},{"date":"2026-01-13","open":8381.04,"high":8381.04,"low":8177.63,"close":8203.13,"volume":45444450300.0,"amount":824652003313.7,"turnover":4.5757,"pct_chg":-1.8413},{"date":"2026-01-14","open":8204.28,"high":8415.1,"low":8154.24,"close":8257.17,"volume":48979835900.0,"amount":884281078762.4,"turnover":4.9317,"pct_chg":0.6588},{"date":"2026-01-15","open":8197.06,"high":8267.81,"low":8151.11,"close":8240.78,"volume":35335770800.0,"amount":638659733155.5,"turnover":3.5576,"pct_chg":-0.1986},{"date":"2026-01-16","open":8276.61,"high":8304.4,"low":8180.12,"close":8232.73,"volume":35253940500.0,"amount":633410677296.9,"turnover":3.5494,"pct_chg":-0.0976},{"date":"2026-01-19","open":8204.63,"high":8298.48,"low":8187.94,"close":8265.65,"volume":32669114900.0,"amount":581675794396.0,"turnover":3.2891,"pct_chg":0.3998},{"date":"2026-01-20","open":8271.78,"high":8300.05,"low":8104.92,"close":8182.75,"volume":33668913400.0,"amount":579037016860.8,"turnover":3.3898,"pct_chg":-1.0029},{"date":"2026-01-21","open":8138.68,"high":8289.13,"low":8136.92,"close":8247.68,"volume":32567636800.0,"amount":564720693794.3,"turnover":3.2789,"pct_chg":0.7935},{"date":"2026-01-22","open":8272.47,"high":8314.22,"low":8252.74,"close":8309.35,"volume":32856328100.0,"amount":571805715998.2,"turnover":3.3073,"pct_chg":0.7477},{"date":"2026-01-23","open":8331.77,"high":8478.56,"low":8323.35,"close":8470.74,"volume":39304302000.0,"amount":681947636157.7,"turnover":3.9561,"pct_chg":1.9424},{"date":"2026-01-26","open":8513.22,"high":8530.42,"low":8302.1,"close":8365.43,"volume":40342837500.0,"amount":703181530463.3,"turnover":4.0598,"pct_chg":-1.2432},{"date":"2026-01-27","open":8325.43,"high":8406.1,"low":8186.24,"close":8382.15,"volume":36565732800.0,"amount":630208311333.5,"turnover":3.6797,"pct_chg":0.1999},{"date":"2026-01-28","open":8392.75,"high":8432.62,"low":8334.68,"close":8399.79,"volume":34965829300.0,"amount":627356672599.6,"turnover":3.5187,"pct_chg":0.2105},{"date":"2026-01-29","open":8380.61,"high":8463.12,"low":8308.82,"close":8332.21,"volume":40198798200.0,"amount":677736377632.4,"turnover":4.0454,"pct_chg":-0.8046},{"date":"2026-01-30","open":8255.33,"high":8313.23,"low":8083.97,"close":8254.86,"volume":36491645100.0,"amount":596749295784.9,"turnover":3.6723,"pct_chg":-0.9283},{"date":"2026-02-02","open":8166.74,"high":8221.58,"low":7974.6,"close":7975.43,"volume":30832146700.0,"amount":498940799234.4,"turnover":3.102,"pct_chg":-3.3851},{"date":"2026-02-03","open":8058.76,"high":8210.05,"low":8023.24,"close":8209.1,"volume":29921845800.0,"amount":525759546405.2,"turnover":3.0087,"pct_chg":2.9299},{"date":"2026-02-04","open":8184.2,"high":8216.2,"low":8101.2,"close":8207.12,"volume":31646115000.0,"amount":516215155944.8,"turnover":3.182,"pct_chg":-0.0241},{"date":"2026-02-05","open":8121.51,"high":8154.56,"low":8027.62,"close":8068.08,"volume":27581682300.0,"amount":440964669773.2,"turnover":2.7753,"pct_chg":-1.6942},{"date":"2026-02-06","open":7980.47,"high":8152.32,"low":7950.01,"close":8051.57,"volume":28108356300.0,"amount":444590291967.1,"turnover":2.8283,"pct_chg":-0.2045},{"date":"2026-02-09","open":8177.29,"high":8235.15,"low":8149.65,"close":8233.78,"volume":28284816900.0,"amount":482557298731.6,"turnover":2.8461,"pct_chg":2.263},{"date":"2026-02-10","open":8246.22,"high":8274.14,"low":8199.51,"close":8250.3,"volume":29191625000.0,"amount":475050653321.2,"turnover":2.9373,"pct_chg":0.2007},{"date":"2026-02-11","open":8239.17,"high":8304.13,"low":8236.96,"close":8239.51,"volume":27323431200.0,"amount":438065440518.3,"turnover":2.7493,"pct_chg":-0.1307},{"date":"2026-02-12","open":8252.19,"high":8337.37,"low":8227.6,"close":8314.83,"volume":27759673600.0,"amount":467860009633.1,"turnover":2.7931,"pct_chg":0.9141},{"date":"2026-02-13","open":8272.88,"high":8323.72,"low":8200.15,"close":8204.83,"volume":26114631200.0,"amount":438924354792.7,"turnover":2.6276,"pct_chg":-1.323},{"date":"2026-02-24","open":8319.69,"high":8356.91,"low":8236.71,"close":8299.77,"volume":27947962000.0,"amount":469515616941.8,"turnover":2.8118,"pct_chg":1.1571},{"date":"2026-02-25","open":8320.61,"high":8449.76,"low":8310.33,"close":8426.33,"volume":33344734600.0,"amount":533140591769.5,"turnover":3.3546,"pct_chg":1.5249},{"date":"2026-02-26","open":8447.78,"high":8496.75,"low":8398.07,"close":8490.62,"volume":33314760800.0,"amount":571186057010.0,"turnover":3.3516,"pct_chg":0.7629},{"date":"2026-02-27","open":8434.1,"high":8561.3,"low":8433.72,"close":8560.84,"volume":31389956300.0,"amount":549574087530.8,"turnover":3.158,"pct_chg":0.8271},{"date":"2026-03-02","open":8464.27,"high":8535.81,"low":8393.93,"close":8476.97,"volume":37890628100.0,"amount":659006885198.7,"turnover":3.8108,"pct_chg":-0.9798},{"date":"2026-03-03","open":8495.95,"high":8510.85,"low":8128.3,"close":8142.45,"volume":39018957900.0,"amount":664863752043.2,"turnover":3.9241,"pct_chg":-3.9461},{"date":"2026-03-04","open":8039.59,"high":8228.9,"low":8039.59,"close":8094.52,"volume":32068956100.0,"amount":502701509918.0,"turnover":3.2246,"pct_chg":-0.5887},{"date":"2026-03-05","open":8235.37,"high":8243.83,"low":8121.38,"close":8171.12,"volume":31536018100.0,"amount":508728534261.8,"turnover":3.171,"pct_chg":0.9463},{"date":"2026-03-06","open":8120.49,"high":8273.68,"low":8115.48,"close":8248.86,"volume":29463326900.0,"amount":474128426842.7,"turnover":2.9625,"pct_chg":0.9514},{"date":"2026-03-09","open":8131.74,"high":8230.66,"low":7983.57,"close":8203.87,"volume":35630788700.0,"amount":568760663973.5,"turnover":3.5825,"pct_chg":-0.5454},{"date":"2026-03-10","open":8272.94,"high":8351.67,"low":8271.49,"close":8350.09,"volume":31168527300.0,"amount":533511444229.1,"turnover":3.1338,"pct_chg":1.7823},{"date":"2026-03-11","open":8356.09,"high":8394.12,"low":8334.33,"close":8363.53,"volume":32173733200.0,"amount":549266931144.7,"turnover":3.234,"pct_chg":0.1609},{"date":"2026-03-12","open":8357.35,"high":8388.63,"low":8267.39,"close":8335.91,"volume":32821274700.0,"amount":531966072601.4,"turnover":3.2979,"pct_chg":-0.3302},{"date":"2026-03-13","open":8297.91,"high":8350.92,"low":8196.37,"close":8214.29,"volume":33312302000.0,"amount":523300349106.4,"turnover":3.347,"pct_chg":-1.4589},{"date":"2026-03-16","open":8212.27,"high":8226.03,"low":8089.49,"close":8211.35,"volume":31153245800.0,"amount":489125149211.3,"turnover":3.1297,"pct_chg":-0.0358},{"date":"2026-03-17","open":8219.5,"high":8223.99,"low":8019.07,"close":8019.86,"volume":29972338000.0,"amount":452754327270.6,"turnover":3.0111,"pct_chg":-2.3321},{"date":"2026-03-18","open":8050.71,"high":8105.81,"low":7970.19,"close":8096.59,"volume":27089355400.0,"amount":419893070233.5,"turnover":2.7214,"pct_chg":0.9568},{"date":"2026-03-19","open":7988.87,"high":8008.39,"low":7874.26,"close":7909.23,"volume":28459109900.0,"amount":443807163446.1,"turnover":2.8588,"pct_chg":-2.3141},{"date":"2026-03-20","open":7943.41,"high":7996.16,"low":7781.58,"close":7783.43,"volume":29902296300.0,"amount":486114330316.8,"turnover":3.0036,"pct_chg":-1.5905},{"date":"2026-03-23","open":7632.97,"high":7712.04,"low":7357.7,"close":7409.11,"volume":34925621000.0,"amount":505938395297.6,"turnover":3.5076,"pct_chg":-4.8093},{"date":"2026-03-24","open":7538.7,"high":7601.88,"low":7361.79,"close":7600.86,"volume":29385508500.0,"amount":432416549029.6,"turnover":2.9512,"pct_chg":2.588},{"date":"2026-03-25","open":7654.78,"high":7781.2,"low":7654.78,"close":7751.18,"volume":30366881700.0,"amount":471082962176.8,"turnover":3.0497,"pct_chg":1.9777},{"date":"2026-03-26","open":7733.7,"high":7775.89,"low":7614.89,"close":7639.38,"volume":27345513300.0,"amount":404052687696.6,"turnover":2.7464,"pct_chg":-1.4424},{"date":"2026-03-27","open":7526.59,"high":7784.55,"low":7526.59,"close":7746.31,"volume":25889527400.0,"amount":403803691770.2,"turnover":2.5997,"pct_chg":1.3998},{"date":"2026-03-30","open":7664.64,"high":7774.85,"low":7618.96,"close":7767.93,"volume":26117412900.0,"amount":411973881300.1,"turnover":2.622,"pct_chg":0.2791},{"date":"2026-03-31","open":7741.96,"high":7789.24,"low":7618.19,"close":7619.85,"volume":25525579000.0,"amount":404652134124.8,"turnover":2.5626,"pct_chg":-1.9063},{"date":"2026-04-01","open":7767.88,"high":7786.76,"low":7692.01,"close":7764.15,"volume":25597564400.0,"amount":420061154056.5,"turnover":2.5694,"pct_chg":1.8938},{"date":"2026-04-02","open":7733.75,"high":7764.03,"low":7581.39,"close":7623.42,"volume":24684116100.0,"amount":388676703461.5,"turnover":2.4775,"pct_chg":-1.8126},{"date":"2026-04-03","open":7658.82,"high":7664.76,"low":7521.94,"close":7536.6,"volume":22368034900.0,"amount":354378845650.9,"turnover":2.245,"pct_chg":-1.1388},{"date":"2026-04-07","open":7556.28,"high":7640.51,"low":7554.41,"close":7606.02,"volume":21097435700.0,"amount":343772200425.7,"turnover":2.1164,"pct_chg":0.9211},{"date":"2026-04-08","open":7765.55,"high":7955.77,"low":7765.2,"close":7955.77,"volume":29788517200.0,"amount":520657875320.5,"turnover":2.9881,"pct_chg":4.5984},{"date":"2026-04-09","open":7881.8,"high":7959.07,"low":7872.47,"close":7921.45,"volume":26065017100.0,"amount":466353987595.2,"turnover":2.6147,"pct_chg":-0.4314},{"date":"2026-04-10","open":7981.62,"high":8059.76,"low":7981.62,"close":7998.23,"volume":26241528500.0,"amount":494992306540.9,"turnover":2.6316,"pct_chg":0.9693},{"date":"2026-04-13","open":7947.22,"high":8040.03,"low":7947.22,"close":8025.57,"volume":24984977300.0,"amount":452431894323.4,"turnover":2.5053,"pct_chg":0.3418},{"date":"2026-04-14","open":8088.05,"high":8144.76,"low":8059.38,"close":8144.76,"volume":26630582500.0,"amount":509465034836.6,"turnover":2.6704,"pct_chg":1.4851},{"date":"2026-04-15","open":8186.07,"high":8193.3,"low":8083.27,"close":8106.16,"volume":27384184600.0,"amount":520849253124.5,"turnover":2.7459,"pct_chg":-0.4739},{"date":"2026-04-16","open":8120.36,"high":8239.01,"low":8100.49,"close":8232.98,"volume":27958443300.0,"amount":504935058833.5,"turnover":2.8035,"pct_chg":1.5645},{"date":"2026-04-17","open":8225.73,"high":8333.22,"low":8223.71,"close":8307.44,"volume":28510344300.0,"amount":530440512312.1,"turnover":2.8592,"pct_chg":0.9043},{"date":"2026-04-20","open":8308.06,"high":8374.81,"low":8308.06,"close":8357.81,"volume":29202960400.0,"amount":559665065901.8,"turnover":2.9287,"pct_chg":0.6064},{"date":"2026-04-21","open":8331.59,"high":8358.12,"low":8270.16,"close":8351.16,"volume":27899621000.0,"amount":521902188211.7,"turnover":2.7974,"pct_chg":-0.0797},{"date":"2026-04-22","open":8317.28,"high":8482.15,"low":8317.28,"close":8481.24,"volume":28170553900.0,"amount":558389615169.7,"turnover":2.8245,"pct_chg":1.5577},{"date":"2026-04-23","open":8489.0,"high":8500.44,"low":8302.85,"close":8362.74,"volume":31979149200.0,"amount":623696526109.0,"turnover":3.2059,"pct_chg":-1.3972},{"date":"2026-04-24","open":8318.6,"high":8360.79,"low":8254.43,"close":8304.14,"volume":29374811800.0,"amount":566282031229.8,"turnover":2.9447,"pct_chg":-0.7007},{"date":"2026-04-27","open":8292.81,"high":8366.31,"low":8249.94,"close":8338.73,"volume":27706012400.0,"amount":544735960417.2,"turnover":2.7771,"pct_chg":0.4165},{"date":"2026-04-28","open":8307.69,"high":8316.27,"low":8187.24,"close":8226.69,"volume":28497044600.0,"amount":549201647095.7,"turnover":2.856,"pct_chg":-1.3435},{"date":"2026-04-29","open":8163.35,"high":8361.49,"low":8163.35,"close":8343.07,"volume":28909945600.0,"amount":557143418182.6,"turnover":2.8972,"pct_chg":1.4146},{"date":"2026-04-30","open":8345.25,"high":8402.36,"low":8324.29,"close":8381.95,"volume":29911511000.0,"amount":595981862152.1,"turnover":2.9989,"pct_chg":0.466},{"date":"2026-05-06","open":8462.02,"high":8610.88,"low":8462.02,"close":8574.56,"volume":33085337100.0,"amount":690961217003.3,"turnover":3.3169,"pct_chg":2.2979},{"date":"2026-05-07","open":8602.15,"high":8716.86,"low":8573.3,"close":8714.51,"volume":33247719000.0,"amount":687608424374.6,"turnover":3.3331,"pct_chg":1.6322},{"date":"2026-05-08","open":8655.13,"high":8760.19,"low":8651.06,"close":8741.15,"volume":32178154500.0,"amount":656747057093.8,"turnover":3.2258,"pct_chg":0.3057},{"date":"2026-05-11","open":8807.91,"high":8888.87,"low":8760.71,"close":8866.78,"volume":34480797200.0,"amount":742541492856.3,"turnover":3.4822,"pct_chg":1.4372},{"date":"2026-05-12","open":8880.41,"high":8881.9,"low":8749.72,"close":8821.89,"volume":32084927800.0,"amount":683458191309.9,"turnover":3.24,"pct_chg":-0.5063},{"date":"2026-05-13","open":8764.02,"high":8958.46,"low":8764.02,"close":8955.45,"volume":31915270600.0,"amount":677186620719.2,"turnover":3.2228,"pct_chg":1.514},{"date":"2026-05-14","open":8989.49,"high":8991.85,"low":8778.71,"close":8778.71,"volume":35634417700.0,"amount":730969710799.2,"turnover":3.5984,"pct_chg":-1.9735},{"date":"2026-05-15","open":8786.38,"high":8846.52,"low":8616.06,"close":8682.65,"volume":35570731700.0,"amount":730238194125.1,"turnover":3.591,"pct_chg":-1.0942},{"date":"2026-05-18","open":8645.76,"high":8766.31,"low":8610.74,"close":8720.21,"volume":30042067200.0,"amount":628497008229.2,"turnover":3.0317,"pct_chg":0.4326},{"date":"2026-05-19","open":8691.38,"high":8812.03,"low":8602.05,"close":8808.64,"volume":29921984500.0,"amount":628935613994.7,"turnover":3.0193,"pct_chg":1.0141},{"date":"2026-05-20","open":8769.1,"high":8823.68,"low":8697.4,"close":8808.91,"volume":30671918800.0,"amount":653945996335.4,"turnover":3.094,"pct_chg":0.003},{"date":"2026-05-21","open":8852.43,"high":8896.6,"low":8500.92,"close":8510.5,"volume":35003795100.0,"amount":744490227370.2,"turnover":3.5289,"pct_chg":-3.3876},{"date":"2026-05-22","open":8578.9,"high":8719.39,"low":8521.7,"close":8692.67,"volume":28681240700.0,"amount":613491387497.9,"turnover":2.8911,"pct_chg":2.1405},{"date":"2026-05-25","open":8756.46,"high":8802.95,"low":8670.72,"close":8799.31,"volume":30289600600.0,"amount":668583970114.9,"turnover":3.0527,"pct_chg":1.2269},{"date":"2026-05-26","open":8755.91,"high":8756.46,"low":8560.8,"close":8687.25,"volume":31437355100.0,"amount":681153504048.6,"turnover":3.1682,"pct_chg":-1.2735},{"date":"2026-05-27","open":8679.54,"high":8737.05,"low":8495.72,"close":8546.51,"volume":31311235400.0,"amount":668282707862.7,"turnover":3.1552,"pct_chg":-1.6201},{"date":"2026-05-28","open":8527.91,"high":8659.61,"low":8459.95,"close":8637.74,"volume":30074765000.0,"amount":636606110725.9,"turnover":3.0304,"pct_chg":1.0674},{"date":"2026-05-29","open":8673.8,"high":8680.27,"low":8357.8,"close":8408.74,"volume":33278021700.0,"amount":705660466956.9,"turnover":3.3511,"pct_chg":-2.6512},{"date":"2026-06-01","open":8393.52,"high":8504.98,"low":8339.35,"close":8345.13,"volume":30570642300.0,"amount":607633321058.7,"turnover":3.076,"pct_chg":-0.7564},{"date":"2026-06-02","open":8360.81,"high":8440.23,"low":8219.15,"close":8384.78,"volume":29277785300.0,"amount":589657282873.4,"turnover":2.9442,"pct_chg":0.4752},{"date":"2026-06-03","open":8386.86,"high":8549.25,"low":8357.46,"close":8432.68,"volume":31829116600.0,"amount":688232619745.6,"turnover":3.1997,"pct_chg":0.5712},{"date":"2026-06-04","open":8338.85,"high":8456.02,"low":8338.85,"close":8420.09,"volume":28617360900.0,"amount":599542777865.6,"turnover":2.8765,"pct_chg":-0.1492},{"date":"2026-06-05","open":8380.85,"high":8500.1,"low":8305.4,"close":8340.96,"volume":31495357600.0,"amount":664778756146.5,"turnover":3.1656,"pct_chg":-0.9398},{"date":"2026-06-08","open":8069.48,"high":8260.19,"low":7987.4,"close":8081.26,"volume":30353698500.0,"amount":603155103799.4,"turnover":3.0509,"pct_chg":-3.1136},{"date":"2026-06-09","open":8178.82,"high":8322.11,"low":8096.58,"close":8318.7,"volume":29309759700.0,"amount":602773097270.3,"turnover":2.9458,"pct_chg":2.9381},{"date":"2026-06-10","open":8232.02,"high":8285.29,"low":8103.01,"close":8198.72,"volume":28684456600.0,"amount":582026561181.5,"turnover":2.8828,"pct_chg":-1.4422},{"date":"2026-06-11","open":8158.46,"high":8223.53,"low":8084.9,"close":8159.45,"volume":27116395300.0,"amount":577080601080.8,"turnover":2.725,"pct_chg":-0.479},{"date":"2026-06-12","open":8294.9,"high":8348.79,"low":8181.42,"close":8202.8,"volume":32859908500.0,"amount":717319013093.1,"turnover":3.3012,"pct_chg":0.5312},{"date":"2026-06-15","open":8269.4,"high":8521.23,"low":8269.4,"close":8521.23,"volume":29601206700.0,"amount":640124261587.0,"turnover":3.0043,"pct_chg":3.882},{"date":"2026-06-16","open":8534.27,"high":8684.65,"low":8508.91,"close":8646.4,"volume":29802260700.0,"amount":683488867028.9,"turnover":3.0247,"pct_chg":1.4689},{"date":"2026-06-17","open":8581.65,"high":8705.4,"low":8581.65,"close":8704.47,"volume":28222793700.0,"amount":658867267024.3,"turnover":2.8624,"pct_chg":0.6715},{"date":"2026-06-18","open":8666.64,"high":8796.48,"low":8664.28,"close":8771.02,"volume":29006243500.0,"amount":680473865688.9,"turnover":2.9411,"pct_chg":0.7646},{"date":"2026-06-22","open":8813.72,"high":8865.81,"low":8609.61,"close":8865.68,"volume":33571821000.0,"amount":786541007010.9,"turnover":3.4023,"pct_chg":1.0791},{"date":"2026-06-23","open":8838.76,"high":8862.72,"low":8626.1,"close":8680.04,"volume":30395487800.0,"amount":707484276759.0,"turnover":3.0799,"pct_chg":-2.0939},{"date":"2026-06-24","open":8650.82,"high":8803.5,"low":8581.75,"close":8793.49,"volume":28686714500.0,"amount":680312177616.5,"turnover":2.9058,"pct_chg":1.307},{"date":"2026-06-25","open":8806.07,"high":8872.12,"low":8743.25,"close":8825.92,"volume":30544263800.0,"amount":729838211067.7,"turnover":3.0935,"pct_chg":0.3688},{"date":"2026-06-26","open":8771.6,"high":8797.28,"low":8563.69,"close":8601.41,"volume":32122765600.0,"amount":755464112293.4,"turnover":3.2529,"pct_chg":-2.5438},{"date":"2026-06-29","open":8616.42,"high":8677.63,"low":8413.86,"close":8597.89,"volume":30987102100.0,"amount":750058629128.5,"turnover":3.1375,"pct_chg":-0.0409},{"date":"2026-06-30","open":8574.25,"high":8815.11,"low":8547.31,"close":8809.79,"volume":27911736400.0,"amount":685381605223.9,"turnover":2.8258,"pct_chg":2.4645},{"date":"2026-07-01","open":8827.47,"high":8944.19,"low":8806.65,"close":8876.63,"volume":32576587100.0,"amount":782800133620.8,"turnover":3.2976,"pct_chg":0.7588},{"date":"2026-07-02","open":8688.29,"high":8865.97,"low":8598.87,"close":8625.33,"volume":31085890200.0,"amount":717867291622.4,"turnover":3.1467,"pct_chg":-2.831},{"date":"2026-07-03","open":8627.38,"high":8740.67,"low":8559.28,"close":8620.79,"volume":29024450800.0,"amount":674994834099.3,"turnover":2.9377,"pct_chg":-0.0527},{"date":"2026-07-06","open":8669.12,"high":8694.8,"low":8432.9,"close":8472.6,"volume":28122420800.0,"amount":655013068730.7,"turnover":2.8463,"pct_chg":-1.7189},{"date":"2026-07-07","open":8436.39,"high":8489.48,"low":8261.4,"close":8301.8,"volume":24457508200.0,"amount":544456254012.1,"turnover":2.4753,"pct_chg":-2.0159},{"date":"2026-07-08","open":8315.96,"high":8328.96,"low":8117.86,"close":8117.86,"volume":23828392600.0,"amount":527640623973.8,"turnover":2.4114,"pct_chg":-2.2157},{"date":"2026-07-09","open":8161.86,"high":8312.62,"low":7978.81,"close":8300.08,"volume":25457934400.0,"amount":580421702888.1,"turnover":2.5764,"pct_chg":2.2446},{"date":"2026-07-10","open":8312.49,"high":8438.19,"low":8198.31,"close":8198.31,"volume":30850360900.0,"amount":691814043743.9,"turnover":3.122,"pct_chg":-1.2261}],"indicators":{"ma":{"ma5":[6154.7338,6144.5085,6115.7094,6094.426,6080.5785,6091.218,6119.3735,6159.2868,6214.756,6270.3478,6306.1682,6312.8322,6331.8016,6338.8535,6333.045,6339.831,6356.0273,6368.8133,6398.5939,6425.6271,6432.6544,6446.9739,6472.7946,6490.9895,6520.9803,6559.8342,6588.8656,6621.9553,6652.8624,6676.4065,6703.7626,6726.015,6718.0282,6710.8007,6712.7436,6715.4629,6744.0283,6784.221,6817.7526,6858.6012,6893.8273,6934.4322,6957.2998,7013.174,7071.907,7127.7547,7175.9802,7231.3513,7280.439,7328.4642,7375.1878,7381.3963,7420.1497,7435.2971,7439.9812,7407.4642,7381.5387,7300.3475,7261.7456,7223.7228,7206.1518,7210.8102,7282.5564,7317.9999,7338.9073,7390.4274,7455.3563,7470.6596,7473.7205,7488.502,7473.3901,7469.2721,7475.2942,7467.1743,7468.8448,7502.2236,7524.9896,7530.4511,7554.886,7529.9503,7511.6474,7462.4045,7392.7361,7336.6203,7330.7992,7296.5514,7277.8037,7324.5551,7375.7949,7402.8297,7454.2111,7489.6082,7507.0961,7515.643,7506.945,7486.0942,7499.4433,7506.4839,7511.5111,7532.5231,7536.8258,7544.5751,7536.7508,7528.7153,7510.1772,7490.3436,7440.3107,7353.2999,7279.9665,7240.3358,7212.5839,7195.9923,7249.2936,7295.3482,7307.9943,7307.9594,7306.2,7307.8566,7315.1296,7328.6107,7360.6047,7373.2723,7378.9621,7356.1684,7316.3757,7292.4745,7284.556,7276.3288,7296.1831,7338.3431,7381.8717,7443.2671,7498.4119,7535.5737,7576.5494,7594.33,7629.2302,7681.1049,7743.5573,7818.4153,7925.195,8045.8211,8113.467,8183.6174,8237.4546,8258.1639,8239.891,8235.8149,8233.9165,8247.6306,8295.2335,8315.1912,8355.0714,8385.4942,8390.0664,8346.8897,8268.8885,8234.278,8195.7433,8142.9173,8102.2601,8153.9301,8162.1699,8168.6485,8217.9996,8248.6506,8261.849,8297.0553,8347.2762,8396.4784,8450.9055,8419.4422,8353.0795,8289.18,8226.7827,8172.1634,8213.6906,8267.4922,8300.4498,8293.537,8295.0336,8228.987,8175.6008,8090.2661,8004.0944,7843.6455,7759.8455,7690.7627,7636.7911,7629.3668,7701.1314,7704.9301,7707.5244,7704.3326,7662.3899,7630.0072,7697.1908,7728.6496,7803.6127,7901.4072,8009.1563,8039.2355,8101.5429,8163.3837,8229.832,8271.1108,8346.1258,8372.0772,8371.4182,8367.6007,8342.7079,8315.0729,8318.9142,8372.9971,8448.1538,8551.0456,8655.7884,8743.7766,8819.9549,8832.7947,8821.0953,8791.7821,8789.1335,8759.8259,8706.1833,8708.1857,8724.0054,8699.727,8647.248,8672.6974,8615.9115,8525.075,8464.5806,8441.8136,8398.2839,8384.7294,8331.9559,8318.7392,8271.948,8219.8201,8192.1873,8280.1816,8345.7227,8446.8716,8569.1855,8701.7609,8733.522,8762.9387,8787.2292,8753.3058,8699.7492,8725.6987,8742.3274,8702.2101,8706.0863,8681.0282,8579.4318,8427.6778,8362.6265,8278.1304],"ma10":[6159.7356,6160.957,6149.0779,6133.7526,6119.6785,6122.9759,6131.941,6137.4981,6154.591,6175.4631,6198.6931,6216.1029,6245.5442,6276.8048,6301.6964,6322.9996,6334.4298,6350.3075,6368.7237,6379.3361,6386.2427,6401.5006,6420.8039,6444.7917,6473.3037,6496.2443,6517.9197,6547.375,6571.926,6598.6934,6631.7984,6657.4403,6669.9918,6681.8316,6694.575,6709.6127,6735.0216,6751.1246,6764.2766,6785.6724,6804.6451,6839.2303,6870.7604,6915.4633,6965.2541,7010.791,7055.2062,7094.3255,7146.8065,7200.1856,7251.4712,7278.6882,7325.7505,7357.8681,7384.2227,7391.326,7381.4675,7360.2486,7348.5214,7331.852,7306.808,7296.1745,7291.452,7289.8727,7281.315,7298.2896,7333.0833,7376.608,7395.8602,7413.7046,7431.9088,7462.3142,7472.9769,7470.4474,7478.6734,7487.8069,7497.1308,7502.8727,7511.0302,7499.3975,7506.9355,7493.697,7461.5936,7445.7531,7430.3747,7404.0994,7370.1041,7358.6456,7356.2076,7366.8144,7375.3812,7383.706,7415.8256,7445.719,7454.8873,7470.1527,7494.5257,7506.79,7513.5771,7519.7341,7511.46,7522.0092,7521.6174,7520.1132,7521.3502,7513.5847,7492.4429,7445.0254,7404.3409,7375.2565,7351.4637,7318.1515,7301.2968,7287.6573,7274.1651,7260.2716,7251.0962,7278.5751,7305.2389,7318.3025,7334.282,7339.7361,7343.4093,7335.649,7322.4932,7326.5396,7328.9141,7327.6455,7326.1757,7327.3594,7337.1731,7363.9115,7387.3704,7415.8784,7457.4463,7488.1009,7536.2486,7589.7584,7639.5655,7697.4823,7759.7625,7837.5257,7897.2859,7963.5873,8027.9349,8091.6794,8142.856,8174.6409,8208.7669,8242.5426,8276.6987,8277.5411,8295.4431,8309.7054,8318.8485,8321.0616,8292.0398,8294.6747,8290.6188,8266.4919,8224.5749,8211.4093,8198.224,8182.1959,8180.4584,8175.4554,8207.8896,8229.6126,8257.9623,8307.239,8349.7781,8340.6456,8325.0674,8318.2281,8311.6305,8311.5345,8316.5664,8310.2859,8294.8149,8260.1598,8233.5985,8221.3388,8221.5465,8195.358,8148.8157,8069.3395,7994.4162,7933.1817,7863.5286,7816.7306,7772.3885,7732.3878,7699.1436,7670.5618,7645.8783,7665.5693,7701.0605,7718.087,7753.9726,7781.8985,7819.5818,7868.2132,7915.0963,7983.4982,8065.6196,8140.1336,8192.6807,8236.8101,8267.401,8298.7164,8306.9093,8330.5994,8345.4957,8372.2077,8407.8773,8446.8767,8485.4307,8531.3454,8596.476,8640.4743,8686.0704,8723.7852,8766.455,8789.8904,8769.489,8764.6405,8757.8937,8744.4303,8703.5369,8689.4404,8662.0486,8624.5402,8582.1538,8544.5308,8535.4907,8500.3204,8428.5154,8391.6599,8356.8808,8309.052,8288.4583,8306.0687,8332.2309,8359.4098,8394.5028,8446.9741,8506.8518,8554.3307,8617.0504,8661.2457,8700.7551,8729.6103,8752.633,8744.7196,8729.6961,8690.3887,8652.5652,8585.0026,8532.4183,8492.1083],"ma20":[6106.9604,6106.4289,6102.2311,6098.9055,6103.3328,6111.6268,6125.012,6138.1788,6147.5467,6164.0278,6179.2143,6188.5299,6197.3111,6205.2787,6210.6874,6222.9877,6233.1854,6243.9028,6261.6573,6277.3996,6292.4679,6308.8017,6333.1741,6360.7982,6387.5001,6409.6219,6426.1748,6448.8412,6470.3248,6489.0147,6509.0205,6529.4704,6545.3979,6563.3116,6583.9394,6602.9285,6626.4707,6649.2498,6668.1013,6692.1829,6718.2217,6748.3353,6770.3761,6798.6474,6829.9146,6860.2019,6895.1139,6922.7251,6955.5416,6992.929,7028.0582,7058.9592,7098.2554,7136.6657,7174.7384,7201.0585,7218.3368,7227.2871,7247.6639,7266.0188,7279.1396,7287.4313,7308.6012,7323.8704,7332.7689,7344.8078,7357.2754,7368.4283,7372.1908,7372.7783,7369.3584,7379.2443,7382.2144,7380.1601,7379.9942,7393.0482,7415.1071,7439.7404,7453.4452,7456.5511,7469.4221,7478.0056,7467.2853,7458.1003,7454.524,7445.9531,7433.6175,7430.7591,7433.6189,7433.106,7441.1584,7438.7015,7438.7096,7445.736,7442.631,7437.126,7432.3149,7432.7178,7434.8923,7443.2742,7443.4206,7452.8576,7468.7215,7482.9161,7488.1188,7491.8687,7493.4843,7475.9077,7458.959,7447.4953,7431.4619,7420.0803,7411.4571,7403.8852,7397.7576,7386.9282,7371.7695,7361.8002,7354.7899,7346.7795,7342.8729,7328.9438,7322.3531,7311.6532,7298.3291,7293.4056,7290.0051,7303.1103,7315.7073,7322.831,7335.7276,7351.8238,7365.3898,7375.7637,7389.9697,7407.3202,7432.5814,7458.7019,7482.8706,7512.4209,7548.4678,7600.7186,7642.3281,7689.7329,7742.6906,7789.8902,7839.5523,7882.1997,7924.1662,7970.0125,8018.2306,8057.5334,8096.3645,8136.6463,8173.3917,8206.3705,8217.4479,8234.6578,8249.6929,8254.5173,8250.6368,8244.4752,8246.8336,8245.9506,8249.6535,8248.2585,8249.9647,8262.1437,8274.2905,8286.8654,8287.1765,8276.0274,8261.6457,8250.212,8246.0445,8243.4949,8262.228,8269.9492,8276.3886,8283.6994,8291.6883,8280.9922,8273.3069,8256.793,8230.2231,8190.437,8155.4913,8121.7338,8079.1717,8038.4452,8002.9935,7976.8633,7960.345,7932.9599,7897.347,7867.4544,7847.7384,7825.6344,7808.7506,7799.3146,7795.9851,7800.3005,7807.1199,7827.03,7855.749,7902.8514,7946.8706,7977.4485,8010.6868,8040.3075,8063.2455,8099.4063,8130.296,8177.8529,8236.7484,8293.5051,8339.0557,8384.0777,8431.9385,8469.5953,8496.4899,8527.1923,8555.9754,8581.049,8588.6831,8605.7586,8621.6622,8637.8878,8650.0065,8664.9573,8674.0595,8674.1627,8674.3044,8667.2106,8652.4898,8632.4805,8593.2046,8568.0451,8530.2089,8499.2462,8475.2535,8465.3044,8457.1924,8451.9703,8464.9967,8473.6473,8467.6836,8472.9953,8486.9656,8485.1488,8494.6067,8517.8395,8542.432,8552.0647,8562.0994,8568.6814,8579.7085,8569.6667,8574.7343,8576.677],"ma60":[6075.4999,6068.345,6060.2311,6053.4641,6048.7621,6046.8271,6045.8481,6044.4985,6044.6421,6046.8009,6048.7057,6049.2428,6051.5659,6065.1618,6078.4471,6091.0366,6101.1346,6110.2076,6118.9171,6128.0551,6138.1798,6148.5548,6160.2879,6170.2785,6181.3276,6192.2029,6203.6486,6216.3423,6230.1682,6243.9448,6257.6743,6267.9336,6277.0951,6285.635,6296.5952,6306.9289,6318.7672,6330.4635,6343.4818,6358.0788,6372.55,6387.8553,6401.9271,6419.4504,6440.2491,6460.4835,6482.1002,6503.2483,6524.471,6548.6572,6572.0977,6592.3199,6613.6548,6635.0853,6656.4551,6675.6582,6692.6643,6706.8132,6725.8075,6745.2004,6763.2764,6781.5228,6804.0505,6827.772,6850.0612,6871.5439,6892.8547,6913.3315,6932.6857,6951.574,6968.8124,6989.2247,7008.6226,7026.7125,7046.224,7065.6784,7086.6382,7105.4257,7123.0701,7138.2509,7155.5945,7171.2574,7182.0875,7193.5394,7205.7358,7216.9876,7228.6689,7240.6375,7253.7837,7266.2711,7279.525,7292.3017,7306.3932,7320.8539,7332.4545,7343.7443,7355.2529,7366.5817,7378.6671,7388.6147,7397.3275,7406.0982,7414.8693,7421.6289,7425.1372,7427.5432,7428.1257,7425.0317,7421.5895,7417.7932,7413.9929,7412.6754,7410.7937,7409.9271,7406.7943,7405.7008,7406.3972,7411.4195,7414.3758,7415.5349,7418.5719,7419.9357,7419.4533,7417.5565,7413.6573,7410.4091,7405.7023,7403.259,7402.7617,7401.1441,7402.7826,7403.5352,7405.1855,7408.4617,7410.1195,7410.4581,7412.2219,7417.74,7424.1843,7434.1582,7444.9204,7460.84,7477.8009,7494.7674,7509.7128,7525.0548,7541.0139,7553.7392,7566.2775,7580.1129,7595.14,7609.8125,7624.4038,7638.7651,7653.7064,7666.873,7673.9329,7685.0533,7695.7844,7704.5725,7713.9925,7724.7125,7737.1716,7749.1122,7763.5577,7777.1847,7793.1741,7815.8179,7838.0547,7859.903,7880.3782,7895.1282,7907.8,7920.874,7936.4686,7952.3952,7970.7524,7987.7697,8002.984,8016.8792,8030.2643,8042.062,8054.1562,8064.1588,8074.1891,8076.1952,8081.6694,8088.6924,8092.5428,8098.441,8102.8002,8103.4747,8106.1184,8106.6061,8105.5944,8105.7733,8109.1381,8110.0805,8111.6107,8112.5104,8112.7701,8108.5893,8109.0868,8109.9245,8111.8752,8113.849,8117.4422,8120.442,8121.383,8121.8727,8117.8052,8117.4323,8117.4289,8120.3416,8126.7133,8134.8182,8149.674,8159.8871,8172.3592,8184.2031,8194.7211,8202.8283,8212.1341,8221.624,8224.8851,8233.0157,8241.3414,8245.6901,8246.6217,8247.9033,8246.7662,8250.1441,8254.9818,8259.3411,8262.1951,8264.48,8259.9995,8259.2524,8256.966,8256.052,8255.9095,8264.2657,8273.4292,8286.6831,8303.1429,8327.4191,8345.4055,8362.7772,8382.553,8396.8045,8410.6372,8430.4695,8449.0108,8465.7094,8483.7792,8498.2223,8503.9896,8507.2632,8512.2939,8515.1728]},"boll":{"upper":[6244.4245,6243.366,6240.8896,6243.9154,6239.8934,6249.2151,6271.6396,6279.1395,6298.8652,6330.1269,6362.7837,6378.5732,6398.471,6411.3264,6423.4577,6450.9098,6471.6726,6493.0882,6519.4642,6543.7017,6560.3986,6576.2662,6589.8354,6584.7415,6597.203,6626.5117,6650.2104,6687.3611,6720.1733,6757.1664,6798.6378,6817.5975,6825.5603,6826.8634,6834.5868,6854.832,6882.5223,6904.0523,6920.2081,6952.9218,6978.1686,7021.7952,7042.7777,7091.177,7166.4425,7229.3219,7292.8895,7339.036,7400.9893,7479.9531,7547.1169,7574.1899,7605.9694,7624.9787,7651.9215,7646.941,7636.1141,7621.1427,7598.7199,7588.89,7571.6921,7564.1321,7549.3555,7552.646,7561.2747,7578.4095,7607.1929,7618.7063,7624.2814,7625.9027,7618.6053,7637.9975,7645.3422,7642.1315,7641.663,7666.0269,7695.5431,7665.7217,7663.3598,7659.6737,7642.952,7616.8686,7653.6106,7668.7929,7670.3483,7669.9342,7659.4261,7655.7749,7660.3866,7659.412,7674.6738,7669.264,7669.2816,7679.4115,7675.1023,7661.8885,7642.4553,7643.6645,7650.2341,7661.3834,7661.6414,7679.2404,7659.6198,7643.196,7636.331,7625.1294,7618.3105,7698.3963,7721.051,7724.6625,7715.643,7712.8625,7703.6882,7690.388,7686.5073,7680.9957,7661.4967,7640.9567,7620.0544,7598.4189,7588.0656,7546.3436,7525.8217,7493.0888,7476.8421,7467.2113,7462.6565,7442.9483,7445.4404,7452.9839,7483.7347,7529.3559,7574.1787,7607.1477,7638.4924,7662.2215,7717.9024,7796.9862,7872.6599,7953.0107,8061.1377,8210.2055,8295.4514,8376.0101,8427.4184,8473.0841,8509.3274,8524.7823,8546.8024,8563.6371,8610.0464,8631.6928,8647.583,8651.7413,8630.985,8579.9037,8547.2259,8522.2777,8495.507,8481.3652,8488.324,8477.149,8478.7383,8477.8256,8483.437,8482.7612,8485.4432,8507.4482,8538.8323,8579.3147,8580.4195,8573.4469,8564.9073,8548.9873,8542.4445,8540.4245,8535.4751,8545.4729,8551.7576,8543.9045,8531.9419,8548.1475,8552.1398,8577.633,8610.0315,8712.5865,8734.1842,8711.9454,8679.5236,8612.5055,8551.3489,8545.5745,8533.6003,8515.5754,8485.42,8450.926,8389.8239,8315.3093,8247.5256,8210.0174,8194.1614,8209.7983,8240.0024,8310.5374,8390.9559,8438.3509,8519.3,8569.7879,8597.9975,8631.0423,8645.4594,8656.2568,8677.7926,8705.8623,8726.9303,8739.2773,8822.0969,8870.87,8945.0869,8968.266,8979.9716,8984.9299,9008.4587,9031.2347,9028.5272,9033.7483,9053.5824,9053.7655,9039.5694,9027.6089,8999.4813,8999.1656,8998.7996,9006.0061,9007.0056,9009.1999,9023.944,9001.1918,8953.4741,8935.6634,8921.3542,8897.7761,8869.2013,8848.367,8884.67,8918.134,8897.4908,8915.9499,8955.2158,8951.3223,8961.8693,8999.0611,9043.7904,9052.0192,9059.1035,9057.2113,9032.372,9052.9225,9044.2547,9039.5833],"middle":[6106.9604,6106.4289,6102.2311,6098.9055,6103.3328,6111.6268,6125.012,6138.1788,6147.5467,6164.0278,6179.2143,6188.5299,6197.3111,6205.2787,6210.6874,6222.9877,6233.1854,6243.9028,6261.6573,6277.3996,6292.4679,6308.8017,6333.1741,6360.7982,6387.5001,6409.6219,6426.1748,6448.8412,6470.3248,6489.0147,6509.0205,6529.4704,6545.3979,6563.3116,6583.9394,6602.9285,6626.4707,6649.2498,6668.1013,6692.1829,6718.2217,6748.3353,6770.3761,6798.6474,6829.9146,6860.2019,6895.1139,6922.7251,6955.5416,6992.929,7028.0582,7058.9592,7098.2554,7136.6657,7174.7384,7201.0585,7218.3368,7227.2871,7247.6639,7266.0188,7279.1396,7287.4313,7308.6012,7323.8704,7332.7689,7344.8078,7357.2754,7368.4283,7372.1908,7372.7783,7369.3584,7379.2443,7382.2144,7380.1601,7379.9942,7393.0482,7415.1071,7439.7404,7453.4452,7456.5511,7469.4221,7478.0056,7467.2853,7458.1003,7454.524,7445.9531,7433.6175,7430.7591,7433.6189,7433.106,7441.1584,7438.7015,7438.7096,7445.736,7442.631,7437.126,7432.3149,7432.7178,7434.8923,7443.2742,7443.4206,7452.8576,7468.7215,7482.9161,7488.1188,7491.8687,7493.4843,7475.9077,7458.959,7447.4953,7431.4619,7420.0803,7411.4571,7403.8852,7397.7576,7386.9282,7371.7695,7361.8002,7354.7899,7346.7795,7342.8729,7328.9438,7322.3531,7311.6532,7298.3291,7293.4056,7290.0051,7303.1103,7315.7073,7322.831,7335.7276,7351.8238,7365.3898,7375.7637,7389.9697,7407.3202,7432.5814,7458.7019,7482.8706,7512.4209,7548.4678,7600.7186,7642.3281,7689.7329,7742.6906,7789.8902,7839.5523,7882.1997,7924.1662,7970.0125,8018.2306,8057.5334,8096.3645,8136.6463,8173.3917,8206.3705,8217.4479,8234.6578,8249.6929,8254.5173,8250.6368,8244.4752,8246.8336,8245.9506,8249.6535,8248.2585,8249.9647,8262.1437,8274.2905,8286.8654,8287.1765,8276.0274,8261.6457,8250.212,8246.0445,8243.4949,8262.228,8269.9492,8276.3886,8283.6994,8291.6883,8280.9922,8273.3069,8256.793,8230.2231,8190.437,8155.4913,8121.7338,8079.1717,8038.4452,8002.9935,7976.8633,7960.345,7932.9599,7897.347,7867.4544,7847.7384,7825.6344,7808.7506,7799.3146,7795.9851,7800.3005,7807.1199,7827.03,7855.749,7902.8514,7946.8706,7977.4485,8010.6868,8040.3075,8063.2455,8099.4063,8130.296,8177.8529,8236.7484,8293.5051,8339.0557,8384.0777,8431.9385,8469.5953,8496.4899,8527.1923,8555.9754,8581.049,8588.6831,8605.7586,8621.6622,8637.8878,8650.0065,8664.9573,8674.0595,8674.1627,8674.3044,8667.2106,8652.4898,8632.4805,8593.2046,8568.0451,8530.2089,8499.2462,8475.2535,8465.3044,8457.1924,8451.9703,8464.9967,8473.6473,8467.6836,8472.9953,8486.9656,8485.1488,8494.6067,8517.8395,8542.432,8552.0647,8562.0994,8568.6814,8579.7085,8569.6667,8574.7343,8576.677],"lower":[5969.4963,5969.4918,5963.5725,5953.8955,5966.7722,5974.0385,5978.3844,5997.218,5996.2283,5997.9287,5995.645,5998.4866,5996.1512,5999.231,5997.9172,5995.0657,5994.6982,5994.7174,6003.8505,6011.0975,6024.5372,6041.3373,6076.5128,6136.8549,6177.7971,6192.7321,6202.1391,6210.3214,6220.4763,6220.863,6219.4033,6241.3434,6265.2354,6299.7599,6333.2919,6351.025,6370.4191,6394.4473,6415.9945,6431.444,6458.2749,6474.8753,6497.9745,6506.1179,6493.3866,6491.0818,6497.3383,6506.4142,6510.0938,6505.9049,6508.9994,6543.7285,6590.5415,6648.3526,6697.5553,6755.176,6800.5596,6833.4314,6896.6079,6943.1476,6986.5872,7010.7306,7067.847,7095.0948,7104.2631,7111.2061,7107.3579,7118.1504,7120.1001,7119.6539,7120.1115,7120.4911,7119.0867,7118.1887,7118.3254,7120.0696,7134.6711,7213.759,7243.5306,7253.4285,7295.8923,7339.1427,7280.9599,7247.4076,7238.6998,7221.9721,7207.8089,7205.7433,7206.8511,7206.8,7207.6429,7208.139,7208.1376,7212.0606,7210.1598,7212.3636,7222.1745,7221.7711,7219.5505,7225.1651,7225.1999,7226.4747,7277.8232,7322.6361,7339.9065,7358.608,7368.6581,7253.4191,7196.8669,7170.3281,7147.2808,7127.2982,7119.226,7117.3825,7109.0079,7092.8606,7082.0424,7082.6438,7089.5253,7095.1401,7097.6802,7111.544,7118.8844,7130.2175,7119.8161,7119.5999,7117.3538,7163.2723,7185.9742,7192.678,7187.7204,7174.2918,7156.601,7144.3796,7141.4471,7152.419,7147.2603,7120.4177,7093.0813,7071.8311,7035.7979,6991.2317,6989.2049,7003.4556,7057.9629,7106.6962,7169.7772,7239.6171,7301.53,7376.3878,7426.4148,7483.3739,7545.146,7621.5514,7715.7985,7832.8374,7887.67,7947.038,8003.8787,8027.6693,8012.9496,8011.8014,8014.9289,8014.0756,8015.8699,8013.7558,8014.4862,8016.8391,8009.7488,7994.4162,7993.9334,7978.6079,7958.3841,7951.4366,7949.6445,7946.5653,7988.9808,7994.4255,8001.0196,8023.4943,8051.4346,8013.8369,7994.4741,7935.953,7850.4147,7668.2875,7576.7984,7531.5222,7478.8199,7464.3849,7454.638,7408.1521,7387.0897,7350.3444,7309.2741,7283.9828,7305.6528,7335.9594,7369.9756,7388.6117,7397.8088,7390.8027,7374.2374,7343.5226,7320.542,7367.352,7374.4412,7385.1092,7423.3761,7449.5726,7481.0317,7542.5558,7582.7994,7649.8435,7746.5665,7847.733,7856.0145,7897.2855,7918.7901,7970.9247,8013.0081,8069.4547,8103.4921,8130.8633,8148.839,8177.7689,8189.742,8222.0101,8260.4436,8302.3057,8348.6377,8349.1598,8349.8093,8328.4151,8297.9741,8255.761,8162.4651,8134.8983,8106.9437,8062.829,8029.1527,8032.8328,8045.1834,8055.5736,8045.3235,8029.1605,8037.8764,8030.0407,8018.7154,8018.9754,8027.3441,8036.618,8041.0736,8052.1102,8065.0953,8080.1515,8127.0451,8086.4108,8105.214,8113.7707]},"macd":{"dif":[26.584,24.528,15.6846,4.6977,2.3088,9.6997,21.8811,28.9121,36.4164,48.2023,58.2898,60.4008,64.0112,63.682,63.8903,69.7518,72.1746,74.5348,79.8847,83.2619,83.4059,84.1021,89.561,94.1258,101.4306,107.9797,109.4964,116.9275,121.8549,126.1911,131.6526,130.0118,122.674,116.2678,115.4456,117.2979,123.3019,126.6677,125.9452,132.3842,137.4899,147.9581,147.4659,156.6486,171.6386,181.8455,192.7647,194.9654,203.2104,216.5113,224.3643,216.7949,217.2172,214.3999,214.7328,197.6079,173.4029,139.2428,127.2068,121.5417,108.937,98.1503,102.1194,105.9001,107.0719,112.1988,120.6155,119.5803,114.3582,113.055,104.2515,106.2295,104.3582,93.0138,91.0622,94.6485,102.2101,97.8571,92.2101,75.0395,69.5302,57.9112,30.8885,13.6492,8.3521,1.5671,-4.0945,0.3819,9.9592,16.06,27.828,30.0274,33.1306,37.6927,32.6698,30.6861,35.7197,38.4625,41.8783,42.2853,37.7816,42.1347,38.0595,36.0539,28.0908,16.6742,3.8065,-28.0729,-45.6536,-51.4455,-55.5166,-57.3552,-52.0191,-43.0598,-41.4133,-44.8288,-46.9633,-40.6151,-28.7526,-22.5183,-15.1707,-16.9191,-13.3939,-15.4143,-26.9892,-27.2052,-28.3675,-24.3758,-14.705,-8.2312,6.0256,22.9499,38.0343,48.5119,56.4186,61.8096,77.9805,98.6179,116.9748,135.2226,160.5499,196.7379,210.5732,223.3239,229.4607,231.012,232.2207,223.9086,220.0241,219.3924,229.2724,225.9996,222.1936,218.0869,206.9924,189.7712,151.8253,139.006,127.2202,105.4448,85.8661,84.083,83.0458,80.4262,83.4656,76.1207,77.0722,87.0355,98.9778,112.8084,115.6677,89.905,64.8721,50.6308,45.0974,36.6594,41.2949,45.5281,46.1226,36.3613,28.0646,5.9685,-5.2897,-28.996,-57.2743,-108.6378,-132.3455,-137.4201,-148.7487,-147.3987,-142.9369,-149.6248,-141.6482,-145.0114,-152.9193,-151.8348,-121.3543,-98.8286,-73.9287,-51.3967,-23.6497,-4.7201,20.2812,45.5772,68.8954,85.8483,108.5293,115.6095,115.1647,116.2626,106.8607,107.5601,109.9839,125.9944,148.2668,166.1523,188.2933,199.9133,217.3934,214.5125,202.1482,193.1536,190.9598,187.0859,158.1137,148.1449,147.1536,135.7609,114.0609,103.037,74.9576,47.0297,27.7761,16.1957,5.9344,-8.4853,-40.403,-46.0085,-59.4466,-72.4301,-78.3193,-56.6386,-29.0218,-2.4221,23.7551,51.5442,57.9202,71.3055,83.5673,74.312,65.9334,75.5208,87.5039,75.8487,65.4903,44.8072,14.467,-24.1423,-39.5808,-59.3438],"dea":[24.2354,24.2939,22.5721,18.9972,15.6595,14.4676,15.9503,18.5426,22.1174,27.3344,33.5255,38.9005,43.9227,47.8745,51.0777,54.8125,58.2849,61.5349,65.2048,68.8163,71.7342,74.2078,77.2784,80.6479,84.8044,89.4395,93.4509,98.1462,102.8879,107.5486,112.3694,115.8979,117.2531,117.056,116.7339,116.8467,118.1378,119.8437,121.064,123.3281,126.1604,130.52,133.9091,138.457,145.0933,152.4438,160.508,167.3994,174.5616,182.9516,191.2341,196.3463,200.5205,203.2964,205.5836,203.9885,197.8714,186.1457,174.3579,163.7946,152.8231,141.8886,133.9347,128.3278,124.0766,121.701,121.4839,121.1032,119.7542,118.4144,115.5818,113.7113,111.8407,108.0753,104.6727,102.6679,102.5763,101.6325,99.748,94.8063,89.7511,83.3831,72.8842,61.0372,50.5002,40.7136,31.7519,25.4779,22.3742,21.1113,22.4547,23.9692,25.8015,28.1797,29.0777,29.3994,30.6635,32.2233,34.1543,35.7805,36.1807,37.3715,37.5091,37.2181,35.3926,31.6489,26.0805,15.2498,3.0691,-7.8338,-17.3704,-25.3673,-30.6977,-33.1701,-34.8188,-36.8208,-38.8493,-39.2024,-37.1125,-34.1936,-30.389,-27.695,-24.8348,-22.9507,-23.7584,-24.4478,-25.2317,-25.0605,-22.9894,-20.0378,-14.8251,-7.2701,1.7908,11.135,20.1917,28.5153,38.4083,50.4502,63.7552,78.0486,94.5489,114.9867,134.104,151.948,167.4505,180.1628,190.5744,197.2412,201.7978,205.3167,210.1079,213.2862,215.0677,215.6715,213.9357,209.1028,197.6473,185.919,174.1793,160.4324,145.5191,133.2319,123.1947,114.641,108.4059,101.9489,96.9735,94.9859,95.7843,99.1891,102.4848,99.9689,92.9495,84.4858,76.6081,68.6184,63.1537,59.6286,56.9274,52.8142,47.8642,39.4851,30.5301,18.6249,3.4451,-18.9715,-41.6463,-60.8011,-78.3906,-92.1922,-102.3412,-111.7979,-117.768,-123.2166,-129.1572,-133.6927,-131.225,-124.7457,-114.5823,-101.9452,-86.2861,-69.9729,-51.9221,-32.4222,-12.1587,7.4427,27.66,45.2499,59.2329,70.6388,77.8832,83.8186,89.0516,96.4402,106.8055,118.6749,132.5985,146.0615,160.3279,171.1648,177.3615,180.5199,182.6079,183.5035,178.4255,172.3694,167.3262,161.0132,151.6227,141.9056,128.516,112.2187,95.3302,79.5033,64.7895,50.1346,32.027,16.4199,1.2466,-13.4887,-26.4548,-32.4916,-31.7976,-25.9225,-15.987,-2.4808,9.5994,21.9407,34.266,42.2752,47.0068,52.7096,59.6685,62.9045,63.4217,59.6988,50.6524,35.6935,20.6386,4.6421],"hist":[4.697,0.468,-13.775,-28.599,-26.7015,-9.5356,11.8616,20.739,28.5981,41.7358,49.5287,43.0006,40.1771,31.6149,25.6253,29.8786,27.7793,25.9997,29.3596,28.8914,23.3434,19.7886,24.5652,26.9558,33.2523,37.0805,32.0911,37.5625,37.934,37.285,38.5665,28.2278,10.8418,-1.5765,-2.5767,0.9024,10.3282,13.648,9.7623,18.1123,22.6589,34.8762,27.1134,36.3831,53.0905,58.8034,64.5135,55.1318,57.2975,67.1195,66.2604,40.8973,33.3935,22.2071,18.2983,-12.7612,-48.937,-93.8057,-94.3022,-84.5059,-87.7722,-87.4765,-63.6306,-44.8555,-34.0095,-19.0045,-1.7368,-3.0458,-10.7921,-10.7187,-22.6607,-14.9636,-14.965,-30.123,-27.2209,-16.0388,-0.7325,-7.5508,-15.0758,-39.5336,-40.4417,-50.9439,-83.9914,-94.776,-84.2961,-78.2929,-71.693,-50.1921,-24.83,-10.1027,10.7467,12.1164,14.6583,19.0259,7.1841,2.5733,10.1125,12.4785,15.448,13.0097,3.2018,9.5264,1.1008,-2.3283,-14.6037,-29.9495,-44.5479,-86.6454,-97.4453,-87.2234,-76.2925,-63.9757,-42.6428,-19.7794,-13.189,-16.0161,-16.2281,-2.8253,16.7198,23.3507,30.4367,21.5519,22.8819,15.0728,-6.4616,-5.5148,-6.2716,1.3695,16.5689,23.6131,41.7013,60.44,72.487,74.7537,72.4537,66.5887,79.1444,96.3353,106.4393,114.3479,132.0021,163.5025,152.9384,142.7518,124.0204,101.6984,83.2926,53.3347,36.4525,28.1514,38.3291,25.4268,14.2519,4.8307,-13.8866,-38.6632,-91.644,-93.8261,-93.9181,-109.9752,-119.306,-98.2978,-80.2978,-68.4296,-49.8805,-51.6564,-39.8026,-15.9009,6.387,27.2386,26.3657,-20.1277,-56.1548,-67.7099,-63.0214,-63.918,-43.7175,-28.201,-21.6095,-32.9057,-39.5993,-67.0331,-71.6396,-95.2419,-121.4387,-179.3326,-181.3984,-153.2381,-140.7163,-110.413,-81.1914,-75.6539,-47.7606,-43.5894,-47.5242,-36.2842,19.7414,51.8342,81.3073,101.097,125.2728,130.5056,144.4065,155.9989,162.1081,156.8113,161.7385,140.7192,111.8636,91.2476,57.955,47.483,41.8645,59.1084,82.9226,94.9548,111.3894,107.7036,114.1311,86.6954,49.5735,25.2674,16.7038,7.1648,-40.6237,-48.4491,-40.3452,-50.5045,-75.1237,-77.7371,-107.1168,-130.378,-135.1082,-126.6151,-117.7103,-117.2397,-144.8601,-124.8569,-121.3865,-117.8828,-103.7289,-48.2941,5.5516,47.0009,79.4843,108.0499,96.6415,98.7298,98.6027,64.0736,37.8532,45.6223,55.6709,25.8884,4.1372,-29.7831,-72.3709,-119.6716,-120.4389,-127.9719]},"rsi":{"rsi14":[52.9689,52.4356,45.3848,41.9919,48.6731,56.638,61.1787,58.8675,60.5176,64.6676,65.5335,59.7678,61.6422,58.9276,59.862,64.5451,62.8557,63.8089,66.9064,66.9737,64.6858,65.9238,70.2268,71.1025,74.1113,75.2566,71.1777,75.6446,75.88,76.9032,78.7289,71.0923,64.161,64.7607,68.9336,71.4473,74.8351,74.8717,71.6678,76.4486,77.2185,80.697,70.5754,75.8186,79.2156,79.3521,80.9587,75.6798,78.8089,81.4946,81.3726,69.0213,72.5652,71.8899,73.8326,60.3653,54.2733,46.4544,55.059,57.4145,53.4882,53.6545,59.9703,60.7509,60.3479,62.8196,65.259,60.5468,58.336,60.4247,55.6555,60.8166,59.1871,53.1578,57.4533,60.4581,63.1163,56.7007,55.9471,48.6797,53.5664,49.7887,41.444,43.955,48.5906,47.3111,47.1385,52.214,55.3755,54.5506,58.274,53.8342,54.7873,56.2054,50.6361,52.0908,56.2366,55.6432,56.7001,55.2114,51.6721,57.315,51.8229,52.9464,48.4562,45.1101,42.6714,31.8616,37.4153,42.7174,42.655,43.1916,47.6848,50.5635,46.6879,43.5162,43.5406,49.3119,53.6885,51.1799,52.7293,47.1247,50.5886,47.1011,40.8524,47.193,46.3765,49.6717,53.8504,52.8913,58.5758,61.759,62.8601,62.0237,62.1734,62.0046,69.1146,72.933,74.2167,76.1303,79.9968,84.0254,73.2893,74.5205,73.4147,72.8435,73.7436,67.6618,69.7651,71.6511,75.89,68.6745,69.1756,69.7258,64.9424,59.8797,45.9446,55.3106,55.2232,49.3337,48.6702,55.7465,56.3343,55.813,58.6876,53.2401,56.9539,61.3597,63.4083,65.5566,60.9535,46.8309,45.2142,48.2865,51.2728,49.4916,54.9675,55.4455,54.1726,48.854,48.7294,41.3369,44.9415,38.6905,35.1548,27.1919,35.2791,40.8281,38.2045,42.0408,42.8136,38.9792,44.2218,40.5616,38.4476,41.0914,52.2254,51.2027,53.4013,54.1927,57.5754,56.1298,59.7092,61.6856,63.0079,62.6999,66.1783,60.6314,58.0407,59.1501,54.1549,58.112,59.3737,64.9982,68.4195,69.0399,71.8483,69.4248,72.4069,63.5711,59.3333,60.4437,63.005,63.0127,50.2752,56.1081,59.1306,54.856,49.9702,52.8988,45.6716,43.8784,45.3197,47.0874,46.6606,43.9622,36.5016,45.5926,42.2973,41.2465,42.9318,53.4874,56.8649,58.3749,60.099,62.4793,55.488,58.5412,59.3986,51.4641,51.3485,57.5424,59.3026,50.7793,50.6376,46.1172,41.5169,37.2117,43.4658,41.009]},"kdj":{"k":[54.9906,48.2795,35.476,23.9491,30.6486,52.6323,67.7949,72.4654,77.6621,84.9514,89.9676,88.0611,89.4981,85.8297,81.7226,87.7301,84.0152,83.7481,84.8283,85.7468,82.8848,84.2009,89.4673,91.3824,93.9382,95.3358,89.8306,93.2204,94.4764,95.6455,97.097,90.7475,76.6658,65.2295,70.4669,80.3113,86.3572,88.9962,87.5602,90.3525,93.5493,95.237,89.2636,92.8416,93.1776,92.2127,94.8084,90.4603,93.6402,94.1601,93.1986,82.9366,79.2908,75.5941,78.357,61.6228,43.2212,34.2209,39.1161,45.862,47.5314,48.8896,59.8447,68.6627,75.5262,83.4748,88.3735,79.7285,71.4414,69.3041,62.5025,64.1396,62.9464,53.1707,54.918,62.4422,73.0796,70.8729,68.5824,55.4359,55.413,48.9298,33.1945,26.3266,28.8207,29.3446,29.6152,38.3144,57.2785,66.4008,77.6005,77.6285,78.5697,81.8803,75.3502,67.8692,74.4345,77.4894,81.2198,80.2112,72.7425,80.0792,74.2391,72.8287,54.7522,41.5849,28.7127,19.1418,18.4255,23.7188,27.4475,31.6876,40.7879,53.5619,57.8366,57.4533,57.2372,63.9065,72.9734,73.58,77.5268,67.8317,68.9174,61.7185,45.3325,46.2092,44.994,50.9683,64.4276,70.8013,79.9145,85.6872,87.8439,88.4886,88.3933,87.7348,91.8164,94.5443,94.3547,94.7415,96.3621,96.9751,90.8267,87.723,84.4725,80.4381,77.9168,70.6226,67.8999,67.2353,77.46,72.0487,69.7509,69.601,64.2064,55.5635,37.0921,38.7915,39.8057,32.1431,28.0266,37.1188,44.2535,56.0708,68.7744,67.7774,73.8371,80.9952,86.9563,91.2676,86.4086,58.695,42.6393,36.8299,37.9238,37.9933,46.4762,52.9067,56.5384,52.278,53.346,38.5103,35.6126,25.9842,17.4238,13.2693,16.7083,24.3446,27.0428,32.9818,40.2665,40.2738,48.0696,52.5713,48.6794,42.9373,61.9582,71.77,77.3668,82.7926,88.5284,88.0261,91.7373,93.3879,94.6625,94.872,96.5244,89.3861,78.0888,72.4713,58.8324,56.993,59.6116,70.3688,80.1043,85.6726,89.4334,89.878,93.1259,86.8419,75.7887,66.7695,63.256,59.8602,40.557,40.0572,46.9651,43.9617,33.5312,35.9267,27.1022,18.4137,20.4254,25.8088,28.6792,26.6763,21.9579,30.5772,30.5516,30.5755,33.163,53.7799,67.3582,78.1954,84.4147,89.6039,85.1394,87.0056,89.1073,77.7665,65.2305,72.286,77.2773,64.8099,56.2126,41.1671,29.4173,19.6115,24.1673,23.6906],"d":[65.6681,59.8719,51.7399,42.4763,38.5338,43.2333,51.4205,58.4355,64.8443,71.5467,77.687,81.145,83.9294,84.5628,83.6161,84.9874,84.6633,84.3583,84.5149,84.9256,84.2453,84.2305,85.9761,87.7782,89.8315,91.6663,91.0544,91.7764,92.6764,93.6661,94.8097,93.4557,87.859,80.3159,77.0329,78.1257,80.8695,83.5784,84.9057,86.7213,88.9973,91.0772,90.4727,91.2623,91.9008,92.0047,92.9393,92.113,92.622,93.1347,93.156,89.7495,86.2633,82.7069,81.2569,74.7122,64.2152,54.2171,49.1835,48.0763,47.8947,48.2263,52.0991,57.6203,63.589,70.2176,76.2695,77.4225,75.4288,73.3873,69.759,67.8859,66.2394,61.8831,59.5614,60.5217,64.7077,66.7627,67.3693,63.3915,60.732,56.7979,48.9301,41.3956,37.204,34.5842,32.9279,34.7234,42.2418,50.2948,59.3967,65.474,69.8392,73.8529,74.352,72.1911,72.9389,74.4557,76.7104,77.8773,76.1657,77.4702,76.3932,75.205,68.3874,59.4532,49.2064,39.1849,32.2651,29.4163,28.76,29.7359,33.4199,40.1339,46.0348,49.841,52.3064,56.1731,61.7732,65.7088,69.6481,69.0427,69.0009,66.5734,59.4931,55.0651,51.7081,51.4615,55.7835,60.7894,67.1645,73.3387,78.1738,81.612,83.8725,85.1599,87.3788,89.7673,91.2964,92.4448,93.7505,94.8254,93.4925,91.5693,89.2037,86.2819,83.4935,79.2032,75.4354,72.7021,74.288,73.5416,72.278,71.3857,68.9926,64.5162,55.3748,49.8471,46.4999,41.7143,37.1518,37.1408,39.5117,45.0314,52.9457,57.8896,63.2054,69.1353,75.0757,80.473,82.4515,74.5327,63.9015,54.8777,49.2264,45.482,45.8134,48.1778,50.9647,51.4025,52.0503,47.5369,43.5622,37.7028,30.9432,25.0519,22.2707,22.962,24.3222,27.2088,31.5613,34.4655,39.0002,43.5239,45.2424,44.474,50.3021,57.4581,64.0943,70.3271,76.3942,80.2715,84.0934,87.1916,89.6819,91.4119,93.1161,91.8727,87.2781,82.3425,74.5058,68.6682,65.6493,67.2225,71.5164,76.2352,80.6346,83.7157,86.8524,86.8489,83.1622,77.6979,72.884,68.5427,59.2141,52.8285,50.874,48.5699,43.557,41.0136,36.3764,30.3889,27.0677,26.6481,27.3251,27.1089,25.3919,27.1203,28.2641,29.0345,30.4107,38.2004,47.9197,58.0116,66.8126,74.4097,77.9863,80.9927,83.6976,81.7205,76.2239,74.9112,75.6999,72.0699,66.7842,58.2451,48.6358,38.9611,34.0298,30.5834],"j":[33.6355,25.0948,2.9482,-13.1055,14.8784,71.4303,100.5438,100.5253,103.2977,111.7608,114.5288,101.8932,100.6355,88.3634,77.9357,93.2155,82.7189,82.5278,85.4549,87.3894,80.1638,84.1417,96.4496,98.5908,102.1514,102.6749,87.383,96.1084,98.0764,99.6044,101.6716,85.3311,54.2793,35.0568,57.335,84.6825,97.3327,99.8318,92.8691,97.6149,102.6534,103.5565,86.8456,96.0002,95.7314,92.6285,98.5467,87.155,95.6765,96.2108,93.2838,69.3107,65.3459,61.3685,72.5572,35.4439,1.2331,-5.7714,18.9815,41.4334,46.805,50.2161,75.3358,90.7476,99.4008,109.9893,112.5813,84.3406,63.4665,61.1379,47.9894,56.647,56.3605,35.7457,45.6312,66.2832,89.8236,79.0931,71.0085,39.5248,44.7751,33.1935,1.7232,-3.8114,12.0542,18.8655,22.99,45.4965,87.3521,98.6128,114.0082,101.9376,96.0306,97.9351,77.3465,59.2254,77.4258,83.5567,90.2387,84.8789,65.8961,85.2971,69.9311,68.076,27.4817,5.8483,-12.2747,-20.9443,-9.2538,12.3237,24.8225,35.5911,55.5239,80.4179,81.4402,72.6779,67.0987,79.3733,95.3739,89.3225,93.2842,65.4099,68.7504,52.0085,17.0112,28.4972,31.5657,49.9818,81.7159,90.8249,105.4145,110.3841,107.1841,102.2418,97.435,92.8846,100.6918,104.0983,100.4712,99.335,101.5851,101.2746,85.4952,80.0303,75.01,68.7507,66.7635,53.4614,52.8288,56.3018,83.8038,69.0629,64.6967,66.0317,54.6339,37.6581,0.5265,16.6804,26.4172,13.0007,9.7763,37.0747,53.7371,78.1495,100.4317,87.553,95.1004,104.7148,110.7176,112.8569,94.3227,27.0196,0.1149,0.7343,15.3187,23.0158,47.8017,62.3644,67.6859,54.029,55.9373,20.4569,19.7135,2.5468,-9.615,-10.2958,5.5836,27.1098,32.4838,44.5278,57.6769,51.8905,66.2085,70.666,55.5534,39.8638,85.2704,100.394,103.9119,107.7236,112.7968,103.5353,107.0252,105.7806,104.6237,101.792,103.341,84.4128,59.7101,52.7288,27.4856,33.6426,47.536,76.6615,97.2801,104.5476,107.031,102.2026,105.6727,86.8278,61.0418,44.9126,44.0001,42.4952,3.2427,14.5146,39.1472,34.7454,13.4795,25.7529,8.5538,-5.5367,7.1408,24.1304,31.3875,25.8112,15.0899,37.491,35.1265,33.6575,38.6676,84.9388,106.2352,118.563,119.6188,119.9922,99.4456,99.0314,99.9268,69.8584,43.2437,67.0355,80.4321,50.2899,35.0696,7.011,-9.0199,-19.0876,4.4423,9.905]}},"generated_at":"2026-07-11T04:21:57.907354Z"},"algorithmic":{"ticker":"000852.SH","name":"中证一千","overall_score":26.8,"energy_score":3.16,"energy_class":"歪瓜裂枣（不值得交易）","divergence":{"is_end":true,"type":"top_divergence"},"reversal_status":"trend_intact","wash_conclusion":"dump","central_level":"当前级别中枢","recommendation":"⚠️ 顶背驰确认，趋势末期，建议减仓或离场","source":"report","report_date":"2026-07-10","tone":"neutral"}}