{"ticker":"000938.SZ","mode":"close","summary":{"schema_version":"1.0","ticker":"000938.SZ","name":"紫光股份","data_date":"2026-07-13","generated_at":"2026-07-14T07:23:46.729821Z","conclusion":"日线偏强 4/4，周线偏强 4/4。今日-0.0%，近5日+15.3%，成交额190.6亿，明显放量（量比2.0），价跌量增。MACD 零轴上、金叉区、柱扩大；RSI 超买；KDJ 高位金叉区。","conclusion_segments":[{"text":"日线","tone":"neutral"},{"text":"偏强 4/4","tone":"positive"},{"text":"，周线","tone":"neutral"},{"text":"偏强 4/4","tone":"positive"},{"text":"。今日","tone":"neutral"},{"text":"-0.0%","tone":"risk"},{"text":"，近5日","tone":"neutral"},{"text":"+15.3%","tone":"positive"},{"text":"，成交额190.6亿","tone":"neutral"},{"text":"，","tone":"neutral"},{"text":"明显放量（量比2.0）","tone":"positive"},{"text":"，","tone":"neutral"},{"text":"价跌量增","tone":"orange"},{"text":"。MACD ","tone":"neutral"},{"text":"零轴上","tone":"positive"},{"text":"金叉区","tone":"positive"},{"text":"，柱扩大","tone":"positive"},{"text":"（DIF 2.225 DEA 1.031 柱2.388）","tone":"neutral"},{"text":"；RSI ","tone":"neutral"},{"text":"超买","tone":"orange"},{"text":"（72.6）","tone":"neutral"},{"text":"；KDJ ","tone":"neutral"},{"text":"高位金叉区","tone":"positive"},{"text":"（K88 D85 J94）","tone":"neutral"},{"text":"。","tone":"neutral"}],"trend_score":2,"signals":[{"type":"positive","text":"日线强弱：偏强 4/4"},{"type":"positive","text":"日线 MACD：金叉区"},{"type":"neutral","text":"日线 RSI/KDJ：超买；高位金叉区"},{"type":"neutral","text":"量价：明显放量，价跌量增"}],"key_levels":{"support":[37.66,35.52,32.9],"resistance":[],"extended":{"support":[{"label":"Fib 0.236","value":36.26},{"label":"整数关","value":20.0},{"label":"整数关","value":10.0}],"resistance":[{"label":"整数关","value":40.0},{"label":"整数关","value":50.0},{"label":"整数关","value":60.0}],"high_20":40.28,"low_20":25.34,"high_120":40.28,"low_120":23.23}},"advice":{"text":"当前价约 38.40。日线偏强但短线指标偏热，继续上冲时追涨性价比下降。支撑位参考 37.66 / 35.52 / 32.90，压力位参考 暂无。RSI 超买，KDJ 高位金叉区，BOLL 上轨外。接近压力位或出现放量滞涨时宜先兑现部分仓位，回踩支撑企稳后再观察。主要风险：追涨风险、异常放量。操作区间：回落到 37.66 附近且缩量企稳，可观察低吸或补仓机会。建议仓位：3-5成，并随消息面、成交量和关键价位突破/跌破动态调整。","risk":"追涨风险、异常放量","trend":"日线偏强但短线指标偏热，继续上冲时追涨性价比下降。","overbought_oversold":"RSI 超买，KDJ 高位金叉区，BOLL 上轨外。","timing":"接近压力位或出现放量滞涨时宜先兑现部分仓位，回踩支撑企稳后再观察。","support":[37.66,35.52,32.9],"resistance":[],"operation_range":"回落到 37.66 附近且缩量企稳，可观察低吸或补仓机会。","suggested_position":"3-5成","source":"technical_fallback"},"disclaimer":"仅供研究复盘，不构成投资建议。","close":38.4,"pct_chg":-0.03,"pct_chg_5d":15.28,"volume":493931758,"vol_chg_pct":2.3,"vol_ratio":2.02,"source":"stock-shared/daily"},"analysis_view":{"schema_version":"1.0","ticker":"000938.SZ","name":"紫光股份","data_date":"2026-07-13","generated_at":"2026-07-14T07:23:46.729821Z","sections":[{"id":"conclusion","title":"综合结论","cards":[{"type":"summary","title":"核心判断","items":[{"label":"结论","value":"日线偏强 4/4，周线偏强 4/4。今日-0.0%，近5日+15.3%，成交额190.6亿，明显放量（量比2.0），价跌量增。MACD 零轴上、金叉区、柱扩大；RSI 超买；KDJ 高位金叉区。","tone":"risk"},{"label":"趋势评分","value":2,"tone":"positive"},{"label":"数据日期","value":"2026-07-13","tone":"muted"}]},{"type":"signal_list","title":"信号摘要","items":[{"label":"positive","value":"日线强弱：偏强 4/4","tone":"positive"},{"label":"positive","value":"日线 MACD：金叉区","tone":"positive"},{"label":"neutral","value":"日线 RSI/KDJ：超买；高位金叉区","tone":"neutral"},{"label":"neutral","value":"量价：明显放量，价跌量增","tone":"neutral"}]},{"type":"metric_grid","title":"关键价位","items":[{"label":"支撑位","value":"37.66 / 35.52 / 32.9","tone":"positive"},{"label":"压力位","value":"","tone":"risk"}]},{"type":"text","title":"综合操作建议","items":[{"label":"建议","value":"当前价约 38.40。日线偏强但短线指标偏热，继续上冲时追涨性价比下降。支撑位参考 37.66 / 35.52 / 32.90，压力位参考 暂无。RSI 超买，KDJ 高位金叉区，BOLL 上轨外。接近压力位或出现放量滞涨时宜先兑现部分仓位，回踩支撑企稳后再观察。主要风险：追涨风险、异常放量。操作区间：回落到 37.66 附近且缩量企稳，可观察低吸或补仓机会。建议仓位：3-5成，并随消息面、成交量和关键价位突破/跌破动态调整。","tone":"risk"},{"label":"仓位","value":"3-5成","tone":"neutral"},{"label":"区间","value":"回落到 37.66 附近且缩量企稳，可观察低吸或补仓机会。","tone":"neutral"}]}]},{"id":"daily","title":"日线状态","cards":[{"type":"metric_grid","title":"价格与趋势","items":[{"label":"收盘","value":38.4,"tone":"neutral"},{"label":"涨跌幅","value":-0.026,"tone":"neutral","unit":"%"},{"label":"强弱","value":"偏强 4/4","tone":"positive"},{"label":"BOLL","value":"上轨外 (上37.66/中29.98/下22.31)","tone":"neutral"}]},{"type":"metric_grid","title":"均线","items":[{"label":"MA5","value":35.518,"tone":"neutral"},{"label":"MA10","value":32.9,"tone":"neutral"},{"label":"MA20","value":29.9815,"tone":"neutral"},{"label":"MA60","value":29.776,"tone":"neutral"}]},{"type":"metric_grid","title":"技术指标","items":[{"label":"MACD","value":"金叉区 (DIF 2.225)","tone":"positive"},{"label":"DIF","value":2.2253,"tone":"neutral"},{"label":"DEA","value":1.0314,"tone":"neutral"},{"label":"HIST","value":2.3878,"tone":"neutral"},{"label":"RSI14","value":"72.6 (超买)","tone":"risk"},{"label":"KDJ","value":"高位金叉区 (K 87.8 D 84.9 J 93.8)","tone":"positive"}]},{"type":"metric_grid","title":"量价关系","items":[{"label":"量比","value":"2.02","tone":"positive"},{"label":"量能","value":"明显放量 (量比2.02)","tone":"positive"},{"label":"价量","value":"价跌量增","tone":"risk"},{"label":"换手","value":17.2699,"tone":"neutral","unit":"%"}]}]},{"id":"weekly","title":"周线状态","cards":[{"type":"metric_grid","title":"周线趋势","items":[{"label":"周期","value":"未完成","tone":"muted"},{"label":"强弱","value":"偏强 4/4","tone":"positive"},{"label":"MACD","value":"金叉区 (DIF 1.871)","tone":"positive"},{"label":"RSI14","value":"68.7 (中性偏强)","tone":"positive"},{"label":"KDJ","value":"中位金叉区 (K 65.3 D 50.5 J 94.9)","tone":"positive"}]},{"type":"metric_grid","title":"均线","items":[{"label":"MA5","value":32.032,"tone":"neutral"},{"label":"MA10","value":30.359,"tone":"neutral"},{"label":"MA20","value":29.0865,"tone":"neutral"},{"label":"MA60","value":26.9375,"tone":"neutral"}]},{"type":"signal_list","title":"风险提示","items":[{"label":"风险","value":"追涨风险","tone":"risk"}]},{"type":"metric_grid","title":"量价关系","items":[{"label":"量比","value":"0.63","tone":"risk"},{"label":"量能","value":"缩量 (量比0.63)","tone":"risk"},{"label":"价量","value":"价跌量缩","tone":"risk"}]}]}],"disclaimer":"仅供研究复盘，不构成投资建议。"},"chart_payload":{"schema_version":"1.0","ticker":"000938.SZ","name":"紫光股份","timeframe":"1d","candles":[{"date":"2025-06-18","open":23.01,"high":23.21,"low":22.85,"close":23.1,"volume":28151783.0,"amount":648187973.72,"turnover":0.9843,"pct_chg":0.0433},{"date":"2025-06-19","open":23.0,"high":23.2,"low":22.72,"close":22.81,"volume":29019974.0,"amount":665695427.77,"turnover":1.0147,"pct_chg":-1.2554},{"date":"2025-06-20","open":22.82,"high":22.93,"low":22.46,"close":22.71,"volume":34135569.0,"amount":772079482.58,"turnover":1.1935,"pct_chg":-0.4384},{"date":"2025-06-23","open":22.51,"high":22.88,"low":22.35,"close":22.8,"volume":24534238.0,"amount":556515118.36,"turnover":0.8578,"pct_chg":0.3963},{"date":"2025-06-24","open":22.89,"high":23.38,"low":22.87,"close":23.32,"volume":40223015.0,"amount":933637467.16,"turnover":1.4064,"pct_chg":2.2807},{"date":"2025-06-25","open":23.38,"high":23.72,"low":23.27,"close":23.71,"volume":48669584.0,"amount":1144810519.73,"turnover":1.7017,"pct_chg":1.6724},{"date":"2025-06-26","open":23.76,"high":23.94,"low":23.56,"close":23.57,"volume":41397229.0,"amount":982883954.95,"turnover":1.4474,"pct_chg":-0.5905},{"date":"2025-06-27","open":23.6,"high":23.87,"low":23.49,"close":23.66,"volume":40737471.0,"amount":966020533.78,"turnover":1.4243,"pct_chg":0.3818},{"date":"2025-06-30","open":23.68,"high":24.05,"low":23.67,"close":23.99,"volume":38791960.0,"amount":927444333.46,"turnover":1.3563,"pct_chg":1.3948},{"date":"2025-07-01","open":23.98,"high":23.99,"low":23.62,"close":23.85,"volume":31874996.0,"amount":758902281.85,"turnover":1.1145,"pct_chg":-0.5836},{"date":"2025-07-02","open":23.76,"high":23.85,"low":23.37,"close":23.5,"volume":29831708.0,"amount":701629911.14,"turnover":1.043,"pct_chg":-1.4675},{"date":"2025-07-03","open":23.5,"high":23.95,"low":23.44,"close":23.89,"volume":37698721.0,"amount":897457669.72,"turnover":1.3181,"pct_chg":1.6596},{"date":"2025-07-04","open":23.82,"high":23.99,"low":23.63,"close":23.65,"volume":31738735.0,"amount":754749380.64,"turnover":1.1097,"pct_chg":-1.0046},{"date":"2025-07-07","open":23.6,"high":23.62,"low":23.34,"close":23.38,"volume":23786850.0,"amount":557087639.2,"turnover":0.8317,"pct_chg":-1.1416},{"date":"2025-07-08","open":23.41,"high":24.25,"low":23.41,"close":24.16,"volume":72138770.0,"amount":1732844218.77,"turnover":2.5223,"pct_chg":3.3362},{"date":"2025-07-09","open":24.18,"high":24.27,"low":23.91,"close":23.98,"volume":36559561.0,"amount":880802274.91,"turnover":1.2783,"pct_chg":-0.745},{"date":"2025-07-10","open":24.0,"high":24.14,"low":23.9,"close":24.03,"volume":28914705.0,"amount":694441043.24,"turnover":1.011,"pct_chg":0.2085},{"date":"2025-07-11","open":24.08,"high":24.4,"low":23.88,"close":24.24,"volume":46676417.0,"amount":1130182642.45,"turnover":1.632,"pct_chg":0.8739},{"date":"2025-07-14","open":24.33,"high":24.65,"low":24.15,"close":24.15,"volume":52243111.0,"amount":1272788837.34,"turnover":1.8266,"pct_chg":-0.3713},{"date":"2025-07-15","open":24.15,"high":25.11,"low":24.08,"close":24.85,"volume":98106455.0,"amount":2426010411.08,"turnover":3.4302,"pct_chg":2.8986},{"date":"2025-07-16","open":24.96,"high":25.14,"low":24.6,"close":24.67,"volume":61388865.0,"amount":1525860009.87,"turnover":2.1464,"pct_chg":-0.7243},{"date":"2025-07-17","open":24.61,"high":25.1,"low":24.52,"close":25.02,"volume":54152296.0,"amount":1348197565.66,"turnover":1.8934,"pct_chg":1.4187},{"date":"2025-07-18","open":25.03,"high":25.17,"low":24.75,"close":24.85,"volume":45720747.0,"amount":1138314464.53,"turnover":1.5986,"pct_chg":-0.6795},{"date":"2025-07-21","open":24.77,"high":24.78,"low":24.49,"close":24.72,"volume":46968720.0,"amount":1156538827.89,"turnover":1.6422,"pct_chg":-0.5231},{"date":"2025-07-22","open":24.68,"high":24.82,"low":24.52,"close":24.59,"volume":38931133.0,"amount":957853655.53,"turnover":1.3612,"pct_chg":-0.5259},{"date":"2025-07-23","open":24.56,"high":24.75,"low":24.41,"close":24.45,"volume":39536980.0,"amount":971227761.89,"turnover":1.3824,"pct_chg":-0.5693},{"date":"2025-07-24","open":24.49,"high":24.88,"low":24.46,"close":24.88,"volume":43922822.0,"amount":1084768834.06,"turnover":1.5357,"pct_chg":1.7587},{"date":"2025-07-25","open":24.93,"high":25.1,"low":24.74,"close":25.04,"volume":50911191.0,"amount":1270096657.55,"turnover":1.7801,"pct_chg":0.6431},{"date":"2025-07-28","open":25.19,"high":25.19,"low":24.72,"close":24.84,"volume":38502059.0,"amount":957060000.22,"turnover":1.3462,"pct_chg":-0.7987},{"date":"2025-07-29","open":24.77,"high":25.15,"low":24.43,"close":25.1,"volume":58211575.0,"amount":1447329649.67,"turnover":2.0353,"pct_chg":1.0467},{"date":"2025-07-30","open":24.96,"high":25.1,"low":24.58,"close":24.75,"volume":49872618.0,"amount":1238334217.99,"turnover":1.7437,"pct_chg":-1.3944},{"date":"2025-07-31","open":24.67,"high":25.44,"low":24.62,"close":24.73,"volume":92329437.0,"amount":2319258607.78,"turnover":3.2282,"pct_chg":-0.0808},{"date":"2025-08-01","open":24.9,"high":24.95,"low":24.2,"close":24.5,"volume":63237242.0,"amount":1554501024.02,"turnover":2.211,"pct_chg":-0.93},{"date":"2025-08-04","open":24.23,"high":24.55,"low":24.21,"close":24.54,"volume":29362883.0,"amount":716666811.44,"turnover":1.0266,"pct_chg":0.1633},{"date":"2025-08-05","open":24.55,"high":24.69,"low":24.31,"close":24.51,"volume":46754645.0,"amount":1143366383.36,"turnover":1.6347,"pct_chg":-0.1222},{"date":"2025-08-06","open":24.42,"high":24.91,"low":24.35,"close":24.9,"volume":55903468.0,"amount":1381955901.6,"turnover":1.9546,"pct_chg":1.5912},{"date":"2025-08-07","open":24.9,"high":25.15,"low":24.56,"close":24.75,"volume":44429958.0,"amount":1100013127.2,"turnover":1.5535,"pct_chg":-0.6024},{"date":"2025-08-08","open":24.75,"high":24.75,"low":24.29,"close":24.31,"volume":45651614.0,"amount":1113762257.11,"turnover":1.5962,"pct_chg":-1.7778},{"date":"2025-08-11","open":24.3,"high":24.83,"low":24.28,"close":24.8,"volume":54729731.0,"amount":1349788168.97,"turnover":1.9136,"pct_chg":2.0156},{"date":"2025-08-12","open":24.76,"high":25.08,"low":24.57,"close":24.98,"volume":58792313.0,"amount":1463801440.36,"turnover":2.0556,"pct_chg":0.7258},{"date":"2025-08-13","open":24.99,"high":25.58,"low":24.88,"close":25.33,"volume":94753898.0,"amount":2397398225.7,"turnover":3.313,"pct_chg":1.4011},{"date":"2025-08-14","open":25.3,"high":25.76,"low":25.0,"close":25.12,"volume":84918433.0,"amount":2152419815.73,"turnover":2.9691,"pct_chg":-0.8291},{"date":"2025-08-15","open":25.0,"high":25.49,"low":24.94,"close":25.4,"volume":65450538.0,"amount":1657101022.07,"turnover":2.2884,"pct_chg":1.1146},{"date":"2025-08-18","open":25.6,"high":26.82,"low":25.56,"close":26.46,"volume":133824772.0,"amount":3531524489.43,"turnover":4.6791,"pct_chg":4.1732},{"date":"2025-08-19","open":26.61,"high":26.62,"low":26.12,"close":26.2,"volume":82446010.0,"amount":2169788041.28,"turnover":2.8826,"pct_chg":-0.9826},{"date":"2025-08-20","open":26.1,"high":28.17,"low":25.85,"close":27.71,"volume":183499470.0,"amount":4958632117.71,"turnover":6.4159,"pct_chg":5.7634},{"date":"2025-08-21","open":27.76,"high":28.5,"low":27.06,"close":27.25,"volume":156646576.0,"amount":4349726415.64,"turnover":5.477,"pct_chg":-1.6601},{"date":"2025-08-22","open":27.49,"high":28.73,"low":27.2,"close":28.5,"volume":183619133.0,"amount":5164727134.57,"turnover":6.4201,"pct_chg":4.5872},{"date":"2025-08-25","open":29.05,"high":29.21,"low":28.06,"close":28.62,"volume":172971753.0,"amount":4946907644.43,"turnover":6.0478,"pct_chg":0.4211},{"date":"2025-08-26","open":28.41,"high":28.96,"low":28.2,"close":28.25,"volume":108121007.0,"amount":3078817519.77,"turnover":3.7803,"pct_chg":-1.2928},{"date":"2025-08-27","open":28.41,"high":28.77,"low":27.4,"close":27.47,"volume":152354329.0,"amount":4296107404.48,"turnover":5.3269,"pct_chg":-2.7611},{"date":"2025-08-28","open":27.25,"high":28.39,"low":27.25,"close":28.39,"volume":133577479.0,"amount":3722133127.23,"turnover":4.6704,"pct_chg":3.3491},{"date":"2025-08-29","open":28.2,"high":28.24,"low":27.63,"close":27.9,"volume":87747798.0,"amount":2446382435.5,"turnover":3.068,"pct_chg":-1.726},{"date":"2025-09-01","open":29.81,"high":30.0,"low":28.46,"close":29.09,"volume":241475073.0,"amount":7053880678.81,"turnover":8.4429,"pct_chg":4.2652},{"date":"2025-09-02","open":28.99,"high":29.0,"low":27.21,"close":27.41,"volume":151784488.0,"amount":4238238464.13,"turnover":5.307,"pct_chg":-5.7752},{"date":"2025-09-03","open":27.6,"high":30.15,"low":27.38,"close":28.66,"volume":315533245.0,"amount":9232552842.64,"turnover":11.0323,"pct_chg":4.5604},{"date":"2025-09-04","open":28.91,"high":29.0,"low":27.08,"close":27.66,"volume":230385716.0,"amount":6487045042.81,"turnover":8.0552,"pct_chg":-3.4892},{"date":"2025-09-05","open":27.8,"high":28.37,"low":26.9,"close":28.13,"volume":161364431.0,"amount":4469193915.85,"turnover":5.642,"pct_chg":1.6992},{"date":"2025-09-08","open":28.13,"high":28.38,"low":27.32,"close":27.8,"volume":117230571.0,"amount":3251951227.83,"turnover":4.0989,"pct_chg":-1.1731},{"date":"2025-09-09","open":27.51,"high":27.51,"low":26.28,"close":26.35,"volume":134313022.0,"amount":3586717144.56,"turnover":4.6961,"pct_chg":-5.2158},{"date":"2025-09-10","open":26.46,"high":27.03,"low":26.35,"close":26.51,"volume":80345434.0,"amount":2142609801.65,"turnover":2.8092,"pct_chg":0.6072},{"date":"2025-09-11","open":26.65,"high":28.78,"low":26.36,"close":28.67,"volume":219234223.0,"amount":6114944950.89,"turnover":7.6653,"pct_chg":8.1479},{"date":"2025-09-12","open":28.35,"high":30.21,"low":28.19,"close":29.28,"volume":216282788.0,"amount":6314718907.49,"turnover":7.5621,"pct_chg":2.1277},{"date":"2025-09-15","open":29.27,"high":29.32,"low":28.66,"close":28.76,"volume":121783235.0,"amount":3520966242.61,"turnover":4.258,"pct_chg":-1.776},{"date":"2025-09-16","open":28.77,"high":29.86,"low":28.62,"close":29.64,"volume":165770501.0,"amount":4875239454.6,"turnover":5.796,"pct_chg":3.0598},{"date":"2025-09-17","open":29.25,"high":29.73,"low":28.92,"close":29.41,"volume":116618490.0,"amount":3416455549.09,"turnover":4.0775,"pct_chg":-0.776},{"date":"2025-09-18","open":29.48,"high":31.88,"low":29.42,"close":30.94,"volume":310805146.0,"amount":9571536865.05,"turnover":10.867,"pct_chg":5.2023},{"date":"2025-09-19","open":31.29,"high":31.49,"low":30.01,"close":30.15,"volume":157558380.0,"amount":4819027296.93,"turnover":5.5089,"pct_chg":-2.5533},{"date":"2025-09-22","open":30.64,"high":30.77,"low":29.88,"close":30.47,"volume":144418233.0,"amount":4389738216.22,"turnover":5.0494,"pct_chg":1.0614},{"date":"2025-09-23","open":30.79,"high":30.95,"low":28.68,"close":29.44,"volume":169184137.0,"amount":4997641496.63,"turnover":5.9154,"pct_chg":-3.3804},{"date":"2025-09-24","open":29.34,"high":31.21,"low":29.16,"close":30.5,"volume":167324412.0,"amount":5062258226.04,"turnover":5.8503,"pct_chg":3.6005},{"date":"2025-09-25","open":30.5,"high":32.16,"low":30.3,"close":31.51,"volume":195832616.0,"amount":6156681855.62,"turnover":6.8471,"pct_chg":3.3115},{"date":"2025-09-26","open":31.11,"high":31.31,"low":29.93,"close":29.93,"volume":163395484.0,"amount":4973814050.35,"turnover":5.713,"pct_chg":-5.0143},{"date":"2025-09-29","open":30.27,"high":30.7,"low":29.91,"close":30.12,"volume":101682565.0,"amount":3069550152.81,"turnover":3.5552,"pct_chg":0.6348},{"date":"2025-09-30","open":30.2,"high":30.76,"low":29.98,"close":30.18,"volume":110213096.0,"amount":3329428152.3,"turnover":3.8535,"pct_chg":0.1992},{"date":"2025-10-09","open":30.51,"high":32.06,"low":30.4,"close":31.05,"volume":183432232.0,"amount":5732819246.59,"turnover":6.4135,"pct_chg":2.8827},{"date":"2025-10-10","open":30.53,"high":30.63,"low":29.1,"close":29.29,"volume":149766488.0,"amount":4455396191.67,"turnover":5.2364,"pct_chg":-5.6683},{"date":"2025-10-13","open":28.5,"high":29.29,"low":28.22,"close":29.01,"volume":102554279.0,"amount":2948907290.43,"turnover":3.5857,"pct_chg":-0.956},{"date":"2025-10-14","open":29.2,"high":29.99,"low":27.72,"close":27.87,"volume":128266479.0,"amount":3685383454.49,"turnover":4.4847,"pct_chg":-3.9297},{"date":"2025-10-15","open":27.95,"high":28.46,"low":27.55,"close":28.43,"volume":72642160.0,"amount":2036885952.7,"turnover":2.5399,"pct_chg":2.0093},{"date":"2025-10-16","open":28.08,"high":28.9,"low":27.98,"close":28.24,"volume":78359209.0,"amount":2224793714.51,"turnover":2.7398,"pct_chg":-0.6683},{"date":"2025-10-17","open":28.62,"high":28.84,"low":27.05,"close":27.09,"volume":88901326.0,"amount":2459033002.13,"turnover":3.1084,"pct_chg":-4.0722},{"date":"2025-10-20","open":27.55,"high":27.85,"low":27.19,"close":27.37,"volume":65474079.0,"amount":1804356608.29,"turnover":2.2892,"pct_chg":1.0336},{"date":"2025-10-21","open":27.47,"high":28.13,"low":27.37,"close":28.05,"volume":80936664.0,"amount":2256447001.29,"turnover":2.8299,"pct_chg":2.4845},{"date":"2025-10-22","open":27.72,"high":28.0,"low":27.42,"close":27.69,"volume":52509359.0,"amount":1453545023.29,"turnover":1.8359,"pct_chg":-1.2834},{"date":"2025-10-23","open":28.0,"high":28.18,"low":26.88,"close":27.37,"volume":67627565.0,"amount":1845620918.88,"turnover":2.3645,"pct_chg":-1.1557},{"date":"2025-10-24","open":27.51,"high":28.12,"low":27.51,"close":28.11,"volume":72682061.0,"amount":2023304296.7,"turnover":2.5413,"pct_chg":2.7037},{"date":"2025-10-27","open":28.35,"high":28.64,"low":27.84,"close":28.56,"volume":89876512.0,"amount":2543694681.12,"turnover":3.1424,"pct_chg":1.6009},{"date":"2025-10-28","open":28.23,"high":28.85,"low":28.11,"close":28.33,"volume":74620492.0,"amount":2124468472.03,"turnover":2.609,"pct_chg":-0.8053},{"date":"2025-10-29","open":28.28,"high":28.63,"low":28.1,"close":28.51,"volume":67352897.0,"amount":1913257894.89,"turnover":2.3549,"pct_chg":0.6354},{"date":"2025-10-30","open":28.46,"high":28.88,"low":28.0,"close":28.1,"volume":77836196.0,"amount":2204482535.31,"turnover":2.7215,"pct_chg":-1.4381},{"date":"2025-10-31","open":27.4,"high":27.5,"low":27.0,"close":27.08,"volume":97840536.0,"amount":2662847626.16,"turnover":3.4209,"pct_chg":-3.6299},{"date":"2025-11-03","open":27.0,"high":27.3,"low":26.4,"close":27.21,"volume":73705802.0,"amount":1974346314.08,"turnover":2.5771,"pct_chg":0.4801},{"date":"2025-11-04","open":27.07,"high":27.07,"low":26.5,"close":26.66,"volume":50635196.0,"amount":1354149858.83,"turnover":1.7704,"pct_chg":-2.0213},{"date":"2025-11-05","open":26.23,"high":26.63,"low":26.12,"close":26.44,"volume":46154470.0,"amount":1217243171.79,"turnover":1.6137,"pct_chg":-0.8252},{"date":"2025-11-06","open":26.5,"high":26.86,"low":26.42,"close":26.68,"volume":47903870.0,"amount":1275682298.97,"turnover":1.6749,"pct_chg":0.9077},{"date":"2025-11-07","open":26.42,"high":26.58,"low":26.18,"close":26.29,"volume":41286915.0,"amount":1088008190.91,"turnover":1.4436,"pct_chg":-1.4618},{"date":"2025-11-10","open":26.37,"high":26.56,"low":26.2,"close":26.45,"volume":36612288.0,"amount":964848068.15,"turnover":1.2801,"pct_chg":0.6086},{"date":"2025-11-11","open":26.55,"high":26.6,"low":26.06,"close":26.12,"volume":42126222.0,"amount":1106191957.55,"turnover":1.4729,"pct_chg":-1.2476},{"date":"2025-11-12","open":26.28,"high":26.3,"low":25.53,"close":25.83,"volume":43652403.0,"amount":1127627727.86,"turnover":1.5263,"pct_chg":-1.1103},{"date":"2025-11-13","open":25.7,"high":26.03,"low":25.63,"close":25.9,"volume":33560257.0,"amount":867470660.87,"turnover":1.1734,"pct_chg":0.271},{"date":"2025-11-14","open":25.65,"high":25.79,"low":25.33,"close":25.35,"volume":37212193.0,"amount":951600517.33,"turnover":1.3011,"pct_chg":-2.1236},{"date":"2025-11-17","open":25.29,"high":25.57,"low":25.25,"close":25.41,"volume":26456068.0,"amount":671689790.59,"turnover":0.925,"pct_chg":0.2367},{"date":"2025-11-18","open":25.55,"high":25.96,"low":25.41,"close":25.75,"volume":46908663.0,"amount":1210360861.43,"turnover":1.6401,"pct_chg":1.3381},{"date":"2025-11-19","open":25.75,"high":25.85,"low":25.12,"close":25.34,"volume":35582535.0,"amount":904637637.07,"turnover":1.2441,"pct_chg":-1.5922},{"date":"2025-11-20","open":25.3,"high":25.54,"low":24.58,"close":24.61,"volume":56888829.0,"amount":1418621717.35,"turnover":1.9891,"pct_chg":-2.8808},{"date":"2025-11-21","open":24.3,"high":24.5,"low":24.06,"close":24.08,"volume":47351777.0,"amount":1149745811.23,"turnover":1.6556,"pct_chg":-2.1536},{"date":"2025-11-24","open":24.26,"high":24.57,"low":24.01,"close":24.45,"volume":36135327.0,"amount":877942634.51,"turnover":1.2634,"pct_chg":1.5365},{"date":"2025-11-25","open":24.76,"high":25.03,"low":24.58,"close":24.7,"volume":46511820.0,"amount":1154899441.06,"turnover":1.6262,"pct_chg":1.0225},{"date":"2025-11-26","open":24.64,"high":25.35,"low":24.61,"close":24.98,"volume":49722816.0,"amount":1245190182.82,"turnover":1.7385,"pct_chg":1.1336},{"date":"2025-11-27","open":24.89,"high":25.33,"low":24.77,"close":24.8,"volume":37442778.0,"amount":937857244.15,"turnover":1.3092,"pct_chg":-0.7206},{"date":"2025-11-28","open":24.75,"high":24.93,"low":24.66,"close":24.92,"volume":26802125.0,"amount":665785498.48,"turnover":0.9371,"pct_chg":0.4839},{"date":"2025-12-01","open":25.06,"high":25.47,"low":24.95,"close":25.46,"volume":49920397.0,"amount":1263377234.24,"turnover":1.7454,"pct_chg":2.1669},{"date":"2025-12-02","open":25.32,"high":25.4,"low":25.06,"close":25.11,"volume":30381950.0,"amount":764855618.31,"turnover":1.0623,"pct_chg":-1.3747},{"date":"2025-12-03","open":25.1,"high":25.28,"low":24.76,"close":24.81,"volume":25168031.0,"amount":626649761.13,"turnover":0.88,"pct_chg":-1.1947},{"date":"2025-12-04","open":24.81,"high":25.02,"low":24.59,"close":24.97,"volume":23429974.0,"amount":582132765.52,"turnover":0.8192,"pct_chg":0.6449},{"date":"2025-12-05","open":24.97,"high":25.15,"low":24.66,"close":24.99,"volume":32862211.0,"amount":819247174.34,"turnover":1.149,"pct_chg":0.0801},{"date":"2025-12-08","open":25.06,"high":25.58,"low":25.03,"close":25.43,"volume":48666244.0,"amount":1236387096.85,"turnover":1.7016,"pct_chg":1.7607},{"date":"2025-12-09","open":25.8,"high":26.15,"low":25.39,"close":25.48,"volume":58513753.0,"amount":1504798375.21,"turnover":2.0459,"pct_chg":0.1966},{"date":"2025-12-10","open":25.28,"high":25.57,"low":25.03,"close":25.5,"volume":34528960.0,"amount":872699329.95,"turnover":1.2073,"pct_chg":0.0785},{"date":"2025-12-11","open":25.49,"high":25.49,"low":24.65,"close":24.66,"volume":45614682.0,"amount":1139736291.71,"turnover":1.5949,"pct_chg":-3.2941},{"date":"2025-12-12","open":24.63,"high":25.18,"low":24.5,"close":25.05,"volume":48792135.0,"amount":1217427007.88,"turnover":1.706,"pct_chg":1.5815},{"date":"2025-12-15","open":24.86,"high":24.89,"low":24.41,"close":24.42,"volume":41393128.0,"amount":1019204592.21,"turnover":1.4473,"pct_chg":-2.515},{"date":"2025-12-16","open":24.36,"high":24.45,"low":23.92,"close":23.98,"volume":36603924.0,"amount":880924091.38,"turnover":1.2798,"pct_chg":-1.8018},{"date":"2025-12-17","open":24.0,"high":24.53,"low":23.9,"close":24.5,"volume":38208542.0,"amount":925267543.34,"turnover":1.3359,"pct_chg":2.1685},{"date":"2025-12-18","open":24.25,"high":24.57,"low":24.15,"close":24.32,"volume":26778778.0,"amount":653696028.48,"turnover":0.9363,"pct_chg":-0.7347},{"date":"2025-12-19","open":24.45,"high":24.72,"low":24.43,"close":24.43,"volume":28456199.0,"amount":699229290.6,"turnover":0.9949,"pct_chg":0.4523},{"date":"2025-12-22","open":24.56,"high":24.97,"low":24.51,"close":24.83,"volume":37987029.0,"amount":943431183.3,"turnover":1.3282,"pct_chg":1.6373},{"date":"2025-12-23","open":24.8,"high":24.94,"low":24.55,"close":24.69,"volume":29237439.0,"amount":723061779.04,"turnover":1.0223,"pct_chg":-0.5638},{"date":"2025-12-24","open":24.3,"high":24.66,"low":24.11,"close":24.64,"volume":44264997.0,"amount":1082500185.45,"turnover":1.5477,"pct_chg":-0.2025},{"date":"2025-12-25","open":24.65,"high":24.77,"low":24.43,"close":24.63,"volume":30361582.0,"amount":747311913.71,"turnover":1.0616,"pct_chg":-0.0406},{"date":"2025-12-26","open":24.58,"high":24.99,"low":24.53,"close":24.76,"volume":41459625.0,"amount":1027626940.39,"turnover":1.4496,"pct_chg":0.5278},{"date":"2025-12-29","open":24.77,"high":25.13,"low":24.68,"close":24.75,"volume":38465905.0,"amount":956993379.39,"turnover":1.3449,"pct_chg":-0.0404},{"date":"2025-12-30","open":24.69,"high":24.92,"low":24.58,"close":24.73,"volume":35492614.0,"amount":879630874.19,"turnover":1.241,"pct_chg":-0.0808},{"date":"2025-12-31","open":24.73,"high":24.79,"low":24.47,"close":24.6,"volume":34787409.0,"amount":856636038.29,"turnover":1.2163,"pct_chg":-0.5257},{"date":"2026-01-05","open":24.7,"high":25.25,"low":24.7,"close":25.25,"volume":64172776.0,"amount":1610582581.35,"turnover":2.2437,"pct_chg":2.6423},{"date":"2026-01-06","open":25.26,"high":25.52,"low":25.13,"close":25.49,"volume":60973320.0,"amount":1546917365.4,"turnover":2.1319,"pct_chg":0.9505},{"date":"2026-01-07","open":25.5,"high":25.72,"low":25.3,"close":25.4,"volume":59535187.0,"amount":1516291509.27,"turnover":2.0816,"pct_chg":-0.3531},{"date":"2026-01-08","open":25.46,"high":25.88,"low":25.46,"close":25.69,"volume":66479156.0,"amount":1710004570.08,"turnover":2.3244,"pct_chg":1.1417},{"date":"2026-01-09","open":25.6,"high":26.06,"low":25.48,"close":25.91,"volume":67089946.0,"amount":1734038494.56,"turnover":2.3457,"pct_chg":0.8564},{"date":"2026-01-12","open":26.25,"high":27.08,"low":26.22,"close":27.0,"volume":120037712.0,"amount":3215014559.98,"turnover":4.197,"pct_chg":4.2069},{"date":"2026-01-13","open":27.2,"high":27.3,"low":26.04,"close":26.17,"volume":91583050.0,"amount":2428118796.82,"turnover":3.2021,"pct_chg":-3.0741},{"date":"2026-01-14","open":26.28,"high":27.25,"low":26.28,"close":27.08,"volume":134237329.0,"amount":3609317887.75,"turnover":4.6935,"pct_chg":3.4773},{"date":"2026-01-15","open":26.9,"high":26.98,"low":26.57,"close":26.89,"volume":72312630.0,"amount":1935829759.37,"turnover":2.5283,"pct_chg":-0.7016},{"date":"2026-01-16","open":27.2,"high":27.5,"low":26.84,"close":27.07,"volume":93623572.0,"amount":2535941344.59,"turnover":3.2735,"pct_chg":0.6694},{"date":"2026-01-19","open":27.81,"high":28.3,"low":27.21,"close":27.82,"volume":152417279.0,"amount":4235192446.0,"turnover":5.3291,"pct_chg":2.7706},{"date":"2026-01-20","open":27.79,"high":28.06,"low":26.66,"close":26.75,"volume":117168836.0,"amount":3183982845.76,"turnover":4.0967,"pct_chg":-3.8462},{"date":"2026-01-21","open":26.23,"high":27.1,"low":26.0,"close":26.59,"volume":91906366.0,"amount":2451741933.73,"turnover":3.2134,"pct_chg":-0.5981},{"date":"2026-01-22","open":27.12,"high":27.49,"low":26.32,"close":26.39,"volume":73548312.0,"amount":1961445480.99,"turnover":2.5715,"pct_chg":-0.7522},{"date":"2026-01-23","open":26.45,"high":26.61,"low":26.25,"close":26.56,"volume":63617455.0,"amount":1682380474.44,"turnover":2.2243,"pct_chg":0.6442},{"date":"2026-01-26","open":26.53,"high":27.08,"low":25.79,"close":26.0,"volume":81752746.0,"amount":2148445246.76,"turnover":2.8584,"pct_chg":-2.1084},{"date":"2026-01-27","open":25.93,"high":26.17,"low":25.29,"close":25.88,"volume":69124604.0,"amount":1777412778.42,"turnover":2.4169,"pct_chg":-0.4615},{"date":"2026-01-28","open":26.11,"high":26.32,"low":25.64,"close":25.73,"volume":58249767.0,"amount":1509352782.97,"turnover":2.0366,"pct_chg":-0.5796},{"date":"2026-01-29","open":25.73,"high":26.2,"low":25.45,"close":25.52,"volume":67137690.0,"amount":1732883951.85,"turnover":2.3474,"pct_chg":-0.8162},{"date":"2026-01-30","open":25.29,"high":25.47,"low":24.66,"close":25.02,"volume":58230975.0,"amount":1457478812.15,"turnover":2.036,"pct_chg":-1.9592},{"date":"2026-02-02","open":24.95,"high":25.25,"low":24.44,"close":24.49,"volume":51822865.0,"amount":1288793878.98,"turnover":1.8119,"pct_chg":-2.1183},{"date":"2026-02-03","open":24.74,"high":24.89,"low":24.46,"close":24.89,"volume":38583544.0,"amount":954170955.78,"turnover":1.349,"pct_chg":1.6333},{"date":"2026-02-04","open":24.7,"high":24.81,"low":24.41,"close":24.81,"volume":40007530.0,"amount":984865030.54,"turnover":1.3988,"pct_chg":-0.3214},{"date":"2026-02-05","open":24.61,"high":24.74,"low":24.42,"close":24.47,"volume":31828332.0,"amount":780561828.25,"turnover":1.1128,"pct_chg":-1.3704},{"date":"2026-02-06","open":24.29,"high":24.62,"low":24.11,"close":24.35,"volume":33393282.0,"amount":814441784.19,"turnover":1.1676,"pct_chg":-0.4904},{"date":"2026-02-09","open":24.79,"high":25.24,"low":24.65,"close":25.15,"volume":56626952.0,"amount":1413996222.44,"turnover":1.9799,"pct_chg":3.2854},{"date":"2026-02-10","open":25.2,"high":25.63,"low":25.08,"close":25.31,"volume":43856735.0,"amount":1113286247.38,"turnover":1.5334,"pct_chg":0.6362},{"date":"2026-02-11","open":25.18,"high":25.42,"low":25.1,"close":25.13,"volume":27445256.0,"amount":692789201.35,"turnover":0.9596,"pct_chg":-0.7112},{"date":"2026-02-12","open":25.17,"high":25.74,"low":25.08,"close":25.62,"volume":55658112.0,"amount":1416482495.54,"turnover":1.946,"pct_chg":1.9499},{"date":"2026-02-13","open":25.4,"high":25.88,"low":25.36,"close":25.5,"volume":42163162.0,"amount":1081072052.81,"turnover":1.4742,"pct_chg":-0.4684},{"date":"2026-02-24","open":25.99,"high":25.99,"low":25.2,"close":25.46,"volume":43232072.0,"amount":1100889949.36,"turnover":1.5116,"pct_chg":-0.1569},{"date":"2026-02-25","open":25.48,"high":25.55,"low":25.21,"close":25.28,"volume":46412819.0,"amount":1175969011.43,"turnover":1.6228,"pct_chg":-0.707},{"date":"2026-02-26","open":25.31,"high":25.86,"low":25.31,"close":25.73,"volume":54800832.0,"amount":1405091547.59,"turnover":1.9161,"pct_chg":1.7801},{"date":"2026-02-27","open":25.55,"high":26.09,"low":25.34,"close":25.95,"volume":57328517.0,"amount":1478386304.8,"turnover":2.0044,"pct_chg":0.855},{"date":"2026-03-02","open":25.51,"high":25.68,"low":24.97,"close":25.08,"volume":59089872.0,"amount":1492815855.61,"turnover":2.066,"pct_chg":-3.3526},{"date":"2026-03-03","open":25.17,"high":25.45,"low":23.77,"close":23.86,"volume":76568093.0,"amount":1872691712.92,"turnover":2.6771,"pct_chg":-4.8644},{"date":"2026-03-04","open":23.6,"high":24.06,"low":23.4,"close":23.56,"volume":48059887.0,"amount":1138809632.65,"turnover":1.6804,"pct_chg":-1.2573},{"date":"2026-03-05","open":24.0,"high":24.6,"low":23.9,"close":24.1,"volume":51550679.0,"amount":1247309425.29,"turnover":1.8024,"pct_chg":2.292},{"date":"2026-03-06","open":23.98,"high":24.23,"low":23.91,"close":24.13,"volume":29008051.0,"amount":699200705.46,"turnover":1.0142,"pct_chg":0.1245},{"date":"2026-03-09","open":23.66,"high":24.34,"low":23.23,"close":24.26,"volume":58872701.0,"amount":1393099879.77,"turnover":2.0584,"pct_chg":0.5387},{"date":"2026-03-10","open":24.7,"high":25.12,"low":24.4,"close":24.92,"volume":59436974.0,"amount":1472507234.24,"turnover":2.0782,"pct_chg":2.7205},{"date":"2026-03-11","open":24.86,"high":25.46,"low":24.78,"close":25.23,"volume":61142814.0,"amount":1540063687.46,"turnover":2.1378,"pct_chg":1.244},{"date":"2026-03-12","open":25.01,"high":27.75,"low":25.0,"close":26.52,"volume":207864376.0,"amount":5555842437.73,"turnover":7.2678,"pct_chg":5.113},{"date":"2026-03-13","open":26.15,"high":26.45,"low":25.72,"close":25.8,"volume":106021324.0,"amount":2754297220.77,"turnover":3.7069,"pct_chg":-2.7149},{"date":"2026-03-16","open":25.8,"high":25.93,"low":24.91,"close":25.39,"volume":71034649.0,"amount":1793097734.51,"turnover":2.4837,"pct_chg":-1.5891},{"date":"2026-03-17","open":25.5,"high":25.52,"low":24.42,"close":24.45,"volume":69881051.0,"amount":1737236531.91,"turnover":2.4433,"pct_chg":-3.7022},{"date":"2026-03-18","open":24.5,"high":26.69,"low":24.41,"close":26.3,"volume":136567172.0,"amount":3487029226.91,"turnover":4.7749,"pct_chg":7.5665},{"date":"2026-03-19","open":25.85,"high":27.5,"low":25.73,"close":26.77,"volume":185804165.0,"amount":4963290052.37,"turnover":6.4965,"pct_chg":1.7871},{"date":"2026-03-20","open":26.78,"high":26.98,"low":26.09,"close":26.18,"volume":111039134.0,"amount":2945381297.55,"turnover":3.8824,"pct_chg":-2.204},{"date":"2026-03-23","open":25.68,"high":26.5,"low":25.13,"close":25.4,"volume":101694504.0,"amount":2611554712.74,"turnover":3.5557,"pct_chg":-2.9794},{"date":"2026-03-24","open":25.72,"high":25.83,"low":24.83,"close":25.7,"volume":99837932.0,"amount":2538696630.13,"turnover":3.4907,"pct_chg":1.1811},{"date":"2026-03-25","open":25.69,"high":26.7,"low":25.67,"close":26.34,"volume":106186124.0,"amount":2794206612.48,"turnover":3.7127,"pct_chg":2.4903},{"date":"2026-03-26","open":26.1,"high":26.29,"low":25.31,"close":25.4,"volume":74983115.0,"amount":1931647118.76,"turnover":2.6217,"pct_chg":-3.5687},{"date":"2026-03-27","open":24.9,"high":25.67,"low":24.3,"close":25.14,"volume":91340134.0,"amount":2267844368.84,"turnover":3.1936,"pct_chg":-1.0236},{"date":"2026-03-30","open":24.55,"high":24.95,"low":23.85,"close":24.82,"volume":86436278.0,"amount":2110689534.54,"turnover":3.0222,"pct_chg":-1.2729},{"date":"2026-03-31","open":24.75,"high":25.72,"low":24.46,"close":24.9,"volume":86936413.0,"amount":2181175420.65,"turnover":3.0396,"pct_chg":0.3223},{"date":"2026-04-01","open":25.5,"high":25.96,"low":25.13,"close":25.29,"volume":79711938.0,"amount":2030277565.03,"turnover":2.7871,"pct_chg":1.5663},{"date":"2026-04-02","open":25.05,"high":25.15,"low":24.02,"close":24.2,"volume":85165957.0,"amount":2087194722.75,"turnover":2.9777,"pct_chg":-4.31},{"date":"2026-04-03","open":24.43,"high":26.0,"low":24.27,"close":25.62,"volume":144640485.0,"amount":3665293297.32,"turnover":5.0572,"pct_chg":5.8678},{"date":"2026-04-07","open":25.51,"high":25.86,"low":25.08,"close":25.13,"volume":77436455.0,"amount":1968333905.04,"turnover":2.7075,"pct_chg":-1.9126},{"date":"2026-04-08","open":25.85,"high":26.49,"low":25.82,"close":26.46,"volume":124984923.0,"amount":3272390661.71,"turnover":4.37,"pct_chg":5.2925},{"date":"2026-04-09","open":26.16,"high":27.43,"low":26.03,"close":27.02,"volume":165867813.0,"amount":4444598682.72,"turnover":5.7994,"pct_chg":2.1164},{"date":"2026-04-10","open":27.02,"high":27.76,"low":26.74,"close":27.09,"volume":135986122.0,"amount":3690418696.36,"turnover":4.7546,"pct_chg":0.2591},{"date":"2026-04-13","open":26.93,"high":28.62,"low":26.8,"close":28.24,"volume":217479422.0,"amount":6071364325.22,"turnover":7.604,"pct_chg":4.2451},{"date":"2026-04-14","open":28.09,"high":28.18,"low":27.52,"close":27.86,"volume":139728303.0,"amount":3891913514.0,"turnover":4.8855,"pct_chg":-1.3456},{"date":"2026-04-15","open":27.85,"high":27.97,"low":26.98,"close":27.48,"volume":138609120.0,"amount":3813153403.74,"turnover":4.8463,"pct_chg":-1.364},{"date":"2026-04-16","open":27.56,"high":28.68,"low":27.5,"close":28.09,"volume":150701407.0,"amount":4247694400.85,"turnover":5.2691,"pct_chg":2.2198},{"date":"2026-04-17","open":27.93,"high":28.38,"low":27.66,"close":27.7,"volume":103392759.0,"amount":2886003914.33,"turnover":3.615,"pct_chg":-1.3884},{"date":"2026-04-20","open":27.95,"high":29.15,"low":27.9,"close":28.41,"volume":136187814.0,"amount":3905210625.17,"turnover":4.7617,"pct_chg":2.5632},{"date":"2026-04-21","open":28.08,"high":28.21,"low":27.3,"close":27.61,"volume":94090777.0,"amount":2591716565.43,"turnover":3.2898,"pct_chg":-2.8159},{"date":"2026-04-22","open":27.52,"high":30.37,"low":27.45,"close":29.92,"volume":323135423.0,"amount":9570357043.38,"turnover":11.2982,"pct_chg":8.3665},{"date":"2026-04-23","open":30.52,"high":31.81,"low":30.1,"close":31.2,"volume":319670124.0,"amount":9910213646.06,"turnover":11.177,"pct_chg":4.2781},{"date":"2026-04-24","open":30.88,"high":32.15,"low":30.41,"close":31.32,"volume":247848576.0,"amount":7737031828.61,"turnover":8.6658,"pct_chg":0.3846},{"date":"2026-04-27","open":31.98,"high":32.86,"low":31.25,"close":32.19,"volume":228551343.0,"amount":7349564292.54,"turnover":7.9911,"pct_chg":2.7778},{"date":"2026-04-28","open":31.85,"high":32.28,"low":31.0,"close":31.58,"volume":141452252.0,"amount":4452188772.25,"turnover":4.9458,"pct_chg":-1.895},{"date":"2026-04-29","open":32.5,"high":33.62,"low":31.89,"close":32.42,"volume":255392326.0,"amount":8334139055.29,"turnover":8.9296,"pct_chg":2.6599},{"date":"2026-04-30","open":32.66,"high":32.76,"low":30.74,"close":31.99,"volume":210809542.0,"amount":6695067933.82,"turnover":7.3708,"pct_chg":-1.3263},{"date":"2026-05-06","open":32.47,"high":33.06,"low":31.8,"close":31.85,"volume":244376509.0,"amount":7906131025.3,"turnover":8.5444,"pct_chg":-0.4376},{"date":"2026-05-07","open":32.08,"high":33.13,"low":31.35,"close":32.93,"volume":234899086.0,"amount":7590483693.06,"turnover":8.213,"pct_chg":3.3909},{"date":"2026-05-08","open":32.39,"high":33.59,"low":31.67,"close":33.17,"volume":212798744.0,"amount":6974225407.78,"turnover":7.4403,"pct_chg":0.7288},{"date":"2026-05-11","open":33.78,"high":33.93,"low":31.56,"close":31.69,"volume":282769102.0,"amount":9135895819.72,"turnover":9.8868,"pct_chg":-4.4619},{"date":"2026-05-12","open":32.19,"high":32.3,"low":30.53,"close":30.69,"volume":217969497.0,"amount":6782403864.66,"turnover":7.6211,"pct_chg":-3.1556},{"date":"2026-05-13","open":30.6,"high":33.16,"low":30.35,"close":32.91,"volume":237260135.0,"amount":7568339934.67,"turnover":8.2956,"pct_chg":7.2336},{"date":"2026-05-14","open":33.88,"high":34.49,"low":31.46,"close":32.14,"volume":233491614.0,"amount":7610279255.95,"turnover":8.1638,"pct_chg":-2.3397},{"date":"2026-05-15","open":32.3,"high":33.96,"low":31.66,"close":31.91,"volume":273908225.0,"amount":8967377277.91,"turnover":9.577,"pct_chg":-0.7156},{"date":"2026-05-18","open":31.9,"high":32.62,"low":31.2,"close":31.83,"volume":162540826.0,"amount":5194042040.87,"turnover":5.6831,"pct_chg":-0.2507},{"date":"2026-05-19","open":31.63,"high":32.58,"low":30.51,"close":32.49,"volume":202281232.0,"amount":6381164900.63,"turnover":7.0726,"pct_chg":2.0735},{"date":"2026-05-20","open":32.29,"high":33.08,"low":31.92,"close":32.21,"volume":136923851.0,"amount":4414256145.4,"turnover":4.7874,"pct_chg":-0.8618},{"date":"2026-05-21","open":32.67,"high":32.93,"low":29.05,"close":29.25,"volume":255957311.0,"amount":7894693974.76,"turnover":8.9493,"pct_chg":-9.1897},{"date":"2026-05-22","open":29.62,"high":29.99,"low":29.11,"close":29.86,"volume":153432535.0,"amount":4539277787.06,"turnover":5.3646,"pct_chg":2.0855},{"date":"2026-05-25","open":30.51,"high":31.82,"low":30.02,"close":31.04,"volume":178269230.0,"amount":5500116027.06,"turnover":6.233,"pct_chg":3.9518},{"date":"2026-05-26","open":30.5,"high":30.5,"low":28.19,"close":28.9,"volume":210281079.0,"amount":6082946992.55,"turnover":7.3523,"pct_chg":-6.8943},{"date":"2026-05-27","open":28.78,"high":29.44,"low":27.78,"close":28.02,"volume":152357186.0,"amount":4347242838.73,"turnover":5.327,"pct_chg":-3.045},{"date":"2026-05-28","open":27.99,"high":29.11,"low":27.16,"close":28.92,"volume":169069651.0,"amount":4751272845.83,"turnover":5.9114,"pct_chg":3.212},{"date":"2026-05-29","open":30.03,"high":30.49,"low":27.45,"close":28.64,"volume":255632978.0,"amount":7356950501.77,"turnover":8.938,"pct_chg":-0.9682},{"date":"2026-06-01","open":29.11,"high":29.89,"low":27.65,"close":27.84,"volume":180393593.0,"amount":5157391649.5,"turnover":6.3073,"pct_chg":-2.7933},{"date":"2026-06-02","open":28.29,"high":28.69,"low":27.65,"close":28.21,"volume":150129015.0,"amount":4233144330.11,"turnover":5.2491,"pct_chg":1.329},{"date":"2026-06-03","open":28.67,"high":29.88,"low":27.87,"close":28.22,"volume":216574382.0,"amount":6266226232.41,"turnover":7.5723,"pct_chg":0.0354},{"date":"2026-06-04","open":27.54,"high":28.18,"low":27.21,"close":27.72,"volume":125517428.0,"amount":3484422702.16,"turnover":4.3886,"pct_chg":-1.7718},{"date":"2026-06-05","open":27.31,"high":29.09,"low":26.67,"close":27.87,"volume":226674194.0,"amount":6356007087.66,"turnover":7.9255,"pct_chg":0.5411},{"date":"2026-06-08","open":26.91,"high":27.3,"low":25.6,"close":25.91,"volume":176475647.0,"amount":4669746784.42,"turnover":6.1703,"pct_chg":-7.0327},{"date":"2026-06-09","open":26.16,"high":26.41,"low":25.67,"close":26.38,"volume":114806119.0,"amount":2999097224.73,"turnover":4.0141,"pct_chg":1.814},{"date":"2026-06-10","open":25.9,"high":26.97,"low":25.65,"close":25.92,"volume":118284059.0,"amount":3104787803.35,"turnover":4.1357,"pct_chg":-1.7437},{"date":"2026-06-11","open":25.73,"high":26.01,"low":25.03,"close":25.35,"volume":91225877.0,"amount":2318413715.73,"turnover":3.1896,"pct_chg":-2.1991},{"date":"2026-06-12","open":25.79,"high":25.86,"low":25.12,"close":25.15,"volume":109831732.0,"amount":2802364612.36,"turnover":3.8402,"pct_chg":-0.789},{"date":"2026-06-15","open":25.37,"high":26.58,"low":25.34,"close":26.48,"volume":136285618.0,"amount":3559159325.36,"turnover":4.7651,"pct_chg":5.2883},{"date":"2026-06-16","open":26.48,"high":26.79,"low":26.12,"close":26.78,"volume":102560591.0,"amount":2721707499.62,"turnover":3.5859,"pct_chg":1.1329},{"date":"2026-06-17","open":26.48,"high":28.0,"low":26.36,"close":27.21,"volume":127704022.0,"amount":3474251845.72,"turnover":4.4651,"pct_chg":1.6057},{"date":"2026-06-18","open":27.16,"high":27.94,"low":27.02,"close":27.45,"volume":125208234.0,"amount":3443275011.16,"turnover":4.3778,"pct_chg":0.882},{"date":"2026-06-22","open":27.53,"high":27.94,"low":26.68,"close":27.89,"volume":147328411.0,"amount":4038866524.21,"turnover":5.1512,"pct_chg":1.6029},{"date":"2026-06-23","open":27.8,"high":28.22,"low":26.7,"close":26.91,"volume":115021627.0,"amount":3153038690.8,"turnover":4.0216,"pct_chg":-3.5138},{"date":"2026-06-24","open":26.81,"high":27.66,"low":26.69,"close":27.66,"volume":115890823.0,"amount":3160553151.12,"turnover":4.052,"pct_chg":2.7871},{"date":"2026-06-25","open":27.61,"high":28.57,"low":27.06,"close":28.39,"volume":192026364.0,"amount":5366366377.22,"turnover":6.714,"pct_chg":2.6392},{"date":"2026-06-26","open":27.67,"high":27.73,"low":25.6,"close":25.62,"volume":223675110.0,"amount":5923074242.53,"turnover":7.8206,"pct_chg":-9.757},{"date":"2026-06-29","open":25.5,"high":27.11,"low":25.44,"close":26.24,"volume":155271344.0,"amount":4106876519.25,"turnover":5.4289,"pct_chg":2.42},{"date":"2026-06-30","open":26.0,"high":28.86,"low":25.83,"close":28.86,"volume":167866097.0,"amount":4698481942.81,"turnover":5.8693,"pct_chg":9.9848},{"date":"2026-07-01","open":30.34,"high":31.29,"low":29.45,"close":29.93,"volume":339206614.0,"amount":10312108233.68,"turnover":11.8601,"pct_chg":3.7076},{"date":"2026-07-02","open":29.18,"high":30.42,"low":28.7,"close":29.03,"volume":217379157.0,"amount":6401919439.46,"turnover":7.6005,"pct_chg":-3.007},{"date":"2026-07-03","open":30.5,"high":31.59,"low":30.22,"close":30.28,"volume":246180310.0,"amount":7584138424.93,"turnover":8.6075,"pct_chg":4.3059},{"date":"2026-07-06","open":30.82,"high":33.31,"low":29.58,"close":33.31,"volume":315681432.0,"amount":9933778019.89,"turnover":11.0375,"pct_chg":10.0066},{"date":"2026-07-07","open":31.66,"high":32.66,"low":30.9,"close":31.48,"volume":280355891.0,"amount":8917565681.08,"turnover":9.8024,"pct_chg":-5.4938},{"date":"2026-07-08","open":34.5,"high":34.63,"low":33.32,"close":33.62,"volume":479884868.0,"amount":16415139487.87,"turnover":16.7788,"pct_chg":6.798},{"date":"2026-07-09","open":33.33,"high":35.75,"low":32.82,"close":35.68,"volume":435698684.0,"amount":14996337962.6,"turnover":15.2338,"pct_chg":6.1273},{"date":"2026-07-10","open":36.2,"high":39.25,"low":36.2,"close":38.41,"volume":482836141.0,"amount":18573421371.59,"turnover":16.882,"pct_chg":7.6513},{"date":"2026-07-13","open":38.43,"high":40.28,"low":36.5,"close":38.4,"volume":493931758.0,"amount":19056672592.86,"turnover":17.2699,"pct_chg":-0.026}],"indicators":{"ma":{"ma5":[23.324,23.102,23.0,22.902,22.948,23.07,23.222,23.412,23.65,23.756,23.714,23.778,23.776,23.654,23.716,23.812,23.84,23.958,24.112,24.25,24.388,24.586,24.708,24.822,24.77,24.726,24.698,24.736,24.76,24.862,24.922,24.892,24.784,24.724,24.606,24.636,24.64,24.602,24.654,24.748,24.834,24.908,25.126,25.458,25.702,26.178,26.604,27.224,27.656,28.066,28.018,28.246,28.126,28.22,28.052,28.29,28.144,28.19,27.932,27.72,27.29,27.492,27.722,27.914,28.572,29.152,29.606,29.78,30.122,30.082,30.3,30.414,30.37,30.3,30.448,30.558,30.114,29.93,29.48,29.13,28.568,28.128,27.8,27.836,27.688,27.514,27.718,27.956,28.012,28.176,28.322,28.116,27.846,27.512,27.098,26.814,26.656,26.504,26.396,26.274,26.118,25.93,25.722,25.648,25.55,25.292,25.038,24.846,24.636,24.564,24.602,24.77,24.972,25.054,25.02,25.054,25.068,25.062,25.136,25.274,25.212,25.224,25.022,24.722,24.522,24.454,24.33,24.412,24.554,24.582,24.644,24.71,24.694,24.702,24.694,24.818,24.964,25.094,25.286,25.548,25.898,26.034,26.37,26.61,26.842,27.006,27.122,27.024,26.924,26.822,26.458,26.284,26.112,25.938,25.63,25.328,25.13,24.946,24.736,24.602,24.734,24.818,24.882,25.112,25.342,25.404,25.398,25.518,25.584,25.5,25.18,24.836,24.51,24.146,23.982,24.194,24.528,25.012,25.346,25.572,25.478,25.692,25.742,25.818,25.82,26.07,26.078,25.804,25.596,25.48,25.32,25.11,24.87,24.966,25.028,25.34,25.686,26.264,26.788,27.334,27.538,27.752,27.874,27.908,27.858,28.346,28.968,29.692,30.448,31.242,31.742,31.9,32.006,32.154,32.472,32.326,32.066,32.278,32.12,31.868,31.896,32.256,32.116,31.538,31.128,30.97,30.252,29.414,29.348,29.104,28.464,28.326,28.366,28.126,27.972,27.586,27.22,26.76,26.286,25.742,25.856,25.936,26.194,26.614,27.162,27.248,27.424,27.66,27.294,26.964,27.354,27.808,27.936,28.868,30.282,30.806,31.544,32.874,34.5,35.518],"ma10":[23.916,23.723,23.52,23.316,23.237,23.197,23.162,23.206,23.276,23.352,23.392,23.5,23.594,23.652,23.736,23.763,23.809,23.867,23.883,23.983,24.1,24.213,24.333,24.467,24.51,24.557,24.642,24.722,24.791,24.816,24.824,24.795,24.76,24.742,24.734,24.779,24.766,24.693,24.689,24.677,24.735,24.774,24.864,25.056,25.225,25.506,25.756,26.175,26.557,26.884,27.098,27.425,27.675,27.938,28.059,28.154,28.195,28.158,28.076,27.886,27.79,27.818,27.956,27.923,28.146,28.221,28.549,28.751,29.018,29.327,29.726,30.01,30.075,30.211,30.265,30.429,30.264,30.15,29.89,29.789,29.563,29.121,28.865,28.658,28.409,28.041,27.923,27.878,27.924,27.932,27.918,27.917,27.901,27.762,27.637,27.568,27.386,27.175,26.954,26.686,26.466,26.293,26.113,26.022,25.912,25.705,25.484,25.284,25.142,25.057,24.947,24.904,24.909,24.845,24.792,24.828,24.919,25.017,25.095,25.147,25.133,25.146,25.042,24.929,24.898,24.833,24.777,24.717,24.638,24.552,24.549,24.52,24.553,24.628,24.638,24.731,24.837,24.894,24.994,25.121,25.358,25.499,25.732,25.948,26.195,26.452,26.578,26.697,26.767,26.832,26.732,26.703,26.568,26.431,26.226,25.893,25.707,25.529,25.337,25.116,25.031,24.974,24.914,24.924,24.972,25.069,25.108,25.2,25.348,25.421,25.292,25.117,25.014,24.865,24.741,24.687,24.682,24.761,24.746,24.777,24.836,25.11,25.377,25.582,25.696,25.774,25.885,25.773,25.707,25.65,25.695,25.594,25.337,25.281,25.254,25.33,25.398,25.567,25.877,26.181,26.439,26.719,27.069,27.348,27.596,27.942,28.36,28.783,29.178,29.55,30.044,30.434,30.849,31.301,31.857,32.034,31.983,32.142,32.137,32.17,32.111,32.161,32.197,31.829,31.498,31.433,31.254,30.765,30.443,30.116,29.717,29.289,28.89,28.737,28.538,28.025,27.773,27.563,27.206,26.857,26.721,26.578,26.477,26.45,26.452,26.552,26.68,26.927,26.954,27.063,27.301,27.616,27.798,28.081,28.623,29.08,29.676,30.405,31.684,32.9],"ma20":[23.9905,23.9135,23.8435,23.7985,23.7505,23.737,23.7275,23.6905,23.6885,23.6875,23.654,23.6115,23.557,23.484,23.4865,23.48,23.4855,23.5365,23.5795,23.6675,23.746,23.8565,23.9635,24.0595,24.123,24.16,24.2255,24.2945,24.337,24.3995,24.462,24.504,24.5465,24.6045,24.622,24.668,24.704,24.7075,24.74,24.7465,24.7795,24.7845,24.812,24.899,24.9795,25.1425,25.261,25.434,25.623,25.7805,25.9165,26.0995,26.2695,26.497,26.642,26.83,26.9755,27.1665,27.3165,27.385,27.444,27.6215,27.8155,27.9305,28.1025,28.1875,28.372,28.4545,28.547,28.6065,28.758,28.914,29.0155,29.067,29.2055,29.325,29.4065,29.4505,29.454,29.558,29.6445,29.5655,29.47,29.4345,29.337,29.235,29.0935,29.014,28.907,28.8605,28.7405,28.519,28.383,28.21,28.023,27.8045,27.6545,27.5265,27.439,27.309,27.192,27.105,27.007,26.892,26.7745,26.6365,26.435,26.2295,26.048,25.8715,25.7065,25.5985,25.511,25.4335,25.352,25.2665,25.2015,25.1505,25.1185,25.102,25.04,25.025,24.9755,24.887,24.845,24.8305,24.848,24.867,24.8665,24.8495,24.841,24.833,24.7975,24.7785,24.768,24.782,24.807,24.8055,24.816,24.8365,24.9535,25.0095,25.1425,25.288,25.4165,25.5915,25.7075,25.7955,25.8805,25.9765,26.045,26.101,26.15,26.1895,26.2105,26.1725,26.1425,26.113,26.052,25.974,25.8815,25.8385,25.741,25.6775,25.599,25.481,25.4075,25.3645,25.3425,25.2685,25.1615,25.0455,24.964,24.8945,24.8565,24.878,24.895,24.9805,25.047,25.099,25.064,25.1135,25.1955,25.2235,25.2185,25.2305,25.2835,25.267,25.2265,25.2135,25.2655,25.352,25.357,25.4315,25.475,25.552,25.6415,25.67,25.792,25.9155,26.067,26.1565,26.203,26.3145,26.425,26.636,26.879,27.175,27.5275,27.8655,28.2415,28.5765,28.959,29.3245,29.7265,29.988,30.1715,30.4625,30.6575,30.86,31.0775,31.2975,31.523,31.565,31.6775,31.7335,31.6185,31.4535,31.29,31.143,30.914,30.725,30.5435,30.283,30.018,29.729,29.5135,29.164,28.8245,28.4865,28.219,27.9335,27.6835,27.5935,27.495,27.2885,27.2265,27.245,27.08,26.96,27.011,27.097,27.1375,27.2655,27.5375,27.816,28.178,28.666,29.319,29.9815],"ma60":[25.191,25.093,25.0127,24.9298,24.8657,24.8085,24.7473,24.6837,24.6265,24.5683,24.495,24.44,24.4263,24.4165,24.4062,24.3782,24.3505,24.3262,24.3002,24.2962,24.2917,24.2912,24.2792,24.2732,24.2598,24.2512,24.2458,24.2477,24.2545,24.2538,24.237,24.2218,24.2015,24.1905,24.1707,24.1615,24.1483,24.1435,24.1482,24.1583,24.172,24.1848,24.2063,24.2523,24.2843,24.3465,24.4047,24.473,24.5495,24.6225,24.6775,24.7383,24.791,24.8618,24.9168,24.9927,25.055,25.1368,25.212,25.2663,25.3232,25.4208,25.5303,25.6297,25.735,25.83,25.9528,26.061,26.169,26.2622,26.3788,26.5058,26.6105,26.7228,26.8232,26.941,27.0287,27.1082,27.1702,27.2298,27.2893,27.3238,27.3658,27.4213,27.473,27.5217,27.5755,27.6342,27.6923,27.7492,27.805,27.8442,27.8893,27.9247,27.9568,27.9865,28.0122,28.0478,28.0698,28.084,28.0935,28.0973,28.0975,28.0857,28.0713,28.0197,27.9668,27.8993,27.834,27.7795,27.735,27.6772,27.6365,27.5702,27.5268,27.4653,27.4208,27.3758,27.3372,27.323,27.2922,27.2318,27.1508,27.0712,26.9855,26.9007,26.7922,26.7035,26.6072,26.5272,26.4293,26.3168,26.2305,26.1407,26.0477,25.951,25.8877,25.8275,25.7912,25.7492,25.7285,25.7132,25.7083,25.689,25.6787,25.6862,25.6635,25.6307,25.5983,25.5658,25.5308,25.5108,25.4862,25.4672,25.4435,25.407,25.3837,25.3563,25.3288,25.3042,25.2917,25.291,25.2863,25.2842,25.2868,25.301,25.321,25.3423,25.3632,25.3648,25.3492,25.3265,25.3038,25.2875,25.2783,25.2775,25.2815,25.2997,25.305,25.3032,25.2997,25.3205,25.3597,25.3963,25.4113,25.4343,25.4662,25.4757,25.4832,25.4862,25.4907,25.4995,25.4903,25.5052,25.514,25.5342,25.5597,25.5878,25.6303,25.6628,25.6708,25.7028,25.7132,25.7385,25.7475,25.7825,25.8567,25.9355,26.0322,26.1158,26.2228,26.3247,26.4267,26.5502,26.686,26.806,26.9027,27.0377,27.1655,27.2915,27.4028,27.5225,27.6405,27.701,27.7737,27.8667,27.927,27.9652,28.0147,28.074,28.1403,28.2178,28.2865,28.3463,28.4065,28.423,28.4422,28.4322,28.4247,28.4207,28.4545,28.4625,28.4698,28.491,28.5325,28.5527,28.5747,28.6245,28.6325,28.6562,28.7222,28.7995,28.88,28.9577,29.094,29.1777,29.2877,29.4308,29.6003,29.776]},"boll":{"upper":[25.0052,25.0354,25.0768,25.1125,25.0608,25.0431,25.0356,24.9617,24.9577,24.9562,24.9052,24.7663,24.5901,24.3343,24.3444,24.3207,24.339,24.4408,24.5141,24.7246,24.8548,25.0097,25.0674,25.0722,25.1009,25.1285,25.2027,25.2968,25.356,25.4444,25.431,25.4425,25.3995,25.2694,25.2569,25.2405,25.1964,25.1875,25.1471,25.1644,25.2666,25.2832,25.3782,25.8111,26.0403,26.7091,27.07,27.7234,28.2797,28.6587,28.8437,29.1617,29.3351,29.6882,29.7204,29.9191,29.9303,29.8924,29.8266,29.7038,29.6053,29.562,29.5983,29.6441,29.7769,29.9441,30.443,30.666,30.9268,31.013,31.2396,31.6614,31.7556,31.8491,31.9188,32.1403,32.1167,32.1044,32.0993,31.8465,31.5672,31.7534,31.8571,31.8831,31.8978,31.9348,31.7166,31.6003,31.4195,31.3662,31.1487,30.6685,30.5022,30.2984,30.0409,29.3567,29.1831,29.0077,29.0313,28.979,28.9119,29.0035,29.0383,28.9345,28.889,28.9302,28.8787,28.6143,28.3154,27.8796,27.4841,27.2895,27.032,26.8679,26.7326,26.5128,26.36,26.1656,26.0459,25.9891,25.8666,25.8393,25.8103,25.7494,25.6969,25.7074,25.6769,25.6757,25.6757,25.6627,25.6596,25.6515,25.5641,25.5319,25.5252,25.5636,25.6436,25.6377,25.6864,25.7861,26.2865,26.4442,26.8085,27.0291,27.281,27.6576,27.7602,27.841,27.8759,27.9076,27.8748,27.8361,27.7821,27.7171,27.6596,27.7542,27.7959,27.8379,27.9133,27.9779,27.858,27.8254,27.665,27.5281,27.3364,26.8882,26.6899,26.5385,26.4536,26.2328,26.245,26.2823,26.2243,26.1776,26.1672,26.178,26.204,26.4674,26.5555,26.5792,26.5706,26.7115,26.9492,27.0207,27.0132,27.0347,27.1515,27.1247,27.058,27.0527,27.0048,26.9056,26.895,26.8653,26.8137,26.9307,27.1511,27.2641,27.7411,28.0512,28.1952,28.4597,28.5899,28.8878,29.0214,29.6195,30.4586,31.1712,31.9631,32.452,33.0228,33.4221,33.5641,33.9717,34.2419,34.3184,34.2891,34.4895,34.6121,34.6314,34.5326,34.5159,34.3038,34.1767,33.7326,33.6504,33.8923,34.2164,34.2399,34.3058,34.3271,34.2939,34.2323,33.9966,33.6246,33.6647,33.6803,33.3051,33.0466,32.7486,32.2747,31.5235,30.6977,30.5215,30.2381,29.5041,29.3245,29.377,29.1784,28.96,29.1457,29.535,29.6737,30.142,31.4378,31.997,33.0031,34.3726,36.2219,37.6568],"middle":[23.9905,23.9135,23.8435,23.7985,23.7505,23.737,23.7275,23.6905,23.6885,23.6875,23.654,23.6115,23.557,23.484,23.4865,23.48,23.4855,23.5365,23.5795,23.6675,23.746,23.8565,23.9635,24.0595,24.123,24.16,24.2255,24.2945,24.337,24.3995,24.462,24.504,24.5465,24.6045,24.622,24.668,24.704,24.7075,24.74,24.7465,24.7795,24.7845,24.812,24.899,24.9795,25.1425,25.261,25.434,25.623,25.7805,25.9165,26.0995,26.2695,26.497,26.642,26.83,26.9755,27.1665,27.3165,27.385,27.444,27.6215,27.8155,27.9305,28.1025,28.1875,28.372,28.4545,28.547,28.6065,28.758,28.914,29.0155,29.067,29.2055,29.325,29.4065,29.4505,29.454,29.558,29.6445,29.5655,29.47,29.4345,29.337,29.235,29.0935,29.014,28.907,28.8605,28.7405,28.519,28.383,28.21,28.023,27.8045,27.6545,27.5265,27.439,27.309,27.192,27.105,27.007,26.892,26.7745,26.6365,26.435,26.2295,26.048,25.8715,25.7065,25.5985,25.511,25.4335,25.352,25.2665,25.2015,25.1505,25.1185,25.102,25.04,25.025,24.9755,24.887,24.845,24.8305,24.848,24.867,24.8665,24.8495,24.841,24.833,24.7975,24.7785,24.768,24.782,24.807,24.8055,24.816,24.8365,24.9535,25.0095,25.1425,25.288,25.4165,25.5915,25.7075,25.7955,25.8805,25.9765,26.045,26.101,26.15,26.1895,26.2105,26.1725,26.1425,26.113,26.052,25.974,25.8815,25.8385,25.741,25.6775,25.599,25.481,25.4075,25.3645,25.3425,25.2685,25.1615,25.0455,24.964,24.8945,24.8565,24.878,24.895,24.9805,25.047,25.099,25.064,25.1135,25.1955,25.2235,25.2185,25.2305,25.2835,25.267,25.2265,25.2135,25.2655,25.352,25.357,25.4315,25.475,25.552,25.6415,25.67,25.792,25.9155,26.067,26.1565,26.203,26.3145,26.425,26.636,26.879,27.175,27.5275,27.8655,28.2415,28.5765,28.959,29.3245,29.7265,29.988,30.1715,30.4625,30.6575,30.86,31.0775,31.2975,31.523,31.565,31.6775,31.7335,31.6185,31.4535,31.29,31.143,30.914,30.725,30.5435,30.283,30.018,29.729,29.5135,29.164,28.8245,28.4865,28.219,27.9335,27.6835,27.5935,27.495,27.2885,27.2265,27.245,27.08,26.96,27.011,27.097,27.1375,27.2655,27.5375,27.816,28.178,28.666,29.319,29.9815],"lower":[22.9758,22.7916,22.6102,22.4845,22.4402,22.4309,22.4194,22.4193,22.4193,22.4188,22.4028,22.4567,22.5239,22.6337,22.6286,22.6393,22.632,22.6322,22.6449,22.6104,22.6372,22.7033,22.8596,23.0468,23.1451,23.1915,23.2483,23.2922,23.318,23.3546,23.493,23.5655,23.6935,23.9396,23.9871,24.0955,24.2116,24.2275,24.3329,24.3286,24.2924,24.2858,24.2458,23.9869,23.9187,23.5759,23.452,23.1446,22.9663,22.9023,22.9893,23.0373,23.2039,23.3058,23.5636,23.7409,24.0207,24.4406,24.8064,25.0662,25.2827,25.681,26.0327,26.2169,26.4281,26.4309,26.301,26.243,26.1672,26.2,26.2764,26.1666,26.2754,26.2849,26.4922,26.5097,26.6963,26.7966,26.8087,27.2695,27.7218,27.3776,27.0829,26.9859,26.7762,26.5352,26.4704,26.4277,26.3945,26.3548,26.3323,26.3695,26.2638,26.1216,26.0051,26.2523,26.1259,26.0453,25.8467,25.639,25.4721,25.2065,24.9757,24.8495,24.66,24.3428,23.9913,23.8447,23.7806,23.8634,23.9289,23.9075,23.99,23.9991,23.9714,24.0202,24.043,24.1354,24.1911,24.2149,24.2134,24.2107,24.1407,24.0246,23.9931,23.9536,24.0191,24.0583,24.0573,24.0363,24.0224,24.0145,24.0309,24.0251,24.0108,24.0004,23.9704,23.9733,23.9456,23.8869,23.6205,23.5748,23.4765,23.5469,23.552,23.5254,23.6548,23.75,23.8851,24.0454,24.2152,24.3659,24.5179,24.6619,24.7614,24.5908,24.4891,24.3881,24.1907,23.9701,23.905,23.8516,23.817,23.8269,23.8616,24.0738,24.1251,24.1905,24.2314,24.3042,24.078,23.8087,23.7037,23.6114,23.5458,23.578,23.586,23.4936,23.5385,23.6188,23.5574,23.5155,23.4418,23.4263,23.4238,23.4263,23.4155,23.4093,23.395,23.3743,23.5262,23.7984,23.819,23.9977,24.1363,24.1733,24.1319,24.0759,23.8429,23.7798,23.9388,23.8533,23.8161,23.7412,23.8286,23.6525,23.2994,23.1788,23.0919,23.279,23.4602,23.7309,24.3539,24.6773,25.2111,25.6576,26.0539,26.4355,26.7029,27.0886,27.6224,28.0791,28.7422,28.9533,29.6224,29.8166,29.3447,28.6906,28.3401,27.9802,27.5009,27.1561,26.8547,26.5694,26.4114,25.7933,25.3467,25.0229,24.6024,24.2244,24.1633,24.3435,24.6693,24.6655,24.7519,25.0729,25.1285,25.113,24.9816,24.96,24.8763,24.659,24.6013,24.389,23.6372,23.635,23.3529,22.9594,22.4161,22.3062]},"macd":{"dif":[-0.4616,-0.5014,-0.5349,-0.5479,-0.5103,-0.444,-0.3981,-0.3504,-0.2828,-0.2377,-0.2276,-0.186,-0.1704,-0.1778,-0.1193,-0.0865,-0.0559,-0.0144,0.011,0.0866,0.1306,0.1914,0.2233,0.2354,0.2318,0.2152,0.2341,0.2589,0.2595,0.2777,0.2609,0.2432,0.2082,0.1816,0.1562,0.1657,0.1593,0.1174,0.1223,0.1391,0.1786,0.1907,0.2204,0.3257,0.3838,0.5453,0.629,0.7871,0.9116,0.9692,0.9411,0.9817,0.9633,1.0328,0.9414,0.9589,0.8818,0.8489,0.7871,0.6141,0.4842,0.5493,0.6427,0.6671,0.7488,0.7859,0.9281,0.9659,1.01,0.9509,0.9783,1.0692,1.0022,0.9534,0.9092,0.9335,0.8016,0.6667,0.4625,0.3419,0.2284,0.0451,-0.0767,-0.117,-0.1759,-0.2456,-0.2384,-0.1941,-0.1756,-0.1447,-0.1516,-0.2366,-0.2901,-0.3726,-0.4506,-0.4874,-0.5418,-0.5654,-0.6038,-0.6502,-0.6735,-0.728,-0.7576,-0.745,-0.7594,-0.8202,-0.9008,-0.9242,-0.912,-0.8698,-0.8411,-0.7995,-0.7147,-0.668,-0.6478,-0.6118,-0.575,-0.5046,-0.4396,-0.3821,-0.3997,-0.3779,-0.4067,-0.4597,-0.4546,-0.4597,-0.4497,-0.4049,-0.3763,-0.3536,-0.3325,-0.3019,-0.2753,-0.2529,-0.2428,-0.1803,-0.1101,-0.0611,0.0012,0.0675,0.2057,0.2453,0.3462,0.4062,0.4628,0.5618,0.5476,0.5175,0.472,0.4445,0.3733,0.3037,0.2337,0.1594,0.0596,-0.0617,-0.124,-0.1778,-0.2451,-0.3046,-0.2839,-0.2517,-0.2379,-0.1854,-0.1516,-0.1267,-0.12,-0.0776,-0.0259,-0.0545,-0.1736,-0.2888,-0.3328,-0.361,-0.3687,-0.3178,-0.2496,-0.0904,-0.0221,-0.001,-0.0595,0.0429,0.1602,0.2032,0.1723,0.1701,0.2175,0.1772,0.1228,0.0533,0.0046,-0.0025,-0.095,-0.0531,-0.0587,0.0436,0.168,0.2691,0.4369,0.5332,0.5722,0.6449,0.6634,0.727,0.7047,0.8634,1.0801,1.2471,1.4332,1.5139,1.627,1.6627,1.6606,1.7261,1.777,1.6785,1.5024,1.5244,1.4629,1.3797,1.2924,1.2619,1.2013,0.904,0.7094,0.643,0.413,0.1578,0.0279,-0.0965,-0.2567,-0.3498,-0.4179,-0.5064,-0.5581,-0.7485,-0.8517,-0.9595,-1.0785,-1.1754,-1.1318,-1.0609,-0.9589,-0.8489,-0.718,-0.6854,-0.5922,-0.4542,-0.5619,-0.5904,-0.397,-0.1556,-0.0365,0.157,0.5484,0.7029,0.9867,1.3621,1.8584,2.2253],"dea":[-0.3877,-0.4105,-0.4354,-0.4579,-0.4684,-0.4635,-0.4504,-0.4304,-0.4009,-0.3682,-0.3401,-0.3093,-0.2815,-0.2608,-0.2325,-0.2033,-0.1738,-0.1419,-0.1113,-0.0718,-0.0313,0.0132,0.0553,0.0913,0.1194,0.1386,0.1577,0.1779,0.1942,0.2109,0.2209,0.2254,0.2219,0.2139,0.2023,0.195,0.1879,0.1738,0.1635,0.1586,0.1626,0.1682,0.1787,0.2081,0.2432,0.3036,0.3687,0.4524,0.5442,0.6292,0.6916,0.7496,0.7923,0.8404,0.8606,0.8803,0.8806,0.8742,0.8568,0.8083,0.7435,0.7046,0.6922,0.6872,0.6995,0.7168,0.759,0.8004,0.8423,0.864,0.8869,0.9234,0.9391,0.942,0.9354,0.935,0.9083,0.86,0.7805,0.6928,0.5999,0.489,0.3758,0.2773,0.1866,0.1002,0.0325,-0.0129,-0.0454,-0.0653,-0.0825,-0.1133,-0.1487,-0.1935,-0.2449,-0.2934,-0.3431,-0.3875,-0.4308,-0.4747,-0.5145,-0.5572,-0.5973,-0.6268,-0.6533,-0.6867,-0.7295,-0.7685,-0.7972,-0.8117,-0.8176,-0.814,-0.7941,-0.7689,-0.7447,-0.7181,-0.6895,-0.6525,-0.6099,-0.5644,-0.5314,-0.5007,-0.4819,-0.4775,-0.4729,-0.4703,-0.4662,-0.4539,-0.4384,-0.4214,-0.4036,-0.3833,-0.3617,-0.3399,-0.3205,-0.2925,-0.256,-0.217,-0.1734,-0.1252,-0.059,0.0019,0.0707,0.1378,0.2028,0.2746,0.3292,0.3669,0.3879,0.3992,0.394,0.376,0.3475,0.3099,0.2598,0.1955,0.1316,0.0697,0.0068,-0.0555,-0.1012,-0.1313,-0.1526,-0.1592,-0.1577,-0.1515,-0.1452,-0.1317,-0.1105,-0.0993,-0.1141,-0.1491,-0.1858,-0.2209,-0.2504,-0.2639,-0.261,-0.2269,-0.186,-0.149,-0.1311,-0.0963,-0.045,0.0047,0.0382,0.0646,0.0952,0.1116,0.1138,0.1017,0.0823,0.0653,0.0333,0.016,0.0011,0.0096,0.0412,0.0868,0.1568,0.2321,0.3001,0.3691,0.4279,0.4877,0.5311,0.5976,0.6941,0.8047,0.9304,1.0471,1.1631,1.263,1.3425,1.4192,1.4908,1.5283,1.5231,1.5234,1.5113,1.485,1.4465,1.4095,1.3679,1.2751,1.162,1.0582,0.9291,0.7749,0.6255,0.4811,0.3335,0.1969,0.0739,-0.0422,-0.1453,-0.266,-0.3831,-0.4984,-0.6144,-0.7266,-0.8076,-0.8583,-0.8784,-0.8725,-0.8416,-0.8103,-0.7667,-0.7042,-0.6757,-0.6587,-0.6063,-0.5162,-0.4203,-0.3048,-0.1342,0.0333,0.2239,0.4516,0.7329,1.0314],"hist":[-0.1477,-0.1819,-0.1991,-0.1801,-0.0839,0.039,0.1046,0.16,0.2362,0.2611,0.225,0.2466,0.2222,0.1659,0.2263,0.2335,0.2359,0.255,0.2447,0.3168,0.3237,0.3563,0.3361,0.2883,0.2249,0.1533,0.1528,0.162,0.1305,0.1336,0.08,0.0356,-0.0275,-0.0646,-0.0922,-0.0586,-0.0571,-0.1128,-0.0824,-0.039,0.032,0.045,0.0835,0.2353,0.2811,0.4834,0.5206,0.6694,0.7347,0.68,0.499,0.4642,0.3418,0.3847,0.1616,0.1572,0.0025,-0.0507,-0.1394,-0.3884,-0.5184,-0.3106,-0.0991,-0.0403,0.0985,0.1382,0.338,0.3309,0.3353,0.1737,0.1828,0.2917,0.1262,0.0229,-0.0525,-0.0031,-0.2136,-0.3866,-0.636,-0.7018,-0.743,-0.8877,-0.905,-0.7885,-0.7251,-0.6916,-0.5417,-0.3626,-0.2604,-0.1589,-0.1381,-0.2465,-0.2828,-0.3583,-0.4114,-0.388,-0.3974,-0.3558,-0.3461,-0.3511,-0.3182,-0.3417,-0.3207,-0.2365,-0.2122,-0.2671,-0.3426,-0.3115,-0.2297,-0.1161,-0.047,0.029,0.1588,0.2017,0.1938,0.2126,0.2289,0.2959,0.3406,0.3645,0.2634,0.2457,0.1505,0.0355,0.0367,0.0211,0.0329,0.0981,0.1242,0.1357,0.1422,0.1627,0.1728,0.1741,0.1554,0.2243,0.2917,0.3119,0.3491,0.3854,0.5294,0.487,0.551,0.5367,0.52,0.5744,0.4368,0.3012,0.1682,0.0906,-0.0415,-0.1446,-0.2277,-0.3009,-0.4005,-0.5144,-0.5113,-0.4951,-0.5037,-0.4981,-0.3654,-0.2408,-0.1706,-0.0524,0.012,0.0496,0.0503,0.1082,0.1693,0.0897,-0.1188,-0.2795,-0.2939,-0.2803,-0.2365,-0.1078,0.0229,0.273,0.3277,0.2959,0.1431,0.2784,0.4104,0.3971,0.2683,0.2111,0.2447,0.1312,0.018,-0.0968,-0.1554,-0.1357,-0.2565,-0.1381,-0.1196,0.0681,0.2534,0.3645,0.5602,0.6022,0.5441,0.5516,0.4709,0.4784,0.3471,0.5317,0.772,0.8849,1.0056,0.9337,0.9278,0.7994,0.6361,0.6138,0.5724,0.3003,-0.0414,0.0021,-0.0968,-0.2106,-0.3082,-0.2953,-0.3332,-0.7422,-0.9051,-0.8303,-1.0323,-1.2341,-1.1951,-1.1552,-1.1805,-1.0933,-0.9837,-0.9286,-0.8254,-0.965,-0.9371,-0.9222,-0.9282,-0.8976,-0.6484,-0.4051,-0.1609,0.0472,0.2473,0.25,0.3491,0.5,0.2277,0.1366,0.4187,0.7212,0.7675,0.9235,1.3652,1.3393,1.5255,1.821,2.251,2.3878]},"rsi":{"rsi14":[35.3542,32.885,32.0537,33.6787,42.2696,47.7375,46.0513,47.339,51.8751,49.9109,45.2936,50.7599,47.6074,44.2758,54.2387,51.9312,52.5353,55.088,53.7537,61.5537,58.807,62.3271,59.6604,57.6297,55.592,53.4021,58.7738,60.5941,57.1946,60.3119,54.5525,54.2338,50.5746,51.1914,50.6806,56.726,53.9851,46.8362,54.1223,56.4817,60.7127,57.1241,60.4784,70.0356,65.8305,75.159,68.9807,74.9958,75.4872,70.8627,62.2104,67.2844,62.4731,68.3855,55.1702,61.1812,54.8455,57.0944,55.0223,46.9581,47.8661,58.2553,60.6407,57.6181,61.1475,59.7471,65.4206,60.6659,61.8747,55.9182,60.1679,63.7536,55.3583,56.1068,56.3557,59.9056,50.8881,49.6087,44.6831,47.4436,46.594,41.7237,43.2783,46.9776,45.2935,43.7906,48.0808,50.5523,49.2615,50.3304,47.8573,42.29,43.197,40.3105,39.1827,41.1182,38.949,40.3395,38.397,36.7234,37.4323,34.1911,34.8538,38.6255,35.9245,31.6771,28.9965,33.2435,36.0278,39.0918,37.8372,39.2373,45.217,42.3106,39.9409,41.8127,42.0558,47.2749,47.8497,48.0935,39.6998,44.5395,39.0826,35.785,42.0121,40.5464,41.8808,46.5767,45.2001,44.6921,44.5842,46.3965,46.2711,46.0034,44.2128,53.879,56.8519,55.4095,59.0175,61.5586,71.115,59.0725,65.8921,63.5125,64.8091,69.6487,57.4995,55.9284,53.9443,55.3929,49.8327,48.7045,47.264,45.2465,40.7826,36.6546,41.4698,40.8018,38.0001,37.0336,46.7565,48.4703,46.6511,51.9394,50.6161,50.1574,48.0472,53.3331,55.7059,45.7906,36.0897,34.1725,40.3183,40.6498,42.1494,49.1712,52.1114,61.9698,55.1461,51.6579,44.6798,56.9929,59.4616,55.1796,50.0484,51.901,55.6777,49.5267,47.9489,46.0062,46.5888,49.4523,42.5811,51.9482,48.9789,56.283,58.9479,59.282,64.4073,61.6461,58.9255,61.8371,58.9595,62.3907,56.6441,66.2972,70.2498,70.5979,73.0594,68.7156,71.2505,68.2039,67.1965,70.7819,71.5267,61.1714,55.3415,63.6288,59.5042,58.2888,57.8462,60.5102,58.8121,44.5717,47.3984,52.45,44.1661,41.2789,45.2228,44.2276,41.4226,43.2163,43.2669,41.2873,42.1425,34.9736,37.71,36.1084,34.1717,33.4929,41.7759,43.4856,45.9361,47.3094,49.8258,44.7049,49.0229,52.8799,40.3915,43.602,54.7045,58.3137,54.3881,58.5607,66.5489,59.1345,64.1628,68.2169,72.6349,72.5951]},"kdj":{"k":[14.8522,11.2289,10.7928,14.6209,27.3198,48.4354,57.8668,66.0412,76.1843,80.2013,76.0166,80.8738,75.9498,55.334,66.926,67.5564,69.7688,74.8144,70.487,75.4282,74.9151,81.0545,81.3091,75.9115,68.9539,60.698,64.9301,72.6446,66.8058,74.0244,63.8795,52.9423,43.3594,38.046,33.6974,41.2821,42.3064,31.1612,36.9032,45.5699,57.6746,58.0196,63.905,71.2122,72.6717,77.8394,75.3526,81.7255,83.275,81.3559,73.9874,75.1697,70.4504,72.9911,52.629,51.5831,40.6863,39.7396,35.7238,24.4188,18.2603,32.7592,47.2848,52.5579,63.5374,68.9062,73.6755,72.1527,72.9361,67.2231,65.6826,71.0012,59.6694,53.5727,50.0829,56.0898,43.2361,35.5076,24.7979,22.8949,20.363,13.8415,11.3567,14.2245,15.442,15.5466,23.5477,43.4212,52.8749,62.8303,62.2202,44.8135,40.7627,30.6698,24.3113,22.9708,17.367,15.5635,11.0849,12.4661,15.2787,10.5689,10.3586,17.2577,16.4601,11.4684,7.9081,11.6767,19.1706,29.3616,33.0787,37.608,51.3401,58.1919,57.0594,59.9574,55.3274,65.1678,62.4623,61.086,42.2197,39.2576,26.3633,18.4724,21.2038,20.3581,21.4239,32.8455,38.4588,44.9101,52.6815,61.4207,63.9823,62.9163,57.9573,71.9715,80.6051,80.4448,82.5954,85.2523,89.1465,79.4545,83.7117,83.8848,83.2087,83.4725,70.7891,60.3133,45.8611,38.69,28.5822,25.5886,21.9317,17.1682,14.9749,10.5297,11.9378,12.9523,9.3839,9.8759,22.2702,33.9855,45.0255,60.8963,66.7746,68.4525,66.3797,72.9765,78.7436,55.7696,38.4728,27.6312,27.0949,27.1091,30.0774,39.7486,49.8091,57.4686,57.2652,54.106,45.0677,52.6853,61.2297,58.5312,48.9011,45.475,51.1365,44.7706,38.5971,34.5898,32.6489,37.1014,28.8278,39.9203,41.5843,60.6774,69.9674,74.2664,80.0907,81.2199,79.219,81.6865,78.7169,78.4039,69.1496,75.3008,79.4753,80.9655,83.5121,81.3342,81.227,78.8877,76.5897,80.6654,82.8489,67.3538,46.4712,54.8169,50.9568,46.5316,42.9373,45.8552,45.546,31.5895,26.0229,29.5422,23.4514,16.9288,21.1958,22.4638,18.8047,18.6023,19.9838,17.3283,21.996,16.7772,16.5018,13.1825,10.9831,8.1468,15.3969,24.6324,34.3198,50.0403,65.459,63.2841,69.6711,78.0416,54.9173,45.1312,63.4208,67.8646,65.6989,70.0323,80.0216,78.9301,82.29,87.967,89.8916,87.8494],"d":[24.4834,20.0652,16.9744,16.1899,19.8999,29.4117,38.8967,47.9449,57.358,64.9724,68.6538,72.7271,73.8013,67.6456,67.4057,67.4559,68.2269,70.4227,70.4441,72.1055,73.042,75.7129,77.5783,77.0227,74.3331,69.788,68.1687,69.6607,68.709,70.4808,68.2804,63.1677,56.5649,50.392,44.8271,43.6454,43.1991,39.1865,38.4254,40.8069,46.4294,50.2928,54.8302,60.2909,64.4178,68.8917,71.0453,74.6054,77.4953,78.7821,77.1839,76.5125,74.4918,73.9916,66.8707,61.7748,54.7453,49.7434,45.0702,38.1864,31.5444,31.9493,37.0611,42.2267,49.3303,55.8556,61.7956,65.248,67.8107,67.6148,66.9707,68.3142,65.4326,61.4793,57.6805,57.1503,52.5122,46.844,39.4953,33.9618,29.4289,24.2331,19.941,18.0355,17.171,16.6295,18.9356,27.0975,35.6899,44.7367,50.5645,48.6475,46.0193,40.9028,35.3723,31.2384,26.6146,22.9309,18.9822,16.8102,16.2997,14.3894,13.0458,14.4498,15.1199,13.9027,11.9045,11.8286,14.2759,19.3045,23.8959,28.4666,36.0911,43.458,47.9918,51.9804,53.0961,57.12,58.9007,59.6291,53.826,48.9699,41.4343,33.7804,29.5882,26.5115,24.8156,27.4922,31.1478,35.7352,41.384,48.0629,53.3694,56.5517,57.0202,62.004,68.2044,72.2845,75.7215,78.8984,82.3144,81.3611,82.1447,82.7247,82.886,83.0815,78.9841,72.7605,63.794,55.426,46.4781,39.5149,33.6538,28.1586,23.764,19.3526,16.881,15.5714,13.5089,12.2979,15.622,21.7432,29.5039,39.9681,48.9036,55.4199,59.0732,63.7076,68.7196,64.4029,55.7596,46.3834,39.9539,35.6723,33.8073,35.7878,40.4615,46.1305,49.8421,51.2634,49.1982,50.3605,53.9836,55.4995,53.3,50.6917,50.8399,48.8168,45.4102,41.8034,38.7519,38.2018,35.0771,36.6915,38.3224,45.7741,53.8385,60.6478,67.1288,71.8258,74.2902,76.7556,77.4094,77.7409,74.8771,75.0184,76.504,77.9912,79.8315,80.3324,80.6306,80.0496,78.8963,79.486,80.607,76.1892,66.2832,62.4611,58.6264,54.5948,50.709,49.091,47.9093,42.4694,36.9872,34.5055,30.8208,26.1902,24.5254,23.8382,22.1604,20.9744,20.6442,19.5389,20.3579,19.1643,18.2768,16.5787,14.7135,12.5246,13.482,17.1988,22.9058,31.9507,43.1201,49.8414,56.4513,63.6481,60.7378,55.5356,58.164,61.3975,62.8313,65.2317,70.1616,73.0844,76.153,80.091,83.3578,84.855],"j":[-4.4102,-6.4438,-1.5704,11.483,42.1595,86.4828,95.8069,102.2337,113.8369,110.659,90.742,97.1671,80.2466,30.7109,65.9665,67.7573,72.8526,83.5978,70.5726,82.0737,78.6613,91.7378,88.7707,73.6891,58.1955,42.5178,58.4529,78.6123,62.9992,81.1115,55.0777,32.4916,16.9483,13.3542,11.4379,36.5555,40.5209,15.1108,33.8588,55.0959,80.1649,73.4732,82.0545,93.0549,89.1794,95.7348,83.9673,95.9657,94.8346,86.5034,67.5945,72.4841,62.3677,70.99,24.1455,31.1998,12.5682,19.7319,17.031,-3.1164,-8.3079,34.379,67.732,73.2204,91.9515,95.0073,97.4355,85.9623,83.1869,66.4396,63.1063,76.3752,48.1429,37.7594,34.8878,53.9688,24.6839,12.8349,-4.5969,0.761,2.2313,-6.9417,-5.8117,6.6026,11.9841,13.3807,32.7718,76.0687,87.2448,99.0174,85.5315,37.1454,30.2497,10.2038,2.1892,6.4355,-1.1283,0.8287,-4.7098,3.7778,13.2367,2.9279,4.9841,22.8735,19.1405,6.5998,-0.0848,11.373,28.96,49.4758,51.4443,55.8908,81.8382,87.6596,75.1946,75.9116,59.7902,81.2634,69.5854,63.9996,19.0071,19.833,-3.7788,-12.1435,4.4351,8.0513,14.6405,43.552,53.081,63.2598,75.2765,88.1363,85.2083,75.6456,59.8314,91.9066,105.4067,96.7654,96.3432,97.96,102.8106,75.6413,86.8459,86.2049,83.854,84.2544,54.3993,35.419,9.9952,5.218,-7.2096,-2.2641,-1.5126,-4.8127,-2.6034,-7.1161,2.0515,7.7141,1.1339,5.0318,35.5665,58.4703,76.0685,102.7528,102.5166,94.5179,80.9928,91.5144,98.7916,38.5028,3.8993,-9.8733,1.3768,9.9827,22.6175,47.6702,68.5042,80.1447,72.1114,59.7912,36.8068,57.3347,75.7219,64.5948,40.1032,35.0416,51.7296,36.6782,24.9707,20.1626,20.4429,34.9007,16.3293,46.3779,48.108,90.484,102.2252,101.5036,106.0144,100.008,89.0767,91.5481,81.3319,79.7298,57.6945,75.8658,85.418,86.9142,90.8734,83.3379,82.4199,76.5637,71.9764,83.0242,87.3328,49.6829,6.8471,39.5285,35.6178,30.4053,27.3941,39.3834,40.8192,9.8296,4.0942,19.6155,8.7126,-1.594,14.5366,19.7152,12.0934,13.8583,18.6631,12.9071,25.2723,12.0029,12.9516,6.3901,3.5223,-0.6088,19.2265,39.4995,57.1477,86.2197,110.1368,90.1693,96.1106,106.8286,43.2763,24.3225,73.9344,80.7987,71.434,79.6337,99.7414,90.6214,94.564,103.7191,102.959,93.8382]}},"generated_at":"2026-07-14T07:23:46.729821Z"},"algorithmic":null}